Workbook

Sheet 2_清单企业基本信息
A1: 返回目录 | B1: 统一社会信用代码 | C1: 曾用名 | D1: 登记状态 | E1: 法定代表人 | F1: 注册资本 | G1: 实缴资本 | H1: 成立日期 | I1: 成立年限 | J1: 企业地址 | K1: 所属省份 | L1: 所属地区 | M1: 所属7大地理地区 | N1: 所属城市 | O1: 所属区县 | P1: 电话 | Q1: 更多电话 | R1: 邮箱 | S1: 更多邮箱 | T1: 企业（机构）类型 | U1: 纳税人识别号 | V1: 注册号 | W1: 组织机构代码 | X1: 参保人数 | Y1: 参保人数所属年报 | Z1: 营业期限 | AA1: 国标行业门类 | AB1: 国标行业大类 | AC1: 国标行业中类 | AD1: 国标行业小类 | AE1: 企业规模 | AF1: 英文名 | AG1: 官网 | AH1: 通信地址 | AI1: 企业简介 | AJ1: 经营范围 | AK1: 登记机关 | AL1: 纳税人资质
A2: 上海科望饲料有限公司 | B2: - | C2: - | D2: 吊销（2016-12-23） | E2: 许培玉 | F2: 200万元 | G2: 200万元 | H2: 2013-03-06 | I2: =DATEDIF(H2, TODAY(), "Y") -> 12 | J2: 上海市宝山区同济支路65号A725室 | K2: 上海市 | L2: =VLOOKUP(K2,[1]中国省份_标准!$B$2:$F$35,4,FALSE) -> 东部地区 | M2: =VLOOKUP(K2,[1]中国省份_标准!$B$2:$F$35,5,FALSE) -> 华东地区 | N2: 上海市 | O2: 宝山区 | P2: 021-57781980 | Q2: - | R2: - | S2: - | T2: 有限责任公司（自然人投资或控股） | U2: 310113063703205 | V2: 310113001029706 | W2: - | X2: - | Y2: - | Z2: 2013-03-06 至 2023-03-05 | AA2: 租赁和商务服务业 | AB2: 商务服务业 | AC2: 咨询与调查 | AD2: - | AE2: S(小型) | AF2: Shanghai PST Feedstuff Co., Ltd. | AG2: - | AH2: - | AI2: 上海科望饲料有限公司成立于2013-03-06，法定代表人为许培玉，注册资本为200万元，企业注册地址位于上海市宝山区同济支路65号A725室，所属行业为商务服务业，经营范围包含：饲料销售；饲料科技专业领域的技术咨询、技术服务；实业投资。【企业经营涉及行政许可的，凭许可证件经营】。企业当前经营状态为吊销。 | AJ2: 饲料销售；饲料科技专业领域的技术咨询、技术服务；实业投资。【企业经营涉及行政许可的，凭许可证件经营】 | AK2: 宝山区市场监督管理局 | AL2: -
A3: 中国石化销售股份有限公司山东菏泽石油分公司 | B3: 913717007248126452 | C3: 中国石化销售有限公司山东菏泽石油分公司, 中国石油化工股份有限公司山东菏泽石油分公司 | D3: 在业 | E3: 杨凯 | F3: - | G3: - | H3: 2000-07-13 | I3: =DATEDIF(H3, TODAY(), "Y") -> 25 | J3: 菏泽市牡丹路568号 | K3: 山东省 | L3: =VLOOKUP(K3,[1]中国省份_标准!$B$2:$F$35,4,FALSE) -> 东部地区 | M3: =VLOOKUP(K3,[1]中国省份_标准!$B$2:$F$35,5,FALSE) -> 华东地区 | N3: 菏泽市 | O3: 牡丹区 | P3: 0530-5635550 | Q3: 0530-5635552 | R3: zshhzfgs@163.com | S3: ssh1961@126.com;hzsinopec@163.com | T3: 外商投资企业分公司 | U3: 913717007248126452 | V3: 371700119016532 | W3: 72481264-5 | X3: 0 | Y3: 2024年报 | Z3: 2000-07-13 至 无固定期限 | AA3: 批发和零售业 | AB3: 零售业 | AC3: 汽车、摩托车、零配件和燃料及其他动力销售 | AD3: 机动车燃油零售 | AE3: - | AF3: Sinopec Sales Co., Ltd. Shandong Heze Petroleum Branch | AG3: - | AH3: - | AI3: 中国石化销售股份有限公司山东菏泽石油分公司成立于2000-07-13，负责人为杨凯，统一社会信用代码为913717007248126452，企业注册地址位于菏泽市牡丹路568号，所属行业为零售业，经营范围包含：许可项目：危险化学品经营；成品油零售；燃气经营；燃气汽车加气经营；成品油零售（不含危险化学品）；成品油批发；成品油仓储；危险化学品仓储；食品销售；餐饮服务；第三类医疗器械经营；出版物零售；农药零售；药品零售；林木种子生产经营；旅游业务；发电业务、输电业务、供（配）电业务；保险代理业务；供电业务；住宿服务；石油、天然气管道储运；烟草制品零售；电子烟零售。（依法须经批准的项目，经相关部门批准后方可开展经营活动，具体经营项目以相关部门批准文件或许可证件为准）一般项目：成品油批发（不含危险化学品）；成品油仓储（不含危险化学品）；新能源汽车整车销售；汽车销售；集中式快速充电站；机动车充电销售；新能源汽车电附件销售；新能源汽车换电设施销售；电池销售；站用加氢及储氢设施销售；电动汽车充电基础设施运营；食品销售（仅销售预包装食品）；婴幼儿配方乳粉及其他婴幼儿配方食品销售；工艺美术品及礼仪用品销售（象牙及其制品除外）；润滑油销售；石油制品销售（不含危险化学品）；专用化学产品销售（不含危险化学品）；化工产品销售（不含许可类化工产品）；洗车服务；汽车零配件零售；轮胎销售；汽车装饰用品销售；智能车载设备销售；化肥销售；摩托车及零配件零售；五金产品零售；家用电器销售；针纺织品销售；日用品销售；互联网销售（除销售需要许可的商品）；化妆品零售；电子产品销售；办公用品销售；户外用品销售；体育用品及器材零售；工艺美术品及收藏品零售（象牙及其制品除外）；建筑材料销售；信息咨询服务（不含许可类信息咨询服务）；农用薄膜销售；食用农产品零售；畜牧渔业饲料销售；建筑装饰材料销售；广告发布；广告制作；文具用品零售；广告设计、代理；品牌管理；单用途商业预付卡代理销售；住房租赁；非居住房地产租赁；票务代理服务；旅客票务代理；居民日常生活服务；销售代理；煤炭及制品销售；机动车修理和维护；第一类医疗器械销售；教育咨询服务（不含涉许可审批的教育培训活动）；产业用纺织制成品销售；保健食品（预包装）销售；日用百货销售；母婴用品销售；五金产品批发；特种劳动防护用品销售；建筑用金属配件销售；家用电器零配件销售；劳动保护用品销售；美发饰品销售；洗染服务；计算机软硬件及辅助设备零售；玩具、动漫及游艺用品销售；服装服饰零售；办公设备耗材销售；特种设备销售；日用口罩（非医用）销售；新鲜水果零售；新鲜蔬菜零售；照明器具销售；农副产品销售；礼品花卉销售；食用农产品批发；第二类医疗器械销售；体育用品及器材批发；办公设备销售；机械设备销售。（除依法须经批准的项目外，凭营业执照依法自主开展经营活动）。企业当前经营状态为在业。 | AJ3: 许可项目：危险化学品经营；成品油零售；燃气经营；燃气汽车加气经营；成品油零售（不含危险化学品）；成品油批发；成品油仓储；危险化学品仓储；食品销售；餐饮服务；第三类医疗器械经营；出版物零售；农药零售；药品零售；林木种子生产经营；旅游业务；发电业务、输电业务、供（配）电业务；保险代理业务；供电业务；住宿服务；石油、天然气管道储运；烟草制品零售；电子烟零售。（依法须经批准的项目，经相关部门批准后方可开展经营活动，具体经营项目以相关部门批准文件或许可证件为准）一般项目：成品油批发（不含危险化学品）；成品油仓储（不含危险化学品）；新能源汽车整车销售；汽车销售；集中式快速充电站；机动车充电销售；新能源汽车电附件销售；新能源汽车换电设施销售；电池销售；站用加氢及储氢设施销售；电动汽车充电基础设施运营；食品销售（仅销售预包装食品）；婴幼儿配方乳粉及其他婴幼儿配方食品销售；工艺美术品及礼仪用品销售（象牙及其制品除外）；润滑油销售；石油制品销售（不含危险化学品）；专用化学产品销售（不含危险化学品）；化工产品销售（不含许可类化工产品）；洗车服务；汽车零配件零售；轮胎销售；汽车装饰用品销售；智能车载设备销售；化肥销售；摩托车及零配件零售；五金产品零售；家用电器销售；针纺织品销售；日用品销售；互联网销售（除销售需要许可的商品）；化妆品零售；电子产品销售；办公用品销售；户外用品销售；体育用品及器材零售；工艺美术品及收藏品零售（象牙及其制品除外）；建筑材料销售；信息咨询服务（不含许可类信息咨询服务）；农用薄膜销售；食用农产品零售；畜牧渔业饲料销售；建筑装饰材料销售；广告发布；广告制作；文具用品零售；广告设计、代理；品牌管理；单用途商业预付卡代理销售；住房租赁；非居住房地产租赁；票务代理服务；旅客票务代理；居民日常生活服务；销售代理；煤炭及制品销售；机动车修理和维护；第一类医疗器械销售；教育咨询服务（不含涉许可审批的教育培训活动）；产业用纺织制成品销售；保健食品（预包装）销售；日用百货销售；母婴用品销售；五金产品批发；特种劳动防护用品销售；建筑用金属配件销售；家用电器零配件销售；劳动保护用品销售；美发饰品销售；洗染服务；计算机软硬件及辅助设备零售；玩具、动漫及游艺用品销售；服装服饰零售；办公设备耗材销售；特种设备销售；日用口罩（非医用）销售；新鲜水果零售；新鲜蔬菜零售；照明器具销售；农副产品销售；礼品花卉销售；食用农产品批发；第二类医疗器械销售；体育用品及器材批发；办公设备销售；机械设备销售。（除依法须经批准的项目外，凭营业执照依法自主开展经营活动） | AK3: 菏泽市市场监督管理局 | AL3: 一般纳税人
A4: 三门峡华宇商贸有限公司 | B4: 91411282MA9L4EBG3W | C4: 灵宝市华宇商贸有限公司 | D4: 存续 | E4: 刘菲菲 | F4: 20万元 | G4: 20万元 | H4: 2022-04-20 | I4: =DATEDIF(H4, TODAY(), "Y") -> 3 | J4: 河南省三门峡市经济开发区北环路开发区双创园C座304室 | K4: 河南省 | L4: =VLOOKUP(K4,[1]中国省份_标准!$B$2:$F$35,4,FALSE) -> 中部地区 | M4: =VLOOKUP(K4,[1]中国省份_标准!$B$2:$F$35,5,FALSE) -> 华中地区 | N4: 三门峡市 | O4: 河南三门峡经济开发区 | P4: 13503987212 | Q4: 15529655585 | R4: 1181745178@qq.com | S4: - | T4: 有限责任公司（自然人投资或控股） | U4: 91411282MA9L4EBG3W | V4: 411282000111660 | W4: MA9L4EBG-3 | X4: 0 | Y4: 2024年报 | Z4: 2022-04-20 至 无固定期限 | AA4: 批发和零售业 | AB4: 批发业 | AC4: 矿产品、建材及化工产品批发 | AD4: 建材批发 | AE4: XS(微型) | AF4: Sanmenxia Huayu Trading Co., Ltd. | AG4: - | AH4: - | AI4: 三门峡华宇商贸有限公司成立于2022-04-20，法定代表人为刘菲菲，注册资本为20万元，统一社会信用代码为91411282MA9L4EBG3W，企业注册地址位于河南省三门峡市经济开发区北环路开发区双创园C座304室，所属行业为批发业，经营范围包含：一般项目：建筑材料销售；金属矿石销售；非金属矿及制品销售；贵金属冶炼；非金属废料和碎屑加工处理；五金产品零售；办公用品销售；办公设备耗材销售；办公设备销售；计算机及办公设备维修；软件销售；电子产品销售；办公服务；计算机软硬件及辅助设备零售；农副产品销售；日用百货销售；食用农产品零售；水泥制品销售；再生资源回收（除生产性废旧金属）；再生资源加工；再生资源销售；金属材料销售；新型金属功能材料销售（除依法须经批准的项目外，凭营业执照依法自主开展经营活动）。企业当前经营状态为存续。 | AJ4: 一般项目：建筑材料销售；金属矿石销售；非金属矿及制品销售；贵金属冶炼；非金属废料和碎屑加工处理；五金产品零售；办公用品销售；办公设备耗材销售；办公设备销售；计算机及办公设备维修；软件销售；电子产品销售；办公服务；计算机软硬件及辅助设备零售；农副产品销售；日用百货销售；食用农产品零售；水泥制品销售；再生资源回收（除生产性废旧金属）；再生资源加工；再生资源销售；金属材料销售；新型金属功能材料销售（除依法须经批准的项目外，凭营业执照依法自主开展经营活动） | AK4: 三门峡市市场监督管理局经济开发区分局 | AL4: 一般纳税人
A5: 灵宝金硕矿产品有限公司 | B5: 91411282MA9M523B54 | C5: - | D5: 存续 | E5: 嵇磊磊 | F5: 10万元 | G5: - | H5: 2022-09-21 | I5: =DATEDIF(H5, TODAY(), "Y") -> 3 | J5: 河南省三门峡市灵宝市新华东路亚武西区31号楼1楼东商铺1号 | K5: 河南省 | L5: =VLOOKUP(K5,[1]中国省份_标准!$B$2:$F$35,4,FALSE) -> 中部地区 | M5: =VLOOKUP(K5,[1]中国省份_标准!$B$2:$F$35,5,FALSE) -> 华中地区 | N5: 三门峡市 | O5: 灵宝市 | P5: 15139858805 | Q5: 15139899330 | R5: 15139858805@139.com | S5: xueshixin1996@163.com | T5: 有限责任公司（自然人投资或控股） | U5: 91411282MA9M523B54 | V5: 411282000117881 | W5: MA9M523B-5 | X5: 0 | Y5: 2024年报 | Z5: 2022-09-21 至 无固定期限 | AA5: 批发和零售业 | AB5: 批发业 | AC5: 矿产品、建材及化工产品批发 | AD5: 金属及金属矿批发 | AE5: XS(微型) | AF5: Lingbao Jinshuo Mineral Products Co., Ltd. | AG5: - | AH5: - | AI5: 灵宝金硕矿产品有限公司成立于2022-09-21，法定代表人为嵇磊磊，注册资本为10万元，统一社会信用代码为91411282MA9M523B54，企业注册地址位于河南省三门峡市灵宝市新华东路亚武西区31号楼1楼东商铺1号，所属行业为批发业，经营范围包含：一般项目：贵金属冶炼；常用有色金属冶炼；非金属矿及制品销售；金属材料销售；金属矿石销售（除依法须经批准的项目外，凭营业执照依法自主开展经营活动）。企业当前经营状态为存续。 | AJ5: 一般项目：贵金属冶炼；常用有色金属冶炼；非金属矿及制品销售；金属材料销售；金属矿石销售（除依法须经批准的项目外，凭营业执照依法自主开展经营活动） | AK5: 灵宝市市场监督管理局 | AL5: 一般纳税人
A6: 重庆钢铁股份有限公司四川销售分公司 | B6: 91510100MA6CCTJ8XN | C6: - | D6: 存续 | E6: 章远杰 | F6: - | G6: - | H6: 2018-04-08 | I6: =DATEDIF(H6, TODAY(), "Y") -> 7 | J6: 四川省成都市锦江区东华正街42号广电士百达国际大厦28层E区 | K6: 四川省 | L6: =VLOOKUP(K6,[1]中国省份_标准!$B$2:$F$35,4,FALSE) -> 西部地区 | M6: =VLOOKUP(K6,[1]中国省份_标准!$B$2:$F$35,5,FALSE) -> 西南地区 | N6: 成都市 | O6: 锦江区 | P6: 15730328191 | Q6: - | R6: 853175592@qq.com | S6: - | T6: 分公司 | U6: 91510100MA6CCTJ8XN | V6: - | W6: MA6CCTJ8-X | X6: 0 | Y6: 2024年报 | Z6: 2018-04-08 至 无固定期限 | AA6: 批发和零售业 | AB6: 批发业 | AC6: 矿产品、建材及化工产品批发 | AD6: 建材批发 | AE6: - | AF6: Chongqing Iron and Steel Co., Ltd. Sichuan Sales Branch | AG6: - | AH6: 成都市武侯区桐梓林中路8号梓桐苑1栋1单元5号 | AI6: 重庆钢铁股份有限公司四川销售分公司成立于2018-04-08，负责人为章远杰，统一社会信用代码为91510100MA6CCTJ8XN，企业注册地址位于四川省成都市锦江区东华正街42号广电士百达国际大厦28层E区，所属行业为批发业，经营范围包含：销售总公司生产的板材、型材、线材、棒材、钢坯、薄板带、生铁及水渣、钢渣、废钢。（以上经营范围不含国家法律法规限制或禁止的项目，涉及国家规定实施准入特别管理措施的除外，涉及许可证的凭相关许可证方可开展经营活动）。企业当前经营状态为存续。 | AJ6: 销售总公司生产的板材、型材、线材、棒材、钢坯、薄板带、生铁及水渣、钢渣、废钢。（以上经营范围不含国家法律法规限制或禁止的项目，涉及国家规定实施准入特别管理措施的除外，涉及许可证的凭相关许可证方可开展经营活动）。 | AK6: 成都市市场监督管理局 | AL6: 一般纳税人
A7: 抚顺市恒丰益体育运动木制地板厂 | B7: 91210421MA0U2UUU31 | C7: - | D7: 存续 | E7: 王恒 | F7: 100万元 | G7: - | H7: 2017-04-25 | I7: =DATEDIF(H7, TODAY(), "Y") -> 8 | J7: 辽宁省抚顺市抚顺县救兵镇五牛村 | K7: 辽宁省 | L7: =VLOOKUP(K7,[1]中国省份_标准!$B$2:$F$35,4,FALSE) -> 东北地区 | M7: =VLOOKUP(K7,[1]中国省份_标准!$B$2:$F$35,5,FALSE) -> 东北地区 | N7: 抚顺市 | O7: 抚顺县 | P7: 18741371555 | Q7: 13470563899;13700130752;13050170948;4006000247 | R7: 114261272@qq.com | S7: 2064948745@qq.com | T7: 个人独资企业 | U7: 91210421MA0U2UUU31 | V7: 210421003527830 | W7: MA0U2UUU-3 | X7: 14 | Y7: 2024年报 | Z7: *** 至 无固定期限 | AA7: 制造业 | AB7: 木材加工和木、竹、藤、棕、草制品业 | AC7: 木材加工 | AD7: - | AE7: XS(微型) | AF7: Fushun Hengfengyi Sports Wooden Flooring Factory | AG7: - | AH7: - | AI7: - | AJ7: 一般项目：地板制造；木材加工；地板销售；室内木门窗安装服务；家具安装和维修服务。（除依法须经批准的项目外，凭营业执照依法自主开展经营活动） | AK7: 抚顺县市场监督管理局 | AL7: 一般纳税人
A8: 崇州市旺达饲料有限公司 | B8: 91510184MA69RTFWXW | C8: - | D8: 存续 | E8: 朱桂英 | F8: 3000万元 | G8: 3000万元 | H8: 2020-04-26 | I8: =DATEDIF(H8, TODAY(), "Y") -> 5 | J8: 崇州市三江街道顺金西街728号 | K8: 四川省 | L8: =VLOOKUP(K8,[1]中国省份_标准!$B$2:$F$35,4,FALSE) -> 西部地区 | M8: =VLOOKUP(K8,[1]中国省份_标准!$B$2:$F$35,5,FALSE) -> 西南地区 | N8: 成都市 | O8: 崇州市 | P8: 028-82249643 | Q8: 028-82249315;18628221097 | R8: - | S8: - | T8: 有限责任公司（自然人投资或控股的法人独资） | U8: 91510184MA69RTFWXW | V8: 510184002107780 | W8: MA69RTFW-X | X8: 161 | Y8: 2024年报 | Z8: 2020-04-26 至 无固定期限 | AA8: 制造业 | AB8: 食品制造业 | AC8: 其他食品制造 | AD8: 食品及饲料添加剂制造 | AE8: S(小型) | AF8: Chongzhou Wangda Feed Co., Ltd. | AG8: - | AH8: - | AI8: 崇州市旺达饲料有限公司成立于2020-04-26，法定代表人为朱桂英，注册资本为3000万元，统一社会信用代码为91510184MA69RTFWXW，企业注册地址位于崇州市三江街道顺金西街728号，所属行业为食品制造业，经营范围包含：添加剂预混合饲料、配合饲料、浓缩饲料生产、销售；畜禽饲养技术开发、咨询、交流、转让、推广服务；猪的疾病诊断与治疗指导；饲料原料进出口贸易业务。（依法须经批准的项目，经相关部门批准后方可开展经营活动）。企业当前经营状态为存续。 | AJ8: 添加剂预混合饲料、配合饲料、浓缩饲料生产、销售；畜禽饲养技术开发、咨询、交流、转让、推广服务；猪的疾病诊断与治疗指导；饲料原料进出口贸易业务。（依法须经批准的项目，经相关部门批准后方可开展经营活动） | AK8: 崇州市市场监督管理局 | AL8: 一般纳税人
A9: 青岛天驰物流有限公司 | B9: 91370281MA3PBK1X6Y | C9: 中创天驰智慧冷链（青岛）有限公司, 青岛天驰冷链服务有限公司, 青岛海铁供应链管理有限公司 | D9: 在业 | E9: 张秀杰 | F9: 15600万元 | G9: 15600万元 | H9: 2019-03-18 | I9: =DATEDIF(H9, TODAY(), "Y") -> 6 | J9: 山东省青岛市胶州市尚德大道湘江支路6号 | K9: 山东省 | L9: =VLOOKUP(K9,[1]中国省份_标准!$B$2:$F$35,4,FALSE) -> 东部地区 | M9: =VLOOKUP(K9,[1]中国省份_标准!$B$2:$F$35,5,FALSE) -> 华东地区 | N9: 青岛市 | O9: 胶州市 | P9: 18753289809 | Q9: 0532-86627786 | R9: 110877069@qq.com | S9: 463786450@qq.com | T9: 有限责任公司（非自然人投资或控股的法人独资） | U9: 91370281MA3PBK1X6Y | V9: 370281230385738 | W9: MA3PBK1X-6 | X9: 11 | Y9: 2024年报 | Z9: 2019-03-18 至 2031-03-13 | AA9: 制造业 | AB9: 金属制品、机械和设备修理业 | AC9: 其他机械和设备修理业 | AD9: 其他机械和设备修理业 | AE9: S(小型) | AF9: Qingdao Tianchi Logistics Co., Ltd. | AG9: - | AH9: - | AI9: 青岛天驰物流有限公司成立于2019-03-18，法定代表人为张秀杰，注册资本为15600万元，统一社会信用代码为91370281MA3PBK1X6Y，企业注册地址位于山东省青岛市胶州市尚德大道湘江支路6号，所属行业为金属制品、机械和设备修理业，经营范围包含：一般项目：国际货物运输代理；国内贸易代理；国内货物运输代理；普通货物仓储服务（不含危险化学品等需许可审批的项目）；装卸搬运；信息咨询服务（不含许可类信息咨询服务）；农副产品销售；水产品批发；食用农产品批发；木材销售；金属材料销售；建筑材料销售；橡胶制品销售；针纺织品销售；化工产品销售（不含许可类化工产品）；食品销售（仅销售预包装食品）；货物进出口；技术进出口；报关业务；进出口代理。（除依法须经批准的项目外，凭营业执照依法自主开展经营活动）许可项目：海关监管货物仓储服务（不含危险化学品、危险货物）。（依法须经批准的项目，经相关部门批准后方可开展经营活动，具体经营项目以相关部门批准文件或许可证件为准）。企业当前经营状态为在业。 | AJ9: 一般项目：国际货物运输代理；国内贸易代理；国内货物运输代理；普通货物仓储服务（不含危险化学品等需许可审批的项目）；装卸搬运；信息咨询服务（不含许可类信息咨询服务）；农副产品销售；水产品批发；食用农产品批发；木材销售；金属材料销售；建筑材料销售；橡胶制品销售；针纺织品销售；化工产品销售（不含许可类化工产品）；食品销售（仅销售预包装食品）；货物进出口；技术进出口；报关业务；进出口代理。（除依法须经批准的项目外，凭营业执照依法自主开展经营活动）许可项目：海关监管货物仓储服务（不含危险化学品、危险货物）。（依法须经批准的项目，经相关部门批准后方可开展经营活动，具体经营项目以相关部门批准文件或许可证件为准） | AK9: 胶州市市场监督管理局 | AL9: 一般纳税人
A10: 新疆农资（集团）有限责任公司 | B10: 91650000731837138C | C10: 新疆农资（集团）有限责任公司农佳乐连锁总部, 农佳乐连锁总部 | D10: 存续 | E10: 李万君 | F10: 44000万元 | G10: 44000万元 | H10: 2001-12-18 | I10: =DATEDIF(H10, TODAY(), "Y") -> 24 | J10: 新疆乌鲁木齐市天山区中山路2号 | K10: 新疆维吾尔自治区 | L10: =VLOOKUP(K10,[1]中国省份_标准!$B$2:$F$35,4,FALSE) -> 西部地区 | M10: =VLOOKUP(K10,[1]中国省份_标准!$B$2:$F$35,5,FALSE) -> 西北地区 | N10: 乌鲁木齐市 | O10: 天山区 | P10: 18097686898 | Q10: 0991-2840504 | R10: 136173075@qq.com | S10: 2813057570@qq.com;356729482@qq.com | T10: 有限责任公司（非自然人投资或控股的法人独资） | U10: 91650000731837138C | V10: 650000030000157 | W10: 73183713-8 | X10: 275 | Y10: 2024年报 | Z10: 2001-12-18 至 无固定期限 | AA10: 批发和零售业 | AB10: 批发业 | AC10: 矿产品、建材及化工产品批发 | AD10: 农药批发 | AE10: L(大型) | AF10: Xinjiang NONGZI(Group) Co., Ltd. | AG10: - | AH10: - | AI10: 新疆农资（集团）有限责任公司成立于2001-12-18，法定代表人为李万君，注册资本为44000万元，统一社会信用代码为91650000731837138C，企业注册地址位于新疆乌鲁木齐市天山区中山路2号，所属行业为批发业，经营范围包含：农药、茶叶（边销茶限零售）的销售；粮油零售；煤炭的销售 化肥、农膜、滴灌带、种子（不再分装的包装种子）、农副产品、复合饲料、腐植酸、五金交电产品、日用百货、农业机械、汽车配件、钢材、木材、机电产品、化工产品、建筑材料、水泥、皮棉、矿产品、聚乙烯的销售；塑料制品的加工和销售；货运代理；一般货物与技术的进出口经营；仓储服务；货物的装卸服务；废旧物资回收；房屋租赁；销售蔬菜；、针纺织品、化妆品、服装、珠宝首饰、工艺美术品及收藏品、玉器、润滑油的销售。棉粕的销售；自产自销农产品;销售有机肥料。（依法须经批准的项目，经相关部门批准后方可开展经营活动）。企业当前经营状态为存续。 | AJ10: 农药、茶叶（边销茶限零售）的销售；粮油零售；煤炭的销售 化肥、农膜、滴灌带、种子（不再分装的包装种子）、农副产品、复合饲料、腐植酸、五金交电产品、日用百货、农业机械、汽车配件、钢材、木材、机电产品、化工产品、建筑材料、水泥、皮棉、矿产品、聚乙烯的销售；塑料制品的加工和销售；货运代理；一般货物与技术的进出口经营；仓储服务；货物的装卸服务；废旧物资回收；房屋租赁；销售蔬菜；、针纺织品、化妆品、服装、珠宝首饰、工艺美术品及收藏品、玉器、润滑油的销售。棉粕的销售；自产自销农产品;销售有机肥料。（依法须经批准的项目，经相关部门批准后方可开展经营活动） | AK10: 天山区市场监督管理局 | AL10: 一般纳税人
A11: 四川绵竹剑南春酒厂有限公司 | B11: 915106832052585585 | C11: - | D11: 存续 | E11: 乔天明 | F11: 2047万元 | G11: 2047万元 | H11: 2003-11-18 | I11: =DATEDIF(H11, TODAY(), "Y") -> 22 | J11: 四川省绵竹市春溢街289号 | K11: 四川省 | L11: =VLOOKUP(K11,[1]中国省份_标准!$B$2:$F$35,4,FALSE) -> 西部地区 | M11: =VLOOKUP(K11,[1]中国省份_标准!$B$2:$F$35,5,FALSE) -> 西南地区 | N11: 德阳市 | O11: 绵竹市 | P11: 0838-6202206 | Q11: - | R11: jnc-fzb@163.com | S11: jnc@jnc.com.cn;jncxym@163.com | T11: 有限责任公司（自然人投资或控股） | U11: 915106832052585585 | V11: 510683000013614 | W11: 20525855-8 | X11: 5785 | Y11: 2024年报 | Z11: 2003-11-18 至 无固定期限 | AA11: 制造业 | AB11: 酒、饮料和精制茶制造业 | AC11: 酒的制造 | AD11: 白酒制造 | AE11: M(中型) | AF11: Mianzhu Jiannanchun Distillery Co., Ltd. of Sichuan | AG11: https://www.junlebaoruye.com | AH11: - | AI11: 四川绵竹剑南春酒厂有限公司位于西蜀历史文化名城——绵竹。剑南春公司以酒类经营为主业，总资产48亿元，现有员工7000余人。多年来，剑南春集团公司保持了持续稳步发展的好势头，自1998年至今，公司总体经营实力，投入产出效率、盈利能力、偿债能力、营运能力和发展能力等名列行业前茅，被誉为“中国白酒行业三巨头”之一。2007年4月，剑南春集团被四川省人民政府表彰为“四川省十佳民营企业”。公司荣获全国首批重合同守信用企业、中国最具竞争力大企业集团、全国质量效益型先进企业特别奖、全国精神文明建设工作先进单位等称号。公司通过了ISO9001质量管理体系认证、ISO14001环境管理体系认证、职业健康安全管理体系和国家级原产地标记注册。公司享有产品经营出口权。公司龙头产品剑南春酒早在1200年前就成为宫廷御酒而记载于《唐·德宗本纪》，中书舍人李肇所着的《唐国史补》中也将其列为当时的天下名酒。剑南春“天益老号”酒坊遗址入选2004年度“中国考古十大新发现”。该遗址从绵竹城西北的诸葛祠向东南抵至王麻巷口，长约500米，宽约240米，总面积120,000平方米，相当于16个足球场大小。其规模之宏大、生产要素之齐全、保存之完整，并且是仍在使用的活文物原址，举世罕见，是中国近代工业考古的重大发现。2006年，剑南春酒坊遗址入选由国务院核定公布的第六批全国重点文物保护单位，并入选《中国世界文化遗产预备名单》。数千年来，剑南春酒以其尊贵的品质、经典的御酒地位和独特的品位饮醉了无数的华夏儿女，留下了诸多诗词和佳话。作为传承至今的盛唐宫廷御酒，今日剑南春被国家授予“中国名酒”称号，“剑南春”及“绵竹”牌被国家工商局认定为“中国驰名商标”，剑南春品牌被中国商务部认定为“中华老字号”。剑南春酒的生产工艺代表着当今中国白酒酿造技术的最高水平。秉承传统工艺，并加以不断改进和和创新，剑南春酒以其独特的酒体风格受到中外消费者的喜爱。2005年5月中国食品工业协会向四川剑南春（集团）有限责任公司颁发了“纯粮固态发酵白酒认证标志 ”，成为国内排名靠前个允许使用“纯粮固态发酵白酒”标志的企业。“纯粮固态发酵白酒标志”正式在白酒行业内的使用和推广，也标志着中国高级白酒有了自己的身份证。2005年7月印有“纯粮固态发酵白酒标志”、同时防伪升级的新包装剑南春全面上市，很受消费者青睐。2008年，剑南春酒传统酿造技艺入选国家级非物质文化遗产。剑南春酒公司完善的质量管理体系保证产品实现了全优。剑南春、剑南春·典藏、剑南春年份酒及其系列品牌东方红、金剑南、银剑南、剑南老窖、剑南福、绵竹大曲等30多个品牌，多次获得国家级、部级、省级质量奖，产品知名度、美誉度节节攀升，市场占有份额不断扩大，始终保持了畅销的强劲势头。2007年，公司全年生产销售各种饮料酒8万吨，完成销售收入36亿元，比上年上升15.6%；实现税利11.6亿元，比上年上升13%，上缴国地两税9.7亿元，比上年上升23%，销售收入和利税均居全国同行业第三位。 | AJ11: 生产、销售：白酒、其他酒（配制酒）、矿泉水；粮食收购；（以上项目凭许可证在有效期内经营）；及相关进出口业务；酒类技术咨询服务。（依法须经批准的项目，经相关部门批准后方可开展经营活动） | AK11: 绵竹市市场监督管理局 | AL11: 一般纳税人
A12: 贵州省耀盛纺织制造有限公司 | B12: 91522628MAAJNXNT1X | C12: - | D12: 存续 | E12: 鄢金锋 | F12: 1000万元 | G12: 1000万元 | H12: 2020-06-02 | I12: =DATEDIF(H12, TODAY(), "Y") -> 5 | J12: 贵州省黔东南州锦屏县敦寨镇开发区回乡创业园标准厂房8号楼 | K12: 贵州省 | L12: =VLOOKUP(K12,[1]中国省份_标准!$B$2:$F$35,4,FALSE) -> 西部地区 | M12: =VLOOKUP(K12,[1]中国省份_标准!$B$2:$F$35,5,FALSE) -> 西南地区 | N12: 黔东南苗族侗族自治州 | O12: 锦屏县 | P12: 18785181218 | Q12: 13765150116 | R12: 1445969630@qq.com | S12: 14459696302@qq.com | T12: 有限责任公司（自然人独资） | U12: 91522628MAAJNXNT1X | V12: - | W12: MAAJNXNT-1 | X12: 0 | Y12: 2023年报 | Z12: 2020-06-02 至 无固定期限 | AA12: 制造业 | AB12: 纺织业 | AC12: 针织或钩针编织物及其制品制造 | AD12: 针织或钩针编织物织造 | AE12: S(小型) | AF12: Guizhou Yaosheng Textile Manufacturing Co., Ltd. | AG12: - | AH12: - | AI12: 贵州省耀盛纺织制造有限公司成立于2020-06-02，法定代表人为鄢金锋，注册资本为1000万元，统一社会信用代码为91522628MAAJNXNT1X，企业注册地址位于贵州省黔东南州锦屏县敦寨镇开发区回乡创业园标准厂房8号楼，所属行业为纺织业，经营范围包含：法律、法规、国务院决定规定禁止的不得经营；法律、法规、国务院决定规定应当许可（审批）的，经审批机关批准后凭许可（审批）文件经营;法律、法规、国务院决定规定无需许可（审批）的，市场主体自主选择经营。（加工、销售纺织带、松紧带、拉链；销售针纺织原料、针纺织品。（依法须经批准的项目，经相关部门批准后方可开展经营活动）（依法须经批准的项目，经相关部门批准后方可开展经营活动））。企业当前经营状态为存续。 | AJ12: 法律、法规、国务院决定规定禁止的不得经营；法律、法规、国务院决定规定应当许可（审批）的，经审批机关批准后凭许可（审批）文件经营;法律、法规、国务院决定规定无需许可（审批）的，市场主体自主选择经营。（加工、销售纺织带、松紧带、拉链；销售针纺织原料、针纺织品。（依法须经批准的项目，经相关部门批准后方可开展经营活动）（依法须经批准的项目，经相关部门批准后方可开展经营活动）） | AK12: 黔东南州锦屏县市场监督管理局 | AL12: 一般纳税人
A13: 会泽温氏畜牧有限公司 | B13: 91530326MA6K77NL1D | C13: - | D13: 存续 | E13: 陈水华 | F13: 3200万元 | G13: 3200万元 | H13: 2016-08-08 | I13: =DATEDIF(H13, TODAY(), "Y") -> 9 | J13: 云南省曲靖市会泽县宝云街道会泽工业园区宝云绿色食品加工区 | K13: 云南省 | L13: =VLOOKUP(K13,[1]中国省份_标准!$B$2:$F$35,4,FALSE) -> 西部地区 | M13: =VLOOKUP(K13,[1]中国省份_标准!$B$2:$F$35,5,FALSE) -> 西南地区 | N13: 曲靖市 | O13: 会泽县 | P13: 13988460554 | Q13: 18208717028;13529871883 | R13: 1964819318@qq.com | S13: 1425936851@qq.com;78456695@qq.com | T13: 有限责任公司（自然人投资或控股的法人独资） | U13: 91530326MA6K77NL1D | V13: 530326000032312 | W13: MA6K77NL-1 | X13: 133 | Y13: 2024年报 | Z13: 2016-08-08 至 无固定期限 | AA13: 农、林、牧、渔业 | AB13: 畜牧业 | AC13: 牲畜饲养 | AD13: 猪的饲养 | AE13: M(中型) | AF13: Huize Wenshi Livestock Co., Ltd. | AG13: - | AH13: - | AI13: 会泽温氏畜牧有限公司成立于2016-08-08，法定代表人为陈水华，注册资本为3200万元，统一社会信用代码为91530326MA6K77NL1D，企业注册地址位于云南省曲靖市会泽县宝云街道会泽工业园区宝云绿色食品加工区，所属行业为畜牧业，经营范围包含：种猪、猪苗、肉猪、饲料、猪精液的生产和销售及相关副产品销售，肉猪产品的销售。（依法须经批准的项目，经相关部门批准后方可开展经营活动）。企业当前经营状态为存续。 | AJ13: 种猪、猪苗、肉猪、饲料、猪精液的生产和销售及相关副产品销售，肉猪产品的销售。（依法须经批准的项目，经相关部门批准后方可开展经营活动） | AK13: 会泽县市场监督管理局 | AL13: 一般纳税人
... A1087: 河南国储物流股份有限公司 | B1087: 91410100587050882Y | C1087: - | D1087: 存续 | E1087: 崔鹏飞 | F1087: 1200万元 | G1087: 1200万元 | H1087: 2011-11-18 | I1087: =DATEDIF(H1087, TODAY(), "Y") -> 14 | J1087: 郑州市金水区东明路179号 | K1087: 河南省 | L1087: =VLOOKUP(K1087,[1]中国省份_标准!$B$2:$F$35,4,FALSE) -> 中部地区 | M1087: =VLOOKUP(K1087,[1]中国省份_标准!$B$2:$F$35,5,FALSE) -> 华中地区 | N1087: 郑州市 | O1087: 金水区 | P1087: 0371-63287489 | Q1087: 0371-60902859 | R1087: hngcwl@126.com | S1087: - | T1087: 其他股份有限公司（非上市） | U1087: 91410100587050882Y | V1087: 410100000084364 | W1087: 58705088-2 | X1087: 0 | Y1087: 2024年报 | Z1087: 2011-11-18 至 2061-11-17 | AA1087: 交通运输、仓储和邮政业 | AB1087: 装卸搬运和仓储业 | AC1087: 危险品仓储 | AD1087: 危险化学品仓储 | AE1087: XS(微型) | AF1087: Henan Guochu Logistics Co., Ltd. | AG1087: - | AH1087: - | AI1087: 河南国储物流股份有限公司成立于2011-11-18，法定代表人为崔鹏飞，注册资本为1200万元，统一社会信用代码为91410100587050882Y，企业注册地址位于郑州市金水区东明路179号，所属行业为装卸搬运和仓储业，经营范围包含：许可项目：道路货物运输（不含危险货物）；食品销售；住宿服务；洗浴服务；烟草制品零售；餐饮服务（依法须经批准的项目，经相关部门批准后方可开展经营活动，具体经营项目以相关部门批准文件或许可证件为准）一般项目：酒店管理；物业管理；物业服务评估；食品销售（仅销售预包装食品）；保健食品（预包装）销售；电动汽车充电基础设施运营；专用设备修理；农副产品销售；工艺美术品及收藏品零售（象牙及其制品除外）；日用百货销售；会议及展览服务；停车场服务；货物进出口；进出口代理；国际货物运输代理；装卸搬运；国内集装箱货物运输代理；租赁服务（不含许可类租赁服务）；小微型客车租赁经营服务；普通货物仓储服务（不含危险化学品等需许可审批的项目）；仓单登记服务；住房租赁；普通机械设备安装服务；机械设备租赁；集装箱租赁服务；集装箱维修；集装箱销售；金属结构销售；金属材料销售；橡胶制品销售；纸浆销售；纸制品销售（除依法须经批准的项目外，凭营业执照依法自主开展经营活动）。企业当前经营状态为存续。 | AJ1087: 许可项目：道路货物运输（不含危险货物）；食品销售；住宿服务；洗浴服务；烟草制品零售；餐饮服务（依法须经批准的项目，经相关部门批准后方可开展经营活动，具体经营项目以相关部门批准文件或许可证件为准）一般项目：酒店管理；物业管理；物业服务评估；食品销售（仅销售预包装食品）；保健食品（预包装）销售；电动汽车充电基础设施运营；专用设备修理；农副产品销售；工艺美术品及收藏品零售（象牙及其制品除外）；日用百货销售；会议及展览服务；停车场服务；货物进出口；进出口代理；国际货物运输代理；装卸搬运；国内集装箱货物运输代理；租赁服务（不含许可类租赁服务）；小微型客车租赁经营服务；普通货物仓储服务（不含危险化学品等需许可审批的项目）；仓单登记服务；住房租赁；普通机械设备安装服务；机械设备租赁；集装箱租赁服务；集装箱维修；集装箱销售；金属结构销售；金属材料销售；橡胶制品销售；纸浆销售；纸制品销售（除依法须经批准的项目外，凭营业执照依法自主开展经营活动） | AK1087: 郑州市市场监督管理局 | AL1087: 一般纳税人
