Workbook

Sheet 项目汇总表
B1: 表一：基础信息表
A2: 共享系统部门名称 | B2: 项目名称 | C2: 主合同信息 | U2: 分包合同信息 | AH2: 间接费用 | AI2: 财务费用 | AJ2: 税金及附加 | AK2: 预交增值税 | AL2: 管理费比例 | AM2: 合同签订单位 | AN2: 项目管理单位 | AO2: 合同开工日期 | AP2: 预计竣工时间 | AQ2: 合同工期 | AR2: 工程类型 | AS2: 项目所在地（*省*市） | AT2: 项目状态 | AU2: 预计新增业主验工计价 | AV2: 预计新增分包验工计价 | AW2: 预计新增施工成本 | AX2: 预计新增施工收入 | AY2: 预计新增收款 | AZ2: 预计新增付款 | BA2: 预计新增两金 | BB2: 预计新增应付账款 | BC2: 1122应收账款 | BD2: 1123预付款项 | BE2: 1221其他应收款 | BF2: 1221-04-03其他应收款-民工工资保证金 | BG2: 1221-05其他应收款-预付款项转入 | BH2: 1221-09其他应收款-应收押金 | BI2: 1221-11其他应收款-应收押金 | BJ2: 1221-99其他应收款-其他 | BK2: 1231坏账准备 | BL2: 1484合同资产减值准备 | BM2: 1483合同资产 | BN2: 1531长期应收款 | BO2: 2202应付账款 | BP2: 2202-12应付账款-预付账款增值税 | BQ2: 2204合同负债 | BR2: 2204-10合同负债-预收账款增值税 | BS2: 2221-06应交税费-待转销项税额 | BT2: 2241其他应付款 | BU2: 2241-01其他应付款-保证金 | BV2: 2241-05其他应付款-应付押金 | BW2: 2241-99其他应付款-其他 | BX2: 2701长期应付款 | BY2: 2701-05长期应付款-应付质量保证金 | BZ2: 2701-99长期应付款-其他 | CA2: 5601-01-01-01合同履约成本-工程施工-合同成本-直接人工费（期末数） | CB2: 5601-01-01-02合同履约成本-工程施工-合同成本-直接材料费（期末数） | CC2: 5601-01-01-04合同履约成本-工程施工-合同成本-劳务成本（期末数） | CD2: 5601-01-01-05合同履约成本-工程施工-合同成本-专业分包成本（期末数） | CE2: 5601-01-01-06合同履约成本-工程施工-合同成本-其他直接费用（期末数） | CF2: 5601-01-01-07合同履约成本-工程施工-合同成本-间接费用转入（期末数） | CG2: 5601-01-01-01合同履约成本-工程施工-合同成本-直接人工费（当年借方发生数） | CH2: 5601-01-01-02合同履约成本-工程施工-合同成本-直接材料费（当年借方发生数） | CI2: 5601-01-01-04合同履约成本-工程施工-合同成本-劳务成本（当年借方发生数） | CJ2: 5601-01-01-05合同履约成本-工程施工-合同成本-专业分包成本（当年借方发生数） | CK2: 5601-01-01-06合同履约成本-工程施工-合同成本-其他直接费用（当年借方发生数） | CL2: 5601-01-01-07合同履约成本-工程施工-合同成本-间接费用转入（当年借方发生数） | CM2: 5601-02合同履约成本-劳务成本（当年借方发生数） | CN2: 5801-01合同结算-收入结转 | CO2: 5801-02合同结算-价款结算 | CP2: 6001主营业务收入（当年贷方发生数） | CQ2: 6401主营业务成本（当年借方发生数） | CR2: 应为零 | CS2: 应为零 | CT2: 应为零 | CU2: 应为零 | CV2: 应为零（正数为未验完，负数为超验） | CW2: 应为零 | CX2: 应尽量小，超过1000万预警 | CY2: 应尽量小 | CZ2: 校验不平的备注原因 | DA2: 计划完成的工作 | DB2: 完成情况
C3: 勘察设计合同额 | D3: 工程施工合同额 | E3: 设备采购合同额 | F3: 业主承担管理费合同额 | G3: 技术服务等合同额 | H3: 合同额合计 | I3: 合同额不含税合计 | J3: 工程施工预计总收入 | K3: 工程施工预计总成本 | L3: 累计验工计价 | M3: 累计验工计价税额 | N3: 工程施工验工计价 | O3: 累计确认收入 | P3: 工程施工确认收入 | Q3: 累计开票 | R3: 累计施工开票 | S3: 累计开票税金 | T3: 累计收款 | U3: 勘察设计合同额 | V3: 工程施工合同额 | W3: 设备采购合同额 | X3: 技术服务等合同额 | Y3: 合计 | Z3: 不含税合计 | AA3: 累计验工计价 | AB3: 施工验工计价 | AC3: 累计确认成本 | AD3: 施工确认成本 | AE3: 累计开票 | AF3: 累计施工开票 | AG3: 累计付款 | CR3: 业主往来检验 | CS3: 业主发票检验 | CT3: 业主收入检验 | CU3: 分包往来检验 | CV3: 分包施工验工计价校验 | CW3: 预缴税金检验 | CX3: 两金指标 | CY3: 验工进度校验
A4: ='武隆污水（不上系统）'!L4 -> 中铁二院武隆污水厂项目部 | B4: ='武隆污水（不上系统）'!M4 -> 武隆污水处理厂二期扩建工程EPC | C4: ='武隆污水（不上系统）'!E4 -> 2933770.4 | D4: ='武隆污水（不上系统）'!F4 -> 1.16656e+08 | E4: ='武隆污水（不上系统）'!G4 -> 0 | F4: ='武隆污水（不上系统）'!H4 -> 0 | G4: ='武隆污水（不上系统）'!I4 -> 0 | H4: =SUM(C4:G4) -> 1.1958977e+08 | I4: =C4/1.06+D4/1.09+E4/1.13+F4/1.06+G4/1.06 -> 1.0979156e+08 | J4: ='武隆污水（不上系统）'!V11 -> 1.0622063e+08 | K4: ='武隆污水（不上系统）'!W11 -> 1.0324322e+08 | L4: ='武隆污水（不上系统）'!G11 -> 1.1958977e+08 | M4: ='武隆污水（不上系统）'!H17 -> 10601433 | N4: ='武隆污水（不上系统）'!C11 -> 1.16656e+08 | O4: ='武隆污水（不上系统）'!S11 -> 1.0898834e+08 | P4: ='武隆污水（不上系统）'!O11 -> 1.0622063e+08 | Q4: ='武隆污水（不上系统）'!M11 -> 1.1958977e+08 | R4: ='武隆污水（不上系统）'!I11 -> 1.16656e+08 | S4: ='武隆污水（不上系统）'!X17 -> 10601433 | T4: ='武隆污水（不上系统）'!T11 -> 1.1958977e+08 | U4: ='武隆污水（不上系统）'!E5+'武隆污水（不上系统）'!E6 -> 2000000 | V4: ='武隆污水（不上系统）'!F5+'武隆污水（不上系统）'!F6 -> 1.134038e+08 | W4: ='武隆污水（不上系统）'!G5+'武隆污水（不上系统）'!G6 -> 0 | X4: ='武隆污水（不上系统）'!H5+'武隆污水（不上系统）'!H6 -> 0 | Y4: =SUM(U4:X4) -> 1.154038e+08 | Z4: =U4/1.06+V4/1.09+W4/1.13+X4/1.06 -> 1.0592697e+08 | AA4: ='武隆污水（不上系统）'!G12+'武隆污水（不上系统）'!G13 -> 1.149538e+08 | AB4: ='武隆污水（不上系统）'!C12 -> 1.134038e+08 | AC4: ='武隆污水（不上系统）'!S12+'武隆污水（不上系统）'!S13 -> 1.0470548e+08 | AD4: ='武隆污水（不上系统）'!O12 -> 1.0324322e+08 | AE4: ='武隆污水（不上系统）'!M12+'武隆污水（不上系统）'!M13 -> 1.149538e+08 | AF4: ='武隆污水（不上系统）'!I12 -> 1.134038e+08 | AG4: ='武隆污水（不上系统）'!T12+'武隆污水（不上系统）'!T13 -> 1.149538e+08 | AH4: ='武隆污水（不上系统）'!I102 -> 460219.88 | AI4: ='武隆污水（不上系统）'!I103 -> -31159.52 | AJ4: ='武隆污水（不上系统）'!E98+'武隆污水（不上系统）'!F98+'武隆污水（不上系统）'!G98+'武隆污水（不上系统）'!H98+'武隆污水（不上系统）'!J98+'武隆污水（不上系统）'!K98 -> 356700.42 | AK4: ='武隆污水（不上系统）'!D98 -> 35350.07 | AL4: ='武隆污水（不上系统）'!K4 -> 0.027878598 | AM4: ='武隆污水（不上系统）'!N4 -> 经计部 | AN4: ='武隆污水（不上系统）'!O4 -> 生态环境院 | AO4: ='武隆污水（不上系统）'!S4 -> 0 | AP4: ='武隆污水（不上系统）'!T4 -> 0 | AQ4: ='武隆污水（不上系统）'!U4 -> 0 | AR4: ='武隆污水（不上系统）'!V4 -> 市政 | AS4: ='武隆污水（不上系统）'!W4 -> 重庆市武隆区 | AT4: ='武隆污水（不上系统）'!X4 -> 竣工未决算 | AV4: ='武隆污水（不上系统）'!E133 -> 0 | AW4: =AV4/1.09 -> 0 | AX4: =AW4/#REF!*#REF! -> #REF! | BA4: =(AU4-AY4)+(AX4-AU4/1.09) -> #REF! | BB4: =AV4-AZ4 -> 0 | BC4: {=INDEX(账面数据!$A$1:$BB$10000,MATCH($B4,账面数据!$A:$A,0),MATCH(BC$2,账面数据!$1:$1,0))} -> 0 | BD4: {=INDEX(账面数据!$A$1:$BB$10000,MATCH($B4,账面数据!$A:$A,0),MATCH(BD$2,账面数据!$1:$1,0))} -> 0 | BE4: {=INDEX(账面数据!$A$1:$BB$10000,MATCH($B4,账面数据!$A:$A,0),MATCH(BE$2,账面数据!$1:$1,0))} -> 0 | BF4: {=INDEX(账面数据!$A$1:$BB$10000,MATCH($B4,账面数据!$A:$A,0),MATCH(BF$2,账面数据!$1:$1,0))} -> 0 | BG4: {=INDEX(账面数据!$A$1:$BB$10000,MATCH($B4,账面数据!$A:$A,0),MATCH(BG$2,账面数据!$1:$1,0))} -> 0 | BH4: {=INDEX(账面数据!$A$1:$BB$10000,MATCH($B4,账面数据!$A:$A,0),MATCH(BH$2,账面数据!$1:$1,0))} -> 0 | BI4: {=INDEX(账面数据!$A$1:$BB$10000,MATCH($B4,账面数据!$A:$A,0),MATCH(BI$2,账面数据!$1:$1,0))} -> 0 | BJ4: {=INDEX(账面数据!$A$1:$BB$10000,MATCH($B4,账面数据!$A:$A,0),MATCH(BJ$2,账面数据!$1:$1,0))} -> 0 | ... CQ4: {=INDEX(账面数据!$A$1:$BB$10000,MATCH($B4,账面数据!$A:$A,0),MATCH(CQ$2,账面数据!$1:$1,0))} -> 0 | CR4: =L4-T4-BC4-BF4-BM4-BN4+BQ4-BR4 -> 0 | CS4: =M4-S4-BR4-BS4 -> 0 | CT4: =AD4/K4*J4-P4 -> 0 | CU4: =AA4-AG4-BO4+BP4-BX4-BU4+BD4 -> 0 | CV4: =N4*(1-AL4)-AB4 -> 0 | CW4: =(R4-AF4)/1.09*0.02-AK4 -> 24323.431 | CX4: =BC4+(CN4-CO4)-BQ4 -> 0 | CY4: =L4/H4-AA4/Y4 -> 0.0038993517 | CZ4: 未缴纳税金 | DA4: 未办理外经证，8月底前预缴税金 | DB4: 环研院杨琳休假，计划于9.1-9.15日之间预缴
A5: =攀枝花大渡口!L4 -> 中铁二院攀枝花市大渡口污水处理厂提标升级改造工程EPC项目部 | B5: =攀枝花大渡口!M4 -> 攀枝花市大渡口污水处理厂提标升级改造工程项目勘察设计材料及设备采购施工总承包 | C5: =攀枝花大渡口!E4 -> 1520000 | D5: =攀枝花大渡口!F4 -> 13053600 | E5: =攀枝花大渡口!G4 -> 12326400 | F5: =攀枝花大渡口!H4 -> 0 | G5: =攀枝花大渡口!I4 -> 0 | H5: =SUM(C5:G5) -> 26900000 | I5: =C5/1.06+D5/1.09+E5/1.13+F5/1.06+G5/1.06 -> 24318061 | J5: =攀枝花大渡口!V12 -> 11975780 | K5: =攀枝花大渡口!W12 -> 11712313 | L5: =攀枝花大渡口!G12 -> 21835735 | M5: =攀枝花大渡口!H18 -> 2148318.6 | N5: =攀枝花大渡口!C12 -> 8466630 | O5: =攀枝花大渡口!S12 -> 22432092 | P5: =攀枝花大渡口!O12 -> 10512226 | Q5: =攀枝花大渡口!M12 -> 21853450 | R5: =攀枝花大渡口!I12 -> 8788345 | S5: =攀枝花大渡口!X18 -> 2157644.7 | T5: =攀枝花大渡口!T12 -> 21853450 | U5: =攀枝花大渡口!E6 -> 220000 | V5: =攀枝花大渡口!F5+攀枝花大渡口!F7 -> 12766421 | W5: =攀枝花大渡口!G5+攀枝花大渡口!G7 -> 12055219 | X5: =攀枝花大渡口!H5+攀枝花大渡口!H7 -> 0 | Y5: =SUM(U5:X5) -> 25041640 | Z5: =U5/1.06+V5/1.09+W5/1.13+X5/1.06 -> 22588195 | AA5: =攀枝花大渡口!G13+攀枝花大渡口!G14+攀枝花大渡口!G15 -> 20719065 | AB5: =攀枝花大渡口!C13 -> 10060410 | AC5: =攀枝花大渡口!S13+攀枝花大渡口!S14 -> 9437281.6 | AD5: =攀枝花大渡口!O13 -> 9229734.4 | AE5: =攀枝花大渡口!M13+攀枝花大渡口!M14 -> 9964771.5 | AF5: =攀枝花大渡口!I12 -> 8788345 | AG5: =攀枝花大渡口!T13+攀枝花大渡口!T14+攀枝花大渡口!T15 -> 20403427 | AH5: =攀枝花大渡口!I98 -> 57664.54 | AI5: =攀枝花大渡口!I99 -> -10160.24 | AJ5: =攀枝花大渡口!E94+攀枝花大渡口!F94+攀枝花大渡口!G94+攀枝花大渡口!H94+攀枝花大渡口!J94+攀枝花大渡口!K94 -> 8070 | AK5: =攀枝花大渡口!D94 -> 0 | AL5: =攀枝花大渡口!K4 -> 0.022 | AM5: =攀枝花大渡口!N4 -> 经计部 | AN5: =攀枝花大渡口!O4 -> 生态环境院 | AO5: =攀枝花大渡口!S4 -> 0 | AP5: =攀枝花大渡口!T4 -> 0 | AQ5: =攀枝花大渡口!U4 -> 0 | AR5: =攀枝花大渡口!V4 -> 市政 | AS5: =攀枝花大渡口!W4 -> 四川省攀枝花市 | AT5: =攀枝花大渡口!X4 -> 收尾 | AV5: =攀枝花大渡口!E129 -> -1780045.9 | AW5: =AV5/1.09 -> -1633069.7 | AX5: =AW5/#REF!*#REF! -> #REF! | BA5: =(AU5-AY5)+(AX5-AU5/1.09) -> #REF! | BB5: =AV5-AZ5 -> -1780045.9 | BC5: {=INDEX(账面数据!$A$1:$BB$10000,MATCH($B5,账面数据!$A:$A,0),MATCH(BC$2,账面数据!$1:$1,0))} -> 304000 | BD5: {=INDEX(账面数据!$A$1:$BB$10000,MATCH($B5,账面数据!$A:$A,0),MATCH(BD$2,账面数据!$1:$1,0))} -> 314638 | BE5: {=INDEX(账面数据!$A$1:$BB$10000,MATCH($B5,账面数据!$A:$A,0),MATCH(BE$2,账面数据!$1:$1,0))} -> 0 | BF5: {=INDEX(账面数据!$A$1:$BB$10000,MATCH($B5,账面数据!$A:$A,0),MATCH(BF$2,账面数据!$1:$1,0))} -> 0 | BG5: {=INDEX(账面数据!$A$1:$BB$10000,MATCH($B5,账面数据!$A:$A,0),MATCH(BG$2,账面数据!$1:$1,0))} -> 0 | BH5: {=INDEX(账面数据!$A$1:$BB$10000,MATCH($B5,账面数据!$A:$A,0),MATCH(BH$2,账面数据!$1:$1,0))} -> 0 | BI5: {=INDEX(账面数据!$A$1:$BB$10000,MATCH($B5,账面数据!$A:$A,0),MATCH(BI$2,账面数据!$1:$1,0))} -> 0 | BJ5: {=INDEX(账面数据!$A$1:$BB$10000,MATCH($B5,账面数据!$A:$A,0),MATCH(BJ$2,账面数据!$1:$1,0))} -> 0 | ... CQ5: {=INDEX(账面数据!$A$1:$BB$10000,MATCH($B5,账面数据!$A:$A,0),MATCH(CQ$2,账面数据!$1:$1,0))} -> 0 | CR5: =L5-T5-BC5-BF5-BM5-BN5+BQ5-BR5 -> 0 | CS5: =M5-S5-BR5-BS5 -> -2.9831426e-10 | CT5: =AD5/K5*J5-P5 -> -1074869.7 | CU5: =AA5-AG5-BO5+BP5-BX5-BU5+BD5 -> 2.4447218e-09 | CV5: =N5*(1-AL5)-AB5 -> -1780045.9 | CW5: =(R5-AF5)/1.09*0.02-AK5 -> 0 | CX5: =BC5+(CN5-CO5)-BQ5 -> 2726960.5 | CY5: =L5/H5-AA5/Y5 -> -0.015647163 | CZ5: 1、业主无验工计价，验工未列账； 2、施工多确认收入 | DA5: 1、8月1月前补充预缴税金销售额和抵扣额 | DB5: 已完成
A6: =攀枝花小沙坝!L4 -> 中铁二院攀枝花小沙坝污水处理厂改扩建EPC项目部 | B6: =攀枝花小沙坝!M4 -> 攀枝花小沙坝污水处理厂改扩建工程勘察-设计-采购-施工总承包合同 | C6: =攀枝花小沙坝!E4 -> 3326600 | D6: =攀枝花小沙坝!F4 -> 50118040 | E6: =攀枝花小沙坝!G4 -> 42060960 | F6: =攀枝花小沙坝!H4 -> 0 | G6: =攀枝花小沙坝!I4 -> 0 | H6: =SUM(C6:G6) -> 95505600 | I6: =C6/1.06+D6/1.09+E6/1.13+F6/1.06+G6/1.06 -> 86340244 | J6: =攀枝花小沙坝!V13 -> 45979853 | K6: =攀枝花小沙坝!W13 -> 45060256 | L6: =攀枝花小沙坝!G13 -> 81784714 | M6: =攀枝花小沙坝!H19 -> 8074712.7 | N6: =攀枝花小沙坝!C13 -> 35095447 | O6: =攀枝花小沙坝!S13 -> 77565026 | P6: =攀枝花小沙坝!O13 -> 36052683 | Q6: =攀枝花小沙坝!M13 -> 81119394 | R6: =攀枝花小沙坝!I13 -> 35095447 | S6: =攀枝花小沙坝!X19 -> 8037053.1 | T6: =攀枝花小沙坝!T13 -> 81119394 | U6: =攀枝花小沙坝!E6+攀枝花小沙坝!E8 -> 700000 | V6: =攀枝花小沙坝!F5 -> 49115679 | W6: =攀枝花小沙坝!G6+攀枝花小沙坝!G8 -> 41219741 | X6: =攀枝花小沙坝!H6+攀枝花小沙坝!H8 -> 0 | Y6: =SUM(U6:X6) -> 91035420 | Z6: =U6/1.06+V6/1.09+W6/1.13+X6/1.06 -> 82198280 | AA6: =攀枝花小沙坝!G14+攀枝花小沙坝!G15+攀枝花小沙坝!G16+攀枝花小沙坝!G17 -> 76850631 | AB6: =攀枝花小沙坝!C14 -> 34581733 | AC6: =攀枝花小沙坝!S14+攀枝花小沙坝!S15 -> 69061352 | AD6: =攀枝花小沙坝!O14 -> 31726361 | AE6: =攀枝花小沙坝!M14+攀枝花小沙坝!M15 -> 76888952 | AF6: =攀枝花小沙坝!I14 -> 34442715 | AG6: =攀枝花小沙坝!T14+攀枝花小沙坝!T15+攀枝花小沙坝!T16+攀枝花小沙坝!T17 -> 78018950 | AH6: =攀枝花小沙坝!I99 -> 396012.18 | AI6: =攀枝花小沙坝!I100 -> -23435.28 | AJ6: =攀枝花小沙坝!E95+攀枝花小沙坝!F95+攀枝花小沙坝!G95+攀枝花小沙坝!H95+攀枝花小沙坝!J95+攀枝花小沙坝!K95 -> 30088.9 | AK6: =攀枝花小沙坝!D95 -> 11976.73 | AL6: =攀枝花小沙坝!K4 -> 0.02 | AM6: =攀枝花小沙坝!N4 -> 经计部 | AN6: =攀枝花小沙坝!O4 -> 生态环境院 | AO6: =攀枝花小沙坝!S4 -> 0 | AP6: =攀枝花小沙坝!T4 -> 0 | AQ6: =攀枝花小沙坝!U4 -> 0 | AR6: =攀枝花小沙坝!V4 -> 市政 | AS6: =攀枝花小沙坝!W4 -> 四川省攀枝花市 | AT6: =攀枝花小沙坝!X4 -> 收尾 | AV6: =攀枝花小沙坝!E130 -> -188195.35 | AW6: =AV6/1.09 -> -172656.28 | AX6: =AW6/#REF!*#REF! -> #REF! | BA6: =(AU6-AY6)+(AX6-AU6/1.09) -> #REF! | BB6: =AV6-AZ6 -> -188195.35 | BC6: {=INDEX(账面数据!$A$1:$BB$10000,MATCH($B6,账面数据!$A:$A,0),MATCH(BC$2,账面数据!$1:$1,0))} -> 665320 | BD6: {=INDEX(账面数据!$A$1:$BB$10000,MATCH($B6,账面数据!$A:$A,0),MATCH(BD$2,账面数据!$1:$1,0))} -> 1307339.1 | BE6: {=INDEX(账面数据!$A$1:$BB$10000,MATCH($B6,账面数据!$A:$A,0),MATCH(BE$2,账面数据!$1:$1,0))} -> 0 | BF6: {=INDEX(账面数据!$A$1:$BB$10000,MATCH($B6,账面数据!$A:$A,0),MATCH(BF$2,账面数据!$1:$1,0))} -> 0 | BG6: {=INDEX(账面数据!$A$1:$BB$10000,MATCH($B6,账面数据!$A:$A,0),MATCH(BG$2,账面数据!$1:$1,0))} -> 0 | BH6: {=INDEX(账面数据!$A$1:$BB$10000,MATCH($B6,账面数据!$A:$A,0),MATCH(BH$2,账面数据!$1:$1,0))} -> 0 | BI6: {=INDEX(账面数据!$A$1:$BB$10000,MATCH($B6,账面数据!$A:$A,0),MATCH(BI$2,账面数据!$1:$1,0))} -> 0 | BJ6: {=INDEX(账面数据!$A$1:$BB$10000,MATCH($B6,账面数据!$A:$A,0),MATCH(BJ$2,账面数据!$1:$1,0))} -> 0 | ... BQ6: {=INDEX(账面数据!$A$1:$BB$10000,MATCH($B6,账面数据!$A:$A,0),MATCH(BQ$2,账面数据!$1:$1,0))} -> 0 | BR6: =INDEX(账面数据!$A$1:$BB$10000,MATCH($B6,账面数据!$A:$A,0),MATCH(BR$2,账面数据!$1:$1,0)) -> 0 | BS6: {=INDEX(账面数据!$A$1:$BB$10000,MATCH($B6,账面数据!$A:$A,0),MATCH(BS$2,账面数据!$1:$1,0))} -> 37659.62 | BT6: {=INDEX(账面数据!$A$1:$BB$10000,MATCH($B6,账面数据!$A:$A,0),MATCH(BT$2,账面数据!$1:$1,0))} -> 0 | BU6: {=INDEX(账面数据!$A$1:$BB$10000,MATCH($B6,账面数据!$A:$A,0),MATCH(BU$2,账面数据!$1:$1,0))} -> 0 | BV6: {=INDEX(账面数据!$A$1:$BB$10000,MATCH($B6,账面数据!$A:$A,0),MATCH(BV$2,账面数据!$1:$1,0))} -> 0 | BW6: {=INDEX(账面数据!$A$1:$BB$10000,MATCH($B6,账面数据!$A:$A,0),MATCH(BW$2,账面数据!$1:$1,0))} -> 0 | BX6: {=INDEX(账面数据!$A$1:$BB$10000,MATCH($B6,账面数据!$A:$A,0),MATCH(BX$2,账面数据!$1:$1,0))} -> 0 | BY6: {=INDEX(账面数据!$A$1:$BB$10000,MATCH($B6,账面数据!$A:$A,0),MATCH(BY$2,账面数据!$1:$1,0))} -> 0 | BZ6: {=INDEX(账面数据!$A$1:$BB$10000,MATCH($B6,账面数据!$A:$A,0),MATCH(BZ$2,账面数据!$1:$1,0))} -> 0 | ... CQ6: {=INDEX(账面数据!$A$1:$BB$10000,MATCH($B6,账面数据!$A:$A,0),MATCH(CQ$2,账面数据!$1:$1,0))} -> 0 | CR6: =L6-T6-BC6-BF6-BM6-BN6+BQ6-BR6 -> 0 | CS6: =M6-S6-BR6-BS6 -> 0.010000004 | CT6: =AD6/K6*J6-P6 -> -3678845.2 | CU6: =AA6-AG6-BO6+BP6-BX6-BU6+BD6 -> -3.0267984e-09 | CV6: =N6*(1-AL6)-AB6 -> -188195.35 | CW6: =(R6-AF6)/1.09*0.02-AK6 -> 0.011284404 | CX6: =BC6+(CN6-CO6)-BQ6 -> 4520345 | CY6: =L6/H6-AA6/Y6 -> 0.012150374 | CZ6: 1、业主无验工计价，验工未列账； 2、施工多确认收入 | DA6: 1、8月1月前补充预缴税金销售额和抵扣额 | DB6: 已完成
A7: =攀枝花炳草岗!L4 -> 中铁二院攀枝花市炳草岗污水处理厂提标升级改造工程EPC项目部 | B7: =攀枝花炳草岗!M4 -> 攀枝花市炳草岗污水处理厂提标升级改造工程勘察设计-材料及设备采购-施工总承包 | C7: =攀枝花炳草岗!E4 -> 3010000 | D7: =攀枝花炳草岗!F4 -> 34064400 | E7: =攀枝花炳草岗!G4 -> 26215600 | F7: =攀枝花炳草岗!H4 -> 0 | G7: =攀枝花炳草岗!I4 -> 0 | H7: =SUM(C7:G7) -> 63290000 | I7: =C7/1.06+D7/1.09+E7/1.13+F7/1.06+G7/1.06 -> 57291012 | J7: =攀枝花炳草岗!V13 -> 31251743 | K7: =攀枝花炳草岗!W13 -> 30564205 | L7: =攀枝花炳草岗!G13 -> 53147955 | M7: =攀枝花炳草岗!H19 -> 4902419.7 | N7: =攀枝花炳草岗!C13 -> 31902290 | O7: =攀枝花炳草岗!S13 -> 50053853 | P7: =攀枝花炳草岗!O13 -> 31076474 | Q7: =攀枝花炳草岗!M13 -> 54545955 | R7: =攀枝花炳草岗!I13 -> 33902290 | S7: =攀枝花炳草岗!X19 -> 5033481.9 | T7: =攀枝花炳草岗!T13 -> 54545955 | U7: =攀枝花炳草岗!E6+攀枝花炳草岗!E7 -> 940000 | V7: =攀枝花炳草岗!F5+攀枝花炳草岗!F8 -> 33314983 | W7: =攀枝花炳草岗!G5+攀枝花炳草岗!G8 -> 24470147 | X7: =攀枝花炳草岗!H5+攀枝花炳草岗!H8 -> 0 | Y7: =SUM(U7:X7) -> 58725130 | Z7: =U7/1.06+V7/1.09+W7/1.13+X7/1.06 -> 53105994 | AA7: =攀枝花炳草岗!G14+攀枝花炳草岗!G15+攀枝花炳草岗!G16+攀枝花炳草岗!G17 -> 51906920 | AB7: =攀枝花炳草岗!C14 -> 29945306 | AC7: =攀枝花炳草岗!S14+攀枝花炳草岗!S15 -> 27935022 | AD7: =攀枝花炳草岗!O14 -> 27472758 | AE7: =攀枝花炳草岗!M14+攀枝花炳草岗!M15 -> 30435306 | AF7: =攀枝花炳草岗!I14 -> 29945306 | AG7: =攀枝花炳草岗!T14+攀枝花炳草岗!T15+攀枝花炳草岗!T16++攀枝花炳草岗!T17 -> 51840920 | AH7: =攀枝花炳草岗!I99 -> 226992.11 | AI7: =攀枝花炳草岗!I100 -> -18096.88 | AJ7: =攀枝花炳草岗!E95+攀枝花炳草岗!F95+攀枝花炳草岗!G95+攀枝花炳草岗!H95+攀枝花炳草岗!J95+攀枝花炳草岗!K95 -> 40390.33 | AK7: =攀枝花炳草岗!D95 -> 97821.92 | AL7: =攀枝花炳草岗!K4 -> 0.022 | AM7: =攀枝花炳草岗!N4 -> 生态环境院 | AN7: =攀枝花炳草岗!O4 -> 生态环境院 | AO7: =攀枝花炳草岗!S4 -> 0 | AP7: =攀枝花炳草岗!T4 -> 0 | AQ7: =攀枝花炳草岗!U4 -> 0 | AR7: =攀枝花炳草岗!V4 -> 市政 | AS7: =攀枝花炳草岗!W4 -> 四川省攀枝花市 | AT7: =攀枝花炳草岗!X4 -> 收尾 | AV7: =攀枝花炳草岗!E130 -> 1255133.6 | AW7: =AV7/1.09 -> 1151498.7 | AX7: =AW7/#REF!*#REF! -> #REF! | BA7: =(AU7-AY7)+(AX7-AU7/1.09) -> #REF! | BB7: =AV7-AZ7 -> 1255133.6 | BC7: {=INDEX(账面数据!$A$1:$BB$10000,MATCH($B7,账面数据!$A:$A,0),MATCH(BC$2,账面数据!$1:$1,0))} -> -1295271.4 | BD7: {=INDEX(账面数据!$A$1:$BB$10000,MATCH($B7,账面数据!$A:$A,0),MATCH(BD$2,账面数据!$1:$1,0))} -> 0 | BE7: {=INDEX(账面数据!$A$1:$BB$10000,MATCH($B7,账面数据!$A:$A,0),MATCH(BE$2,账面数据!$1:$1,0))} -> 0 | BF7: {=INDEX(账面数据!$A$1:$BB$10000,MATCH($B7,账面数据!$A:$A,0),MATCH(BF$2,账面数据!$1:$1,0))} -> 0 | BG7: {=INDEX(账面数据!$A$1:$BB$10000,MATCH($B7,账面数据!$A:$A,0),MATCH(BG$2,账面数据!$1:$1,0))} -> 0 | BH7: {=INDEX(账面数据!$A$1:$BB$10000,MATCH($B7,账面数据!$A:$A,0),MATCH(BH$2,账面数据!$1:$1,0))} -> 0 | BI7: {=INDEX(账面数据!$A$1:$BB$10000,MATCH($B7,账面数据!$A:$A,0),MATCH(BI$2,账面数据!$1:$1,0))} -> 0 | BJ7: {=INDEX(账面数据!$A$1:$BB$10000,MATCH($B7,账面数据!$A:$A,0),MATCH(BJ$2,账面数据!$1:$1,0))} -> 0 | ... BQ7: {=INDEX(账面数据!$A$1:$BB$10000,MATCH($B7,账面数据!$A:$A,0),MATCH(BQ$2,账面数据!$1:$1,0))} -> 0 | BR7: =INDEX(账面数据!$A$1:$BB$10000,MATCH($B7,账面数据!$A:$A,0),MATCH(BR$2,账面数据!$1:$1,0)) -> -102728.59 | BS7: {=INDEX(账面数据!$A$1:$BB$10000,MATCH($B7,账面数据!$A:$A,0),MATCH(BS$2,账面数据!$1:$1,0))} -> -28333.55 | BT7: {=INDEX(账面数据!$A$1:$BB$10000,MATCH($B7,账面数据!$A:$A,0),MATCH(BT$2,账面数据!$1:$1,0))} -> 0 | BU7: {=INDEX(账面数据!$A$1:$BB$10000,MATCH($B7,账面数据!$A:$A,0),MATCH(BU$2,账面数据!$1:$1,0))} -> 0 | BV7: {=INDEX(账面数据!$A$1:$BB$10000,MATCH($B7,账面数据!$A:$A,0),MATCH(BV$2,账面数据!$1:$1,0))} -> 0 | BW7: {=INDEX(账面数据!$A$1:$BB$10000,MATCH($B7,账面数据!$A:$A,0),MATCH(BW$2,账面数据!$1:$1,0))} -> 0 | BX7: {=INDEX(账面数据!$A$1:$BB$10000,MATCH($B7,账面数据!$A:$A,0),MATCH(BX$2,账面数据!$1:$1,0))} -> 0 | BY7: {=INDEX(账面数据!$A$1:$BB$10000,MATCH($B7,账面数据!$A:$A,0),MATCH(BY$2,账面数据!$1:$1,0))} -> 0 | BZ7: {=INDEX(账面数据!$A$1:$BB$10000,MATCH($B7,账面数据!$A:$A,0),MATCH(BZ$2,账面数据!$1:$1,0))} -> 0 | ... CQ7: {=INDEX(账面数据!$A$1:$BB$10000,MATCH($B7,账面数据!$A:$A,0),MATCH(CQ$2,账面数据!$1:$1,0))} -> 0 | CR7: =L7-T7-BC7-BF7-BM7-BN7+BQ7-BR7 -> -0.0020354018 | CS7: =M7-S7-BR7-BS7 -> 3.3105607e-10 | CT7: =AD7/K7*J7-P7 -> -2985719.8 | CU7: =AA7-AG7-BO7+BP7-BX7-BU7+BD7 -> 0.00097350776 | CV7: =N7*(1-AL7)-AB7 -> 1255133.6 | CW7: =(R7-AF7)/1.09*0.02-AK7 -> -25216.709 | CX7: =BC7+(CN7-CO7)-BQ7 -> 513046.79 | CY7: =L7/H7-AA7/Y7 -> -0.044143408 | CZ7: 1、分包方未足额验工计价； 2、施工多确认收入 | DA7: 1、8月1月前补充预缴税金销售额和抵扣额； 2、8月1日前应收账款-预收账款增值税调整至合同负债-预收账款增值税 | DB7: 已完成
A8: ='XX项目 (6)'!L4 -> 来源于“共享系统”系统管理-权限管理-人员管理 | B8: ='XX项目 (6)'!M4 -> 来源于“共享系统”系统管理-权限管理-人员管理 | C8: ='XX项目 (6)'!E4 -> 0 | D8: ='XX项目 (6)'!F4 -> 0 | E8: ='XX项目 (6)'!G4 -> 0 | F8: ='XX项目 (6)'!H4 -> 0 | G8: ='XX项目 (6)'!I4 -> 0 | H8: =SUM(C8:G8) -> 0 | I8: =C8/1.06+D8/1.09+E8/1.13+F8/1.06+G8/1.06 -> 0 | L8: ='XX项目 (6)'!G11 -> 0 | O8: ='XX项目 (6)'!S11 -> 0 | Q8: ='XX项目 (6)'!M11 -> 0 | T8: ='XX项目 (6)'!T11 -> 0 | U8: ='XX项目 (6)'!E5+'XX项目 (6)'!E6 -> 0 | V8: ='XX项目 (6)'!F5+'XX项目 (6)'!F6 -> 0 | W8: ='XX项目 (6)'!G5+'XX项目 (6)'!G6 -> 0 | X8: ='XX项目 (6)'!H5+'XX项目 (6)'!H6 -> 0 | Y8: =SUM(U8:X8) -> 0 | Z8: =U8/1.06+V8/1.09+W8/1.13+X8/1.06 -> 0 | AA8: ='XX项目 (6)'!G12+'XX项目 (6)'!G13 -> 0 | AC8: ='XX项目 (6)'!S12+'XX项目 (6)'!S13 -> 0 | AE8: ='XX项目 (6)'!M12+'XX项目 (6)'!M13 -> 0 | AG8: ='XX项目 (6)'!T12+'XX项目 (6)'!T13 -> 0 | AH8: ='XX项目 (6)'!I97 -> 0 | AI8: ='XX项目 (6)'!I98 -> 0 | AJ8: ='XX项目 (6)'!E93+'XX项目 (6)'!F93+'XX项目 (6)'!G93+'XX项目 (6)'!H93+'XX项目 (6)'!J93+'XX项目 (6)'!K93 -> 0 | AL8: ='XX项目 (6)'!K4 -> #DIV/0! | AM8: ='XX项目 (6)'!N4 -> 主合同编号中的单位 | AN8: ='XX项目 (6)'!O4 -> 实际管理单位 | AO8: ='XX项目 (6)'!S4 -> 0 | AP8: ='XX项目 (6)'!T4 -> 0 | AQ8: ='XX项目 (6)'!U4 -> 0 | AR8: ='XX项目 (6)'!V4 -> 0 | AS8: ='XX项目 (6)'!W4 -> 0 | AT8: ='XX项目 (6)'!X4 -> 0 | AV8: ='XX项目 (6)'!E128 -> #DIV/0! | AW8: =AV8/1.09 -> #DIV/0! | AX8: =AW8/#REF!*#REF! -> #DIV/0! | BA8: =(AU8-AY8)+(AX8-AU8/1.09) -> #DIV/0! | BB8: =AV8-AZ8 -> #DIV/0! | BC8: {=INDEX(账面数据!$A$1:$BB$10000,MATCH($B8,账面数据!$A:$A,0),MATCH(BC$2,账面数据!$1:$1,0))} -> #N/A | BD8: {=INDEX(账面数据!$A$1:$BB$10000,MATCH($B8,账面数据!$A:$A,0),MATCH(BD$2,账面数据!$1:$1,0))} -> #N/A | BE8: {=INDEX(账面数据!$A$1:$BB$10000,MATCH($B8,账面数据!$A:$A,0),MATCH(BE$2,账面数据!$1:$1,0))} -> #N/A | BF8: {=INDEX(账面数据!$A$1:$BB$10000,MATCH($B8,账面数据!$A:$A,0),MATCH(BF$2,账面数据!$1:$1,0))} -> #N/A | BG8: {=INDEX(账面数据!$A$1:$BB$10000,MATCH($B8,账面数据!$A:$A,0),MATCH(BG$2,账面数据!$1:$1,0))} -> #N/A | BH8: {=INDEX(账面数据!$A$1:$BB$10000,MATCH($B8,账面数据!$A:$A,0),MATCH(BH$2,账面数据!$1:$1,0))} -> #N/A | BI8: {=INDEX(账面数据!$A$1:$BB$10000,MATCH($B8,账面数据!$A:$A,0),MATCH(BI$2,账面数据!$1:$1,0))} -> #N/A | BJ8: {=INDEX(账面数据!$A$1:$BB$10000,MATCH($B8,账面数据!$A:$A,0),MATCH(BJ$2,账面数据!$1:$1,0))} -> #N/A | ... CQ8: {=INDEX(账面数据!$A$1:$BB$10000,MATCH($B8,账面数据!$A:$A,0),MATCH(CQ$2,账面数据!$1:$1,0))} -> #N/A | CR8: =L8-T8-BC8-BF8-BM8-BN8+BQ8-BR8 -> #N/A | CS8: =M8-S8-BR8-BS8 -> #N/A | CT8: =AD8/K8*J8-P8 -> #DIV/0! | CU8: =AA8-AG8-BO8+BP8-BX8-BU8+BD8 -> #N/A | CV8: =N8*(1-AL8)-AB8 -> #DIV/0! | CW8: =(R8-AF8)/1.09*0.02-AK8 -> 0 | CX8: =BC8+(CN8-CO8)-BQ8 -> #N/A | CY8: =L8/H8-AA8/Y8 -> #DIV/0!
A9: ='XX项目 (7)'!L4 -> 来源于“共享系统”系统管理-权限管理-人员管理 | B9: ='XX项目 (7)'!M4 -> 来源于“共享系统”系统管理-权限管理-人员管理 | C9: ='XX项目 (7)'!E4 -> 0 | D9: ='XX项目 (7)'!F4 -> 0 | E9: ='XX项目 (7)'!G4 -> 0 | F9: ='XX项目 (7)'!H4 -> 0 | G9: ='XX项目 (7)'!I4 -> 0 | H9: =SUM(C9:G9) -> 0 | I9: =C9/1.06+D9/1.09+E9/1.13+F9/1.06+G9/1.06 -> 0 | L9: ='XX项目 (7)'!G11 -> 0 | O9: ='XX项目 (7)'!S11 -> 0 | Q9: ='XX项目 (7)'!M11 -> 0 | T9: ='XX项目 (7)'!T11 -> 0 | U9: ='XX项目 (7)'!E5+'XX项目 (7)'!E6 -> 0 | V9: ='XX项目 (7)'!F5+'XX项目 (7)'!F6 -> 0 | W9: ='XX项目 (7)'!G5+'XX项目 (7)'!G6 -> 0 | X9: ='XX项目 (7)'!H5+'XX项目 (7)'!H6 -> 0 | Y9: =SUM(U9:X9) -> 0 | Z9: =U9/1.06+V9/1.09+W9/1.13+X9/1.06 -> 0 | AA9: ='XX项目 (7)'!G12+'XX项目 (7)'!G13 -> 0 | AC9: ='XX项目 (7)'!S12+'XX项目 (7)'!S13 -> 0 | AE9: ='XX项目 (7)'!M12+'XX项目 (7)'!M13 -> 0 | AG9: ='XX项目 (7)'!T12+'XX项目 (7)'!T13 -> 0 | AH9: ='XX项目 (7)'!I97 -> 0 | AI9: ='XX项目 (7)'!I98 -> 0 | AJ9: ='XX项目 (7)'!E93+'XX项目 (7)'!F93+'XX项目 (7)'!G93+'XX项目 (7)'!H93+'XX项目 (7)'!J93+'XX项目 (7)'!K93 -> 0 | AL9: ='XX项目 (7)'!K4 -> #DIV/0! | AM9: ='XX项目 (7)'!N4 -> 主合同编号中的单位 | AN9: ='XX项目 (7)'!O4 -> 实际管理单位 | AO9: ='XX项目 (7)'!S4 -> 0 | AP9: ='XX项目 (7)'!T4 -> 0 | AQ9: ='XX项目 (7)'!U4 -> 0 | AR9: ='XX项目 (7)'!V4 -> 0 | AS9: ='XX项目 (7)'!W4 -> 0 | AT9: ='XX项目 (7)'!X4 -> 0 | AV9: ='XX项目 (7)'!E128 -> #DIV/0! | AW9: =AV9/1.09 -> #DIV/0! | AX9: =AW9/#REF!*#REF! -> #DIV/0! | BA9: =(AU9-AY9)+(AX9-AU9/1.09) -> #DIV/0! | BB9: =AV9-AZ9 -> #DIV/0! | BC9: {=INDEX(账面数据!$A$1:$BB$10000,MATCH($B9,账面数据!$A:$A,0),MATCH(BC$2,账面数据!$1:$1,0))} -> #N/A | BD9: {=INDEX(账面数据!$A$1:$BB$10000,MATCH($B9,账面数据!$A:$A,0),MATCH(BD$2,账面数据!$1:$1,0))} -> #N/A | BE9: {=INDEX(账面数据!$A$1:$BB$10000,MATCH($B9,账面数据!$A:$A,0),MATCH(BE$2,账面数据!$1:$1,0))} -> #N/A | BF9: {=INDEX(账面数据!$A$1:$BB$10000,MATCH($B9,账面数据!$A:$A,0),MATCH(BF$2,账面数据!$1:$1,0))} -> #N/A | BG9: {=INDEX(账面数据!$A$1:$BB$10000,MATCH($B9,账面数据!$A:$A,0),MATCH(BG$2,账面数据!$1:$1,0))} -> #N/A | BH9: {=INDEX(账面数据!$A$1:$BB$10000,MATCH($B9,账面数据!$A:$A,0),MATCH(BH$2,账面数据!$1:$1,0))} -> #N/A | BI9: {=INDEX(账面数据!$A$1:$BB$10000,MATCH($B9,账面数据!$A:$A,0),MATCH(BI$2,账面数据!$1:$1,0))} -> #N/A | BJ9: {=INDEX(账面数据!$A$1:$BB$10000,MATCH($B9,账面数据!$A:$A,0),MATCH(BJ$2,账面数据!$1:$1,0))} -> #N/A | ... CQ9: {=INDEX(账面数据!$A$1:$BB$10000,MATCH($B9,账面数据!$A:$A,0),MATCH(CQ$2,账面数据!$1:$1,0))} -> #N/A | CR9: =L9-T9-BC9-BF9-BM9-BN9+BQ9-BR9 -> #N/A | CS9: =M9-S9-BR9-BS9 -> #N/A | CT9: =AD9/K9*J9-P9 -> #DIV/0! | CU9: =AA9-AG9-BO9+BP9-BX9-BU9+BD9 -> #N/A | CV9: =N9*(1-AL9)-AB9 -> #DIV/0! | CW9: =(R9-AF9)/1.09*0.02-AK9 -> 0 | CX9: =BC9+(CN9-CO9)-BQ9 -> #N/A | CY9: =L9/H9-AA9/Y9 -> #DIV/0!
A10: ='XX项目 (8)'!L4 -> 来源于“共享系统”系统管理-权限管理-人员管理 | B10: ='XX项目 (8)'!M4 -> 来源于“共享系统”系统管理-权限管理-人员管理 | C10: ='XX项目 (8)'!E4 -> 0 | D10: ='XX项目 (8)'!F4 -> 0 | E10: ='XX项目 (8)'!G4 -> 0 | F10: ='XX项目 (8)'!H4 -> 0 | G10: ='XX项目 (8)'!I4 -> 0 | H10: =SUM(C10:G10) -> 0 | I10: =C10/1.06+D10/1.09+E10/1.13+F10/1.06+G10/1.06 -> 0 | L10: ='XX项目 (8)'!G11 -> 0 | O10: ='XX项目 (8)'!S11 -> 0 | Q10: ='XX项目 (8)'!M11 -> 0 | T10: ='XX项目 (8)'!T11 -> 0 | U10: ='XX项目 (8)'!E5+'XX项目 (8)'!E6 -> 0 | V10: ='XX项目 (8)'!F5+'XX项目 (8)'!F6 -> 0 | W10: ='XX项目 (8)'!G5+'XX项目 (8)'!G6 -> 0 | X10: ='XX项目 (8)'!H5+'XX项目 (8)'!H6 -> 0 | Y10: =SUM(U10:X10) -> 0 | Z10: =U10/1.06+V10/1.09+W10/1.13+X10/1.06 -> 0 | AA10: ='XX项目 (8)'!G12+'XX项目 (8)'!G13 -> 0 | AC10: ='XX项目 (8)'!S12+'XX项目 (8)'!S13 -> 0 | AE10: ='XX项目 (8)'!M12+'XX项目 (8)'!M13 -> 0 | AG10: ='XX项目 (8)'!T12+'XX项目 (8)'!T13 -> 0 | AH10: ='XX项目 (8)'!I97 -> 0 | AI10: ='XX项目 (8)'!I98 -> 0 | AJ10: ='XX项目 (8)'!E93+'XX项目 (8)'!F93+'XX项目 (8)'!G93+'XX项目 (8)'!H93+'XX项目 (8)'!J93+'XX项目 (8)'!K93 -> 0 | AL10: ='XX项目 (8)'!K4 -> #DIV/0! | AM10: ='XX项目 (8)'!N4 -> 主合同编号中的单位 | AN10: ='XX项目 (8)'!O4 -> 实际管理单位 | AO10: ='XX项目 (8)'!S4 -> 0 | AP10: ='XX项目 (8)'!T4 -> 0 | AQ10: ='XX项目 (8)'!U4 -> 0 | AR10: ='XX项目 (8)'!V4 -> 0 | AS10: ='XX项目 (8)'!W4 -> 0 | AT10: ='XX项目 (8)'!X4 -> 0 | AV10: ='XX项目 (8)'!E128 -> #DIV/0! | AW10: =AV10/1.09 -> #DIV/0! | AX10: =AW10/#REF!*#REF! -> #DIV/0! | BA10: =(AU10-AY10)+(AX10-AU10/1.09) -> #DIV/0! | BB10: =AV10-AZ10 -> #DIV/0! | BC10: {=INDEX(账面数据!$A$1:$BB$10000,MATCH($B10,账面数据!$A:$A,0),MATCH(BC$2,账面数据!$1:$1,0))} -> #N/A | BD10: {=INDEX(账面数据!$A$1:$BB$10000,MATCH($B10,账面数据!$A:$A,0),MATCH(BD$2,账面数据!$1:$1,0))} -> #N/A | BE10: {=INDEX(账面数据!$A$1:$BB$10000,MATCH($B10,账面数据!$A:$A,0),MATCH(BE$2,账面数据!$1:$1,0))} -> #N/A | BF10: {=INDEX(账面数据!$A$1:$BB$10000,MATCH($B10,账面数据!$A:$A,0),MATCH(BF$2,账面数据!$1:$1,0))} -> #N/A | BG10: {=INDEX(账面数据!$A$1:$BB$10000,MATCH($B10,账面数据!$A:$A,0),MATCH(BG$2,账面数据!$1:$1,0))} -> #N/A | BH10: {=INDEX(账面数据!$A$1:$BB$10000,MATCH($B10,账面数据!$A:$A,0),MATCH(BH$2,账面数据!$1:$1,0))} -> #N/A | BI10: {=INDEX(账面数据!$A$1:$BB$10000,MATCH($B10,账面数据!$A:$A,0),MATCH(BI$2,账面数据!$1:$1,0))} -> #N/A | BJ10: {=INDEX(账面数据!$A$1:$BB$10000,MATCH($B10,账面数据!$A:$A,0),MATCH(BJ$2,账面数据!$1:$1,0))} -> #N/A | ... CQ10: {=INDEX(账面数据!$A$1:$BB$10000,MATCH($B10,账面数据!$A:$A,0),MATCH(CQ$2,账面数据!$1:$1,0))} -> #N/A | CR10: =L10-T10-BC10-BF10-BM10-BN10+BQ10-BR10 -> #N/A | CS10: =M10-S10-BR10-BS10 -> #N/A | CT10: =AD10/K10*J10-P10 -> #DIV/0! | CU10: =AA10-AG10-BO10+BP10-BX10-BU10+BD10 -> #N/A | CV10: =N10*(1-AL10)-AB10 -> #DIV/0! | CW10: =(R10-AF10)/1.09*0.02-AK10 -> 0 | CX10: =BC10+(CN10-CO10)-BQ10 -> #N/A | CY10: =L10/H10-AA10/Y10 -> #DIV/0!
A11: ='XX项目 (9)'!L4 -> 来源于“共享系统”系统管理-权限管理-人员管理 | B11: ='XX项目 (9)'!M4 -> 来源于“共享系统”系统管理-权限管理-人员管理 | C11: ='XX项目 (9)'!E4 -> 0 | D11: ='XX项目 (9)'!F4 -> 0 | E11: ='XX项目 (9)'!G4 -> 0 | F11: ='XX项目 (9)'!H4 -> 0 | G11: ='XX项目 (9)'!I4 -> 0 | H11: =SUM(C11:G11) -> 0 | I11: =C11/1.06+D11/1.09+E11/1.13+F11/1.06+G11/1.06 -> 0 | L11: ='XX项目 (9)'!G11 -> 0 | O11: ='XX项目 (9)'!S11 -> 0 | Q11: ='XX项目 (9)'!M11 -> 0 | T11: ='XX项目 (9)'!T11 -> 0 | U11: ='XX项目 (9)'!E5+'XX项目 (9)'!E6 -> 0 | V11: ='XX项目 (9)'!F5+'XX项目 (9)'!F6 -> 0 | W11: ='XX项目 (9)'!G5+'XX项目 (9)'!G6 -> 0 | X11: ='XX项目 (9)'!H5+'XX项目 (9)'!H6 -> 0 | Y11: =SUM(U11:X11) -> 0 | Z11: =U11/1.06+V11/1.09+W11/1.13+X11/1.06 -> 0 | AA11: ='XX项目 (9)'!G12+'XX项目 (9)'!G13 -> 0 | AC11: ='XX项目 (9)'!S12+'XX项目 (9)'!S13 -> 0 | AE11: ='XX项目 (9)'!M12+'XX项目 (9)'!M13 -> 0 | AG11: ='XX项目 (9)'!T12+'XX项目 (9)'!T13 -> 0 | AH11: ='XX项目 (9)'!I97 -> 0 | AI11: ='XX项目 (9)'!I98 -> 0 | AJ11: ='XX项目 (9)'!E93+'XX项目 (9)'!F93+'XX项目 (9)'!G93+'XX项目 (9)'!H93+'XX项目 (9)'!J93+'XX项目 (9)'!K93 -> 0 | AL11: ='XX项目 (9)'!K4 -> #DIV/0! | AM11: ='XX项目 (9)'!N4 -> 主合同编号中的单位 | AN11: ='XX项目 (9)'!O4 -> 实际管理单位 | AO11: ='XX项目 (9)'!S4 -> 0 | AP11: ='XX项目 (9)'!T4 -> 0 | AQ11: ='XX项目 (9)'!U4 -> 0 | AR11: ='XX项目 (9)'!V4 -> 0 | AS11: ='XX项目 (9)'!W4 -> 0 | AT11: ='XX项目 (9)'!X4 -> 0 | AV11: ='XX项目 (9)'!E128 -> #DIV/0! | AW11: =AV11/1.09 -> #DIV/0! | AX11: =AW11/#REF!*#REF! -> #DIV/0! | BA11: =(AU11-AY11)+(AX11-AU11/1.09) -> #DIV/0! | BB11: =AV11-AZ11 -> #DIV/0! | BC11: {=INDEX(账面数据!$A$1:$BB$10000,MATCH($B11,账面数据!$A:$A,0),MATCH(BC$2,账面数据!$1:$1,0))} -> #N/A | BD11: {=INDEX(账面数据!$A$1:$BB$10000,MATCH($B11,账面数据!$A:$A,0),MATCH(BD$2,账面数据!$1:$1,0))} -> #N/A | BE11: {=INDEX(账面数据!$A$1:$BB$10000,MATCH($B11,账面数据!$A:$A,0),MATCH(BE$2,账面数据!$1:$1,0))} -> #N/A | BF11: {=INDEX(账面数据!$A$1:$BB$10000,MATCH($B11,账面数据!$A:$A,0),MATCH(BF$2,账面数据!$1:$1,0))} -> #N/A | BG11: {=INDEX(账面数据!$A$1:$BB$10000,MATCH($B11,账面数据!$A:$A,0),MATCH(BG$2,账面数据!$1:$1,0))} -> #N/A | BH11: {=INDEX(账面数据!$A$1:$BB$10000,MATCH($B11,账面数据!$A:$A,0),MATCH(BH$2,账面数据!$1:$1,0))} -> #N/A | BI11: {=INDEX(账面数据!$A$1:$BB$10000,MATCH($B11,账面数据!$A:$A,0),MATCH(BI$2,账面数据!$1:$1,0))} -> #N/A | BJ11: {=INDEX(账面数据!$A$1:$BB$10000,MATCH($B11,账面数据!$A:$A,0),MATCH(BJ$2,账面数据!$1:$1,0))} -> #N/A | ... CQ11: {=INDEX(账面数据!$A$1:$BB$10000,MATCH($B11,账面数据!$A:$A,0),MATCH(CQ$2,账面数据!$1:$1,0))} -> #N/A | CR11: =L11-T11-BC11-BF11-BM11-BN11+BQ11-BR11 -> #N/A | CS11: =M11-S11-BR11-BS11 -> #N/A | CT11: =AD11/K11*J11-P11 -> #DIV/0! | CU11: =AA11-AG11-BO11+BP11-BX11-BU11+BD11 -> #N/A | CV11: =N11*(1-AL11)-AB11 -> #DIV/0! | CW11: =(R11-AF11)/1.09*0.02-AK11 -> 0 | CX11: =BC11+(CN11-CO11)-BQ11 -> #N/A | CY11: =L11/H11-AA11/Y11 -> #DIV/0!
A12: ='XX项目 (10)'!L4 -> 来源于“共享系统”系统管理-权限管理-人员管理 | B12: ='XX项目 (10)'!M4 -> 来源于“共享系统”系统管理-权限管理-人员管理 | C12: ='XX项目 (10)'!E4 -> 0 | D12: ='XX项目 (10)'!F4 -> 0 | E12: ='XX项目 (10)'!G4 -> 0 | F12: ='XX项目 (10)'!H4 -> 0 | G12: ='XX项目 (10)'!I4 -> 0 | H12: =SUM(C12:G12) -> 0 | I12: =C12/1.06+D12/1.09+E12/1.13+F12/1.06+G12/1.06 -> 0 | L12: ='XX项目 (10)'!G11 -> 0 | O12: ='XX项目 (10)'!S11 -> 0 | Q12: ='XX项目 (10)'!M11 -> 0 | T12: ='XX项目 (10)'!T11 -> 0 | U12: ='XX项目 (10)'!E5+'XX项目 (10)'!E6 -> 0 | V12: ='XX项目 (10)'!F5+'XX项目 (10)'!F6 -> 0 | W12: ='XX项目 (10)'!G5+'XX项目 (10)'!G6 -> 0 | X12: ='XX项目 (10)'!H5+'XX项目 (10)'!H6 -> 0 | Y12: =SUM(U12:X12) -> 0 | Z12: =U12/1.06+V12/1.09+W12/1.13+X12/1.06 -> 0 | AA12: ='XX项目 (10)'!G12+'XX项目 (10)'!G13 -> 0 | AC12: ='XX项目 (10)'!S12+'XX项目 (10)'!S13 -> 0 | AE12: ='XX项目 (10)'!M12+'XX项目 (10)'!M13 -> 0 | AG12: ='XX项目 (10)'!T12+'XX项目 (10)'!T13 -> 0 | AH12: ='XX项目 (10)'!I97 -> 0 | AI12: ='XX项目 (10)'!I98 -> 0 | AJ12: ='XX项目 (10)'!E93+'XX项目 (10)'!F93+'XX项目 (10)'!G93+'XX项目 (10)'!H93+'XX项目 (10)'!J93+'XX项目 (10)'!K93 -> 0 | AL12: ='XX项目 (10)'!K4 -> #DIV/0! | AM12: ='XX项目 (10)'!N4 -> 主合同编号中的单位 | AN12: ='XX项目 (10)'!O4 -> 实际管理单位 | AO12: ='XX项目 (10)'!S4 -> 0 | AP12: ='XX项目 (10)'!T4 -> 0 | AQ12: ='XX项目 (10)'!U4 -> 0 | AR12: ='XX项目 (10)'!V4 -> 0 | AS12: ='XX项目 (10)'!W4 -> 0 | AT12: ='XX项目 (10)'!X4 -> 0 | AV12: ='XX项目 (10)'!E128 -> #DIV/0! | AW12: =AV12/1.09 -> #DIV/0! | AX12: =AW12/#REF!*#REF! -> #DIV/0! | BA12: =(AU12-AY12)+(AX12-AU12/1.09) -> #DIV/0! | BB12: =AV12-AZ12 -> #DIV/0! | BC12: {=INDEX(账面数据!$A$1:$BB$10000,MATCH($B12,账面数据!$A:$A,0),MATCH(BC$2,账面数据!$1:$1,0))} -> #N/A | BD12: {=INDEX(账面数据!$A$1:$BB$10000,MATCH($B12,账面数据!$A:$A,0),MATCH(BD$2,账面数据!$1:$1,0))} -> #N/A | BE12: {=INDEX(账面数据!$A$1:$BB$10000,MATCH($B12,账面数据!$A:$A,0),MATCH(BE$2,账面数据!$1:$1,0))} -> #N/A | BF12: {=INDEX(账面数据!$A$1:$BB$10000,MATCH($B12,账面数据!$A:$A,0),MATCH(BF$2,账面数据!$1:$1,0))} -> #N/A | BG12: {=INDEX(账面数据!$A$1:$BB$10000,MATCH($B12,账面数据!$A:$A,0),MATCH(BG$2,账面数据!$1:$1,0))} -> #N/A | BH12: {=INDEX(账面数据!$A$1:$BB$10000,MATCH($B12,账面数据!$A:$A,0),MATCH(BH$2,账面数据!$1:$1,0))} -> #N/A | BI12: {=INDEX(账面数据!$A$1:$BB$10000,MATCH($B12,账面数据!$A:$A,0),MATCH(BI$2,账面数据!$1:$1,0))} -> #N/A | BJ12: {=INDEX(账面数据!$A$1:$BB$10000,MATCH($B12,账面数据!$A:$A,0),MATCH(BJ$2,账面数据!$1:$1,0))} -> #N/A | ... CQ12: {=INDEX(账面数据!$A$1:$BB$10000,MATCH($B12,账面数据!$A:$A,0),MATCH(CQ$2,账面数据!$1:$1,0))} -> #N/A | CR12: =L12-T12-BC12-BF12-BM12-BN12+BQ12-BR12 -> #N/A | CS12: =M12-S12-BR12-BS12 -> #N/A | CT12: =AD12/K12*J12-P12 -> #DIV/0! | CU12: =AA12-AG12-BO12+BP12-BX12-BU12+BD12 -> #N/A | CV12: =N12*(1-AL12)-AB12 -> #DIV/0! | CW12: =(R12-AF12)/1.09*0.02-AK12 -> 0 | CX12: =BC12+(CN12-CO12)-BQ12 -> #N/A | CY12: =L12/H12-AA12/Y12 -> #DIV/0!
H13: =SUM(C13:G13) -> 0 | I13: =C13/1.06+D13/1.09+E13/1.13+F13/1.06+G13/1.06 -> 0 | Y13: =SUM(U13:X13) -> 0 | Z13: =U13/1.06+V13/1.09+W13/1.13+X13/1.06 -> 0
H14: =SUM(C14:G14) -> 0 | I14: =C14/1.06+D14/1.09+E14/1.13+F14/1.06+G14/1.06 -> 0 | Y14: =SUM(U14:X14) -> 0 | Z14: =U14/1.06+V14/1.09+W14/1.13+X14/1.06 -> 0
H15: =SUM(C15:G15) -> 0 | I15: =C15/1.06+D15/1.09+E15/1.13+F15/1.06+G15/1.06 -> 0 | Y15: =SUM(U15:X15) -> 0 | Z15: =U15/1.06+V15/1.09+W15/1.13+X15/1.06 -> 0
H16: =SUM(C16:G16) -> 0 | I16: =C16/1.06+D16/1.09+E16/1.13+F16/1.06+G16/1.06 -> 0 | Y16: =SUM(U16:X16) -> 0 | Z16: =U16/1.06+V16/1.09+W16/1.13+X16/1.06 -> 0
H17: =SUM(C17:G17) -> 0 | I17: =C17/1.06+D17/1.09+E17/1.13+F17/1.06+G17/1.06 -> 0 | Y17: =SUM(U17:X17) -> 0 | Z17: =U17/1.06+V17/1.09+W17/1.13+X17/1.06 -> 0
H18: =SUM(C18:G18) -> 0 | I18: =C18/1.06+D18/1.09+E18/1.13+F18/1.06+G18/1.06 -> 0 | Y18: =SUM(U18:X18) -> 0 | Z18: =U18/1.06+V18/1.09+W18/1.13+X18/1.06 -> 0
H19: =SUM(C19:G19) -> 0 | I19: =C19/1.06+D19/1.09+E19/1.13+F19/1.06+G19/1.06 -> 0 | Y19: =SUM(U19:X19) -> 0 | Z19: =U19/1.06+V19/1.09+W19/1.13+X19/1.06 -> 0
H20: =SUM(C20:G20) -> 0 | I20: =C20/1.06+D20/1.09+E20/1.13+F20/1.06+G20/1.06 -> 0 | Y20: =SUM(U20:X20) -> 0 | Z20: =U20/1.06+V20/1.09+W20/1.13+X20/1.06 -> 0 | AW20: =AU20/1.09 -> 0 | AX20: =AW20/#REF!*#REF! -> #REF! | BA20: =(AU20-AY20)+(AX20-AU20/1.09) -> #REF! | BB20: =AV20-AZ20 -> 0

Sheet 账面数据
A1: 项目名称 | B1: 1122应收账款 | C1: 1123预付款项 | D1: 1221其他应收款 | E1: 1221-04-03其他应收款-民工工资保证金 | F1: 1221-05其他应收款-预付款项转入 | G1: 1221-09其他应收款-应收押金 | H1: 1221-11其他应收款-应收押金 | I1: 1221-99其他应收款-其他 | J1: 1231坏账准备 | K1: 1484合同资产减值准备 | L1: 1483合同资产 | M1: 1531长期应收款 | N1: 2202应付账款 | O1: 2202-12应付账款-预付账款增值税 | P1: 2204合同负债 | Q1: 2204-10合同负债-预收账款增值税 | R1: 2221-06应交税费-待转销项税额 | S1: 2241其他应付款 | T1: 2241-01其他应付款-保证金 | U1: 2241-05其他应付款-应付押金 | V1: 2241-99其他应付款-其他 | W1: 2701长期应付款 | X1: 2701-05长期应付款-应付质量保证金 | Y1: 2701-99长期应付款-其他 | Z1: 5601-01-01-01合同履约成本-工程施工-合同成本-直接人工费（期末数） | AA1: 5601-01-01-02合同履约成本-工程施工-合同成本-直接材料费（期末数） | AB1: 5601-01-01-04合同履约成本-工程施工-合同成本-劳务成本（期末数） | AC1: 5601-01-01-05合同履约成本-工程施工-合同成本-专业分包成本（期末数） | AD1: 5601-01-01-06合同履约成本-工程施工-合同成本-其他直接费用（期末数） | AE1: 5601-01-01-07合同履约成本-工程施工-合同成本-间接费用转入（期末数） | AF1: 5601-01-01-01合同履约成本-工程施工-合同成本-直接人工费（当年借方发生数） | AG1: 5601-01-01-02合同履约成本-工程施工-合同成本-直接材料费（当年借方发生数） | AH1: 5601-01-01-04合同履约成本-工程施工-合同成本-劳务成本（当年借方发生数） | AI1: 5601-01-01-05合同履约成本-工程施工-合同成本-专业分包成本（当年借方发生数） | AJ1: 5601-01-01-06合同履约成本-工程施工-合同成本-其他直接费用（当年借方发生数） | AK1: 5601-01-01-07合同履约成本-工程施工-合同成本-间接费用转入（当年借方发生数） | AL1: 5601-02合同履约成本-劳务成本（当年借方发生数） | AM1: 5801-01合同结算-收入结转 | AN1: 5801-02合同结算-价款结算 | AO1: 6001主营业务收入（当年贷方发生数） | AP1: 6401主营业务成本（当年借方发生数）
A2: 2022年东部环线枢纽铁路红线内公网覆盖项目设计施工总包联合 | B2: 4673398 | N2: 6473652.8 | P2: 45988566 | Q2: -4110384 | AC2: 65003844 | AD2: 252289.31 | AE2: 157598.63 | AM2: 68690666 | AN2: 27465637
A3: 2022年西工区老旧小区改造提质EPC项目（四标段） | B3: -12000000 | P3: 1001834.9 | Q3: -1098165.1 | R3: 0 | AC3: 11835780 | AE3: 947 | AM3: 12201835
A4: 2022年西工区老旧小区改造提质项目（四标段)EPC工程总承包合同 | P4: -49541.28 | Q4: -49541.28
A5: 2023年中国电信贵州公司贵广高铁贵州段公网覆盖扩容改造工程设计施工服务总承包采购 | B5: 2532770.9 | P5: 64457.42 | Q5: -6576.15 | R5: 0 | AA5: 3143639.8 | AC5: 5969487.2 | AE5: 8412 | AM5: 6283670.7 | AN5: 12676352
A6: 2024年渝湘高铁（重庆东至黔江段）红线内公网覆盖项目设计施工总包联合采购 | B6: 0 | N6: 7766050 | P6: 17778790 | Q6: -1711824.5 | R6: 102507.72 | AC6: 16299128 | AD6: 356066.04 | AE6: 323349.7 | AM6: 16803225
A7: 318大桥及相关工程EPC | P7: 632463.83 | Q7: 0
A8: B208-B号项目(EPC工程总承包) | B8: 1422295.3 | N8: 678049.72 | Q8: 0 | R8: 0 | W8: 673130.77 | AC8: 20585039 | AE8: 347240.46 | AM8: 22165297 | AN8: 22165297
A9: B208-民航院-2022-001号项目(EPC工程总承包) | B9: 8405313 | N9: 8552520.3 | Q9: 0 | R9: 737304.37 | W9: 1425368.4 | AC9: 42063613 | AM9: 43589236 | AN9: 43589236
A10: B208-土建三院-2020-001号项目(EPC工程总承包) | B10: 74736.28 | N10: 1813597.9 | Q10: 0 | R10: 0.01 | AC10: 31521539 | AE10: 349428.56 | AM10: 33031780 | AN10: 33031780
A11: CRECG-民航院-2023-01 | B11: 12144687 | C11: 0 | L11: 3036171.7 | M11: 0 | N11: 10204150 | Q11: 0 | R11: 1253465.4 | AA11: 16005604 | AC11: 63622546 | AE11: 24306.67 | AM11: 82859221 | AN11: 92849287
A12: G331线青河至富蕴至阿勒泰段公路建设项目（EPC模式）（四标段） | B12: 21137831 | C12: 0 | L12: 21795131 | M12: 0 | N12: 23190681 | P12: -25000 | Q12: 0 | W12: 21206663 | AC12: 6.4852179e+08 | AE12: 718592.4 | AM12: 6.6651777e+08 | AN12: 6.6651777e+08
A13: G347无为市通江大道快速化改造工程及S330六芜路福渡段快速化改造工程 | B13: 1.598801e+08 | M13: 72771174 | N13: 1.3975362e+08 | Q13: 0 | R13: 26621722 | W13: 91774255 | AB13: 213961 | AC13: 8.9726651e+08 | AE13: 1696888 | AM13: 9.1984496e+08 | AN13: 9.1740234e+08
A14: S205利州区河西街道办事处（杨家岩）至下西街道办事处（（塔山湾）段改建工程（下穿广元铁路集装箱运输组货中心段）项目勘察设计施工一体化总承包（EPC） | B14: 16287624 | C14: 9681349 | M14: 2689146 | N14: 31202633 | P14: 0.69 | Q14: 0 | AC14: 97786543 | AE14: 132192.89 | AM14: 1.0081087e+08 | AN14: 1.0081087e+08
A15: S205利州区河西街道办事处（杨家岩）至下西街道办事处（塔山湾）段改建工程（下穿广元铁路集装箱运输组货中心段）勘察设计施工一体化总承包（EPC） | Q15: 0 | AE15: 3720.13
A16: 安宁工业园区大宗工业物资公铁联运物流园项目涉铁部分（铁路专用线部分）工程设计施工总承包 | B16: 16829786 | N16: 6010934 | P16: 55523276 | Q16: -4476723.5 | R16: 9917541.7 | AC16: 1.6156044e+08 | AM16: 1.7278988e+08 | AN16: 1.7278988e+08
A17: 成达万高铁遂宁市范围内三电及管线迁改EPC | B17: 72516056 | C17: 0 | M17: 6761405.2 | N17: 68925268 | Q17: 0 | R17: 6545845.4 | W17: 5224809.8 | AB17: 431625.33 | AC17: 1.9436455e+08 | AE17: 512269.54 | AM17: 2.046089e+08 | AN17: 2.067708e+08
A18: 成达万铁路资阳段三电及地下、地面管线迁改项目 | B18: 13549888 | C18: 3086596 | M18: 5511504.3 | N18: 14293337 | P18: 1730189.8 | Q18: 0 | R18: 2806051.3 | W18: 2727481.8 | AC18: 1.6270463e+08 | AE18: 2551.09 | AM18: 1.6795316e+08 | AN18: 1.6854753e+08
A19: 成都市双流区滨河路下穿成昆铁路立交工程项目EPC总承包合同 | B19: 7506154.8 | N19: 6878062.4 | Q19: 0 | R19: 619774.26 | Z19: 36841.47 | AB19: 98965.77 | AC19: 21033830 | AE19: 79970.76 | AM19: 22862859 | AN19: 22890382
A20: 成都天府国际机场PRT项目部 | C20: -85077 | N20: 4880868 | Q20: 0 | R20: 188200.15 | Z20: 48143.39 | AA20: 76639160 | AB20: 133104.12 | AC20: 427064.22 | AE20: 1789703.6
A21: 成昆复线冕宁站站前广场项目等6个项目集（EPC） | B21: 77093170 | N21: 76962832 | Q21: 0 | R21: 6472471.9 | AC21: 2.4951234e+08 | AE21: 101742.2 | AM21: 2.5630773e+08 | AN21: 2.5127124e+08
A22: 成绵乐高铁峨九路立交道岔特大桥桥梁景观工程及峨九路下穿坡道侧壁改造工程EPC | P22: 173000 | Q22: 0
A23: 成渝铁路重庆站至江津站段改造工程高等级管线迁改 | B23: 14921.55 | M23: 301963.2 | N23: 2292256.9 | P23: 12984546 | Q23: -1168609.1 | R23: 39854.28 | AC23: 15603193 | AE23: 64081.73 | AM23: 16959992 | AN23: 9993497.1
A24: 成渝中线高铁成都段三电及管线迁改工程总包项目 | B24: 10018101 | C24: 5830345.8 | M24: 5388191.4 | N24: 38933198 | P24: 6202495.6 | Q24: 0 | R24: 2965811.8 | W24: 5286576.7 | AB24: 72028.46 | AC24: 1.6166901e+08 | AE24: 260883.77 | AM24: 1.6701959e+08 | AN24: 1.6476732e+08
A25: 成渝中线铁路（含十陵南站）资阳段三电及管线迁改总包 | B25: 92191183 | M25: 6827228.3 | N25: 91247709 | P25: 2307470.2 | Q25: 0 | R25: 8340969.8 | W25: 6613877.5 | AC25: 2.0225925e+08 | AE25: 33663.37 | AM25: 2.0851469e+08 | AN25: 2.0878374e+08
A26: 城东区养老示范基地市政管线下穿国家粮食和物资储备局青海局535处铁路专用防护涵工程（设计、采购、施工）EPC项目（待院签） | B26: 0 | N26: 1906920.1 | Q26: 0 | R26: 0 | AC26: 1749468 | AM26: 7889709.2 | AN26: 7413873.3
A27: 城口县东部新区配套基础设施建设项目（一期）巴山大道、冲沟治理工程和城口高铁站前广场及配套设施项目打捆EPC总承包 | B27: 1500050 | Q27: 0 | R27: 0 | AB27: 749724.96 | AE27: 1447976.2 | AL27: 1607594.7
A28: 齿轨列车试验线建设项目工程总承包 | M28: 829800 | N28: 710350.17 | Q28: 0 | AA28: 7676281.2 | AC28: 12990826 | AE28: 51663.07 | AM28: 12990826 | AN28: 12990826
A29: 川藏铁路天府站至朝阳湖“三电”迁改项目总承包EPC | B29: 21292704 | C29: 4647254.5 | M29: 3722241.8 | N29: 24508888 | P29: 4943887.8 | Q29: 0 | R29: 2048940.5 | W29: 3498907.3 | AB29: 187340.48 | AC29: 1.0700022e+08 | AE29: 359462.23 | AM29: 1.1035597e+08 | AN29: 1.1383003e+08
A30: 川南城际铁路临港高铁站片区基础设施项目-嘉信路立交工程勘察设计施工 | B30: 14453830 | N30: 13174417 | Q30: 0 | R30: 1193435.5 | AC30: 62913777 | AE30: 15948.11 | AM30: 65535184 | AN30: 66205349
A31: 达州城区智能交通系统项目 | Q31: 0 | AC31: 1019912.6
A32: 达州市中心城区道路交通安全设施运维服务 | Q32: 0 | AA32: 2247656.8 | AC32: 4874066.7 | AL32: 2661941.5
A33: 大理州集中建园贝特瑞片区工程设施建设项目（第1标段：三通一平工程）建设项目 | B33: 1.4112537e+08 | M33: 13699259 | N33: 1.2438244e+08 | P33: 14000000 | Q33: 0 | R33: 11627722 | W33: 13397201 | AC33: 4.0970033e+08 | AD33: 461037.73 | AE33: 1254355.9 | AM33: 4.1876663e+08 | AN33: 4.189376e+08
A34: 大理州集中建园材料新能源产业片区基础设施建设项目（一期）工程总承包合同 | B34: 92386595 | L34: 8675790.6 | M34: 0 | N34: 89233758 | Q34: 0 | R34: 10408821 | W34: 8420850 | AC34: 2.5751835e+08 | AD34: 331226.41 | AE34: 496905.66 | AM34: 2.6412138e+08 | AN34: 2.653147e+08
A35: 大丽铁路公网通信覆盖工程EPC项目 | Q35: 0 | AA35: 300540.92 | AC35: 56708370 | AE35: 114984.04 | AM35: 26821503 | AN35: 26912467
A36: 大沙坝油库铁路专用线扩能改造项目EPC | P36: 6728807.3 | Q36: -951192.66 | AE36: 23466.88
A37: 岱阳大街下穿京沪铁路立交桥改建工程总承包（EPC） | C37: 25000000 | P37: 67156679 | Q37: 0 | AE37: 2516817.5
A38: 钒钛高新区物流园主干道北延线 | B38: 15101120 | L38: 1107107 | M38: 0 | N38: 14194506 | Q38: 0 | R38: 956716.21 | W38: 1667660.1 | AC38: 49775459 | AE38: 97288.35 | AM38: 51580787 | AN38: 51580787
A39: 防东高铁（红线内）公网覆盖工程设计施工总承包项目 | B39: 398813.95 | Q39: 0 | R39: 32929.59 | AA39: 880927.72 | AC39: 1396515.1 | AE39: 5078.57 | AM39: 1464828.5 | AN39: 1829421.8
A40: 非生产性工业用房及附属设施（中铁轨道交通高科技产业园1号地块）三期设计-施工总承包II标段 | B40: 5618759.5 | L40: 1195419.1 | M40: 0 | N40: 9496125.3 | Q40: 0 | R40: 176449.82 | W40: 1322316.2 | AB40: 483940.05 | AC40: 40437805 | AE40: 69299.03 | AM40: 43248989 | AN40: 36556993
A41: 非生产性工业用房及附属设施（中铁轨道交通高科技产业园1号地块）三期设计-施工总承包I标段 | B41: 7380233.7 | L41: 573145.77 | M41: 0 | N41: 8738640.1 | Q41: 0 | R41: 1101630.4 | W41: 3737288.6 | AC41: 1.1429017e+08 | AE41: 41694.48 | AM41: 1.2223548e+08 | AN41: 1.2223548e+08
A42: 非生产性工业用房及配套设施（中铁轨道交通高科技产业园3号地块）二期设计-施工总承包Ⅰ标段 | P42: 5107544.6 | Q42: -459679.01 | AE42: 924.53
A43: 高速公路公安交通管理监控二期系统（后台、传输、指挥中心）运行维护项目 | Q43: 0 | AD43: 44617.92 | AL43: 2121698.1
A44: 广安市枣山片区与物流片区连接线工程勘察设计施工总承包项目 | P44: 9174311.9 | Q44: -825688.07 | AB44: 64046.9 | AC44: 1.7382064e+08 | AE44: 8918683.8 | AM44: 1.8292666e+08 | AN44: 1.7375235e+08
A45: 广佛地铁佛山段出入口紧急维护项目工程总承包 | Q45: 0 | AA45: 296220.79 | AC45: 642201.84 | AE45: 46485.83 | AM45: 1100254.3 | AN45: 1100254.3
A46: 广佛地铁夏南车辆段出入段线增设声屏障工程设计采购施工总承包（EPC) | B46: -316375.19 | C46: 3159486.8 | N46: 3536817.2 | O46: 270330.28 | P46: 2872489 | Q46: -286997.78 | AA46: 3374341.2 | AC46: 1707750.6 | AE46: 165456.02 | AM46: 2073837.4 | AN46: 2310529.1
A47: 广佛地铁专用视频监控系统升级改造及重点部位视频监控加装项目工程设计采购施工总承包（EPC) | B47: 5602602 | N47: 35456.63 | Q47: 0 | AA47: 51043916 | AE47: 470662.29
A48: 广西交投桂东多式联运示范工程（广西梧州新港铁路投资有限公司铁路专用线改扩建工程）EPC总承包 | B48: 5941617.2 | C48: 3822377.8 | N48: 7117800.1 | P48: 3204390 | Q48: 0 | AA48: 4595689.4 | AC48: 19097364 | AE48: 58623.67 | AM48: 19205545 | AN48: 19329075
A49: 贵阳南西联络线防护栅栏改扩建工程设计施工总承包项目 | B49: 725544.15 | N49: 731927.19 | Q49: 0 | R49: 59907.32 | AC49: 4408480.8 | AM49: 4437578.9 | AN49: 4437578.9
A50: 贵阳铁路枢纽都拉营新建货运战场专用线战后工程总承包项目 | Q50: 0 | AA50: 1261062
A51: 贵阳综合保税区口岸延伸监管区建设项目（一期）勘察设计施工总承包（EPC） | B51: 44248176 | M51: 4394299.5 | N51: 51262367 | Q51: 0 | AC51: 1.239581e+08 | AE51: 29259.55 | AM51: 1.2779186e+08 | AN51: 1.2779186e+08
A52: 贵州能源水城铁路专用线项目设计施工总承包 | B52: 95173750 | C52: 47890228 | M52: 23002448 | N52: 24965834 | P52: 32165822 | Q52: 0 | R52: 0 | AC52: 64112494 | AE52: 72806.55 | AM52: 66313573 | AN52: 2.1103163e+08
A53: 贵州众一金彩黔织金煤炭运输铁路专用线 | Q53: 0 | AC53: 58282461 | AE53: 911883.02 | AM53: 69153396 | AN53: 69153396
A54: 国电安顺发电有限公司2020年铁路专用线改造EPC工程 | Q54: 0 | AC54: 15525453 | AE54: 297052.18 | AM54: 15687077 | AN54: 15687077
A55: 国能费县热源长输供热管网工程（下穿鲁南高铁新建保护套管）总承包 | B55: 229055 | N55: 845624 | P55: -116.01 | Q55: -116.01 | R55: 116.01 | AC55: 3879005.5 | AM55: 4443922.9 | AN55: 4443922.9
A56: 海南省三亚市崖州区崖州路跨铁路桥工程EPC项目 | B56: 38704.5 | Q56: 0
A57: 海南省三亚市亚洲区崖州路跨铁路桥工程EPC项目 | Q57: 0 | AE57: 8874.51
A58: 汉源县黄家沟山洪灾害治理工程等9个建设项目 | B58: -18484915 | C58: 7307502 | L58: 1811403.8 | M58: 0 | N58: 34657303 | P58: -632785.47 | Q58: -1526784.5 | W58: 2925764.6 | AC58: 89472923 | AE58: 81151.68 | AM58: 92005175 | AN58: 55394613
A59: 杭新景高速公路桐庐服务区“平急两用”改扩建项目设计采购施工（EPC）工程总承包 | B59: 1082041.5 | C59: 19228562 | M59: 5821262.8 | N59: 9778636.4 | O59: 1587679.4 | P59: 13694780 | Q59: -1232530.2 | AC59: 50054783 | AE59: 20776.98 | AM59: 61118329 | AN59: 61118329
A60: 贺州市平桂立交工程EPC | C60: 2783027 | Q60: 0
A61: 湖雍铁路K6+190-+520段增设防护设施工程设计、施工总承包合同 | B61: 732136.32 | L61: 921998.01 | M61: 0 | N61: 969517.67 | Q61: 0 | W61: 684616.56 | AC61: 33587869 | AM61: 33587869 | AN61: 33587869
A62: 花溪水库至南郊、中曹水厂输水工程--管道下穿鑫中路工程设计施工总承包合同 | B62: 1558702.5 | N62: 1558702.5 | Q62: 0 | AC62: 6507822 | AM62: 6507822 | AN62: 6507822
A63: 华电章丘发电有限公司铁路专用线厂内站信号设备升级改造项目 | B63: 0 | L63: 202818 | N63: 6170600 | Q63: 0 | R63: 0 | AA63: 2860531 | AC63: 2695596.3 | AE63: 1960.4 | AM63: 2695596.3 | AN63: 2695596.3
A64: 黄桶至百色铁路”三电“及管线迁改设计施工总承包 | B64: -17491986 | C64: 31984000 | P64: 33880000 | Q64: 0
A65: 济莱高铁沿线车站综合配套建设项目工程总承包（EPC） | N65: 9584.08 | O65: 9584.08 | Q65: 0 | AC65: 6.291519e+08 | AE65: 4536866.1 | AM65: 6.5316532e+08 | AN65: 6.5541089e+08
A66: 江口供电局其他业务用房EPC项目 | P66: -44683.28 | Q66: -44683.28 | R66: 44683.28
A67: 江口供电局其他业务用房勘察设计采购施工总承包(EPC) | B67: 647115.33 | Q67: 0 | R67: 51610.04 | AA67: 1961891.2 | AC67: 30436194 | AE67: 155780.18 | AM67: 30691959 | AN67: 30304926
A68: 江西美扬智慧农业发展有限公司南城县年产80万只乐平湖羊全产业链项目（一期）EPC工程 | Q68: 0 | AE68: 94218.07
A69: 金华至义乌铁路三、四线及引入相关工程（金东段）市政综合管线迁改工程设计施工总承包 | B69: 20299542 | C69: 13814209 | M69: 966847.84 | N69: 34291789 | O69: 1140622.8 | Q69: 0 | R69: 1705842.7 | AC69: 59134425 | AE69: 63980.88 | AM69: 59134425 | AN69: 59134425
A70: 阆中火车站站前广场及地下空间EPC | B70: 17719200 | Q70: 0 | R70: 465393.8
A71: 丽江城市综合轨道交通项目 | B71: 7559402.6 | C71: 1000000 | L71: 59991359 | M71: 0 | N71: 9699699 | P71: 1000000 | Q71: 0 | R71: 7149724 | W71: 55039033 | Z71: 96298.38 | AA71: 24601096 | AB71: 1260469.4 | AC71: 1.7327118e+09 | AE71: 3607376.6 | AM71: 1.8194147e+09 | AN71: 1.8345982e+09
A72: 临海站停车场及配套工程（一期）EPC项目 | B72: 55977742 | N72: 54298407 | Q72: 0 | R72: 3520484.3 | AC72: 2.3264002e+08 | AE72: 189641.63 | AM72: 2.3983507e+08 | AN72: 2.3983507e+08
A73: 临沂市大山路下穿兖石铁路洪沟崖大桥防护工程 | B73: 2639425 | C73: 1792838.6 | P73: 2663833.1 | Q73: 0 | R73: 248708 | AC73: 4885090.3 | AE73: 1273640.7 | AM73: 6699768.6 | AN73: 8156564.4
A74: 临沂市通达南路取直项目铁路道口改造工程EPC总承包项目 | P74: 6121926.3 | Q74: 0 | AE74: 18445.95
A75: 临沂市沂河路上跨华能临沂电厂铁路专用线立交桥工程道口改造项目总承包(EPC) | B75: 0 | C75: 279653 | N75: 499616 | P75: 628061 | Q75: 0 | R75: -51858.23 | AC75: 13508273 | AE75: 486752.56 | AM75: 17673900 | AN75: 17402348
A76: 临沂市沂州路污水管道下穿兖石铁路新建保护套管工程 | B76: 333953 | N76: 204000 | Q76: 0 | R76: -4128.44
A77: 六盘水市德宏路二期工程二标段勘察设计施工总承包工程 | B77: 14484861 | N77: 12974469 | Q77: 0 | AC77: -6300864 | AE77: 1863.25 | AM77: -6702251.4
A78: 六盘水市钢城大道（南干线至水南互通段）道路工程—下穿沪昆铁路段工程勘察、设计、施工（EPC）总承包 | B78: 23243741 | N78: 26063676 | Q78: 0 | R78: 1716501.9 | Z78: 10554.37 | AC78: 77048327 | AE78: 1951269.4 | AM78: 79186358 | AN78: 77322055
A79: 龙口市西热东进供热管网下穿大莱龙铁路进港线保护涵工程EPC | B79: 392940 | N79: 460000 | Q79: 0
A80: 泸定县木角沟流域弃渣综合利用段地质环境治理工程设计施工总承包项目 | B80: 21982128 | N80: 7810000 | Q80: 0 | R80: 1170175.7 | AC80: 44590585 | AE80: 103307.08 | AM80: 46937458 | AN80: 59914302
A81: 泸州市公安局交通警察支队道路交通管理业务系统建设项目 | Q81: 0 | AA81: 352123.9
A82: 罗城仫佬族自治县棉花天坑生态旅游度假区森林小火车游乐设施项目设计采购施工总承包项目 | B82: 2143921.8 | L82: 1105196.4 | M82: 0 | N82: 2914030.9 | Q82: 0 | R82: 268275.8 | W82: 305469.51 | AA82: 2886460.1 | AC82: 21272294 | AM82: 22043828 | AN82: 22043828
A83: 洛阳鑫赟通实业有限公司2023年西工区老旧小区改造提质项目EPC工程(五标)项目 | B83: -14400000 | P83: -1188990.8 | Q83: -1188990.8 | AC83: 12814679 | AM83: 13211009
A84: 眉山市甘眉园区地下管廊管线建设项目三标段——甘眉东南片区排水管道更新改造工程 | B84: -8072130 | C84: 15659932 | M84: 163565.4 | P84: 6086116.9 | Q84: -1986013.1 | R84: 0 | AN84: 14961308
A85: 蒙自北站铁路立交桥EPC | M85: 0 | Q85: 0
A86: 蒙自市天马大道下穿草官支线立交工程DB(设计,施工)总承包项目 | B86: 10756979 | Q86: 0 | R86: 0 | AC86: -7397990
A87: 绵阳至遂宁至内江铁路绵阳至遂宁段--绵阳段三电及管线迁改项目工程总承包标段 | C87: 15000000 | P87: 59270001 | Q87: 0 | AB87: 173494.72 | AE87: 448228.8
A88: 绵阳至遂宁至内江铁路绵阳至遂宁段项目—遂宁段三电迁改项目设计施工总承包标段-1标段 | C88: 9400000 | N88: 2379200.4 | O88: 2379200.4 | P88: 25040778 | Q88: -2515121.7 | AB88: 85471.1 | AE88: 95255.39
A89: 南充北站站前基础配套设施工程设计施工总承包 | B89: 12295589 | C89: 0 | M89: 5343804.8 | N89: 29700719 | Q89: 0 | R89: 1800291.2 | W89: 2599692.8 | AB89: 362362.79 | AC89: 71659412 | AE89: 729807.92 | AM89: 73875682 | AN89: 73875683
A90: 南充机场油库铁路专用线工程EPC | Q90: 0 | AE90: 319.26
A91: 南崇高铁公网覆盖EPC项目 | B91: 1439450.2 | N91: 20424.84 | Q91: 0 | AA91: 1699766.8 | AC91: 2860306 | AE91: 60800.8 | AM91: 3287708.1 | AN91: 5307755.9
A92: 内昆铁路昭通站扶贫铁路专用线工程项目勘察设计施工总承包 | B92: 1.0784478e+08 | C92: -851293.97 | N92: 83456344 | P92: 18405485 | Q92: 0 | R92: 4555559.8 | AC92: 3.6423036e+08 | AE92: 178253.03 | AM92: 3.6811298e+08 | AN92: 3.7062287e+08
A93: 宁波市轨道交通5号线一期工程通信系统公安视频监视子系统 | B93: 520414 | N93: 831234.68 | Q93: 0 | AA93: 21707009 | AE93: 447849.49
A94: 宁夏电力灵武公司铁路专用线升级改造工程项目公开招标 | B94: -11455679 | N94: -2351293.9 | P94: 1468473.8 | Q94: -1163173.8 | AA94: 3713628.3 | AC94: 11021133 | AD94: 179000.58 | AE94: 47327.76 | AM94: 11246054
A95: 攀枝花市炳草岗污水处理厂提标升级改造工程勘察设计-材料及设备采购-施工总承包 | B95: -1295271.4 | N95: 66000 | Q95: -102728.59 | R95: -28333.55 | AA95: 3811260.3 | AC95: 43146229 | AE95: 226992.11 | AM95: 31076474 | AN95: 29268156
A96: 攀枝花市大渡口污水处理厂提标升级改造工程项目勘察设计材料及设备采购施工总承包 | B96: 304000 | C96: 314638 | N96: 656255.84 | O96: 25979.28 | P96: 321715 | Q96: 0 | R96: -9326.07 | AA96: 1215624.2 | AC96: 17459405 | AE96: 60283.69 | AM96: 10512226 | AN96: 7767550.5
A97: 攀枝花小沙坝污水处理厂改扩建工程勘察-设计-采购-施工总承包合同 | B97: 665320 | C97: 1307339.1 | N97: 139020.43 | Q97: 0 | R97: 37659.62 | AA97: 8074168.2 | AC97: 62281272 | AE97: 396012.18 | AM97: 36052683 | AN97: 32197658
A98: 盘江（普定）发电有限公司铁路专用线项目全标段勘察设计施工总承包（EPC） | B98: 35131949 | C98: 35548134 | N98: 79325132 | Q98: 0 | R98: 0 | AC98: 3.1583577e+08 | AE98: 3760 | AM98: 3.1583577e+08 | AN98: 3.1583577e+08
A99: 麒麟区整区屋顶分布式光伏试点项目EPC总承包 | Q99: 0 | AE99: 51297.14
A100: 取消省界广西岑梧项目 | Q100: 0 | AC100: 904174.09
...

Sheet 武隆污水（不上系统）
A1: 表一：基础信息表
A2: 单位名称 | B2: 合同名称 | C2: 合同编号 | D2: 合同类型 | E2: 合同金额 | K2: 管理费比例 | L2: 共享系统部门名称 | M2: 共享系统项目名称 | N2: 合同签订单位 | O2: 项目管理单位 | P2: 业主财务联系人及电话 | Q2: 分包方财务联系人及电话 | R2: 项目部经理及电话 | S2: 合同开工日期 | T2: 预计竣工时间 | U2: 合同工期 | V2: 工程类型 | W2: 项目所在地（*省*市） | X2: 项目状态 | Y2: 工程进度款支付比例 | Z2: 勘察设计费支付比例 | AA2: 主管税务机构名称 | AB2: 税务管理员及电话 | AC2: 银行行号 | AD2: 开户行 | AE2: 银行行号 | AF2: 银行账户名称 | AG2: 银行账号 | AH2: 银行地址 | AI2: 银行联系人 | AJ2: 备注
E3: 勘察设计 | F3: 工程施工 | G3: 设备采购 | H3: 业主承担管理费 | I3: 技术服务等 | J3: 合计
A4: 重庆碧水源建设项目管理有限责任公司 | B4: 武隆污水处理厂二期扩建工程EPC（设计、施工、采购、调试、试运行等交钥匙工程）总承包合同 | C4: 2017-生环院(总包)-001 | D4: 总包合同 | E4: 2933770.4 | F4: 1.16656e+08 | J4: =SUM(E4:I4) -> 1.1958977e+08 | K4: =(F4-F5-F6)/F4 -> 0.027878598 | L4: 中铁二院武隆污水厂项目部 | M4: 武隆污水处理厂二期扩建工程EPC | N4: 经计部 | O4: 生态环境院 | V4: 市政 | W4: 重庆市武隆区 | X4: 竣工未决算 | Y4: 1 | Z4: 1
A5: 重庆对外建设（集团）有限公司 | B5: 武隆污水处理厂二.期扩建工程EPC总承包联合体协议书 | C5: 2017-生环院(总包)-001 | D5: 分包合同 | F5: 1.134038e+08 | J5: =SUM(E5:I5) -> 1.134038e+08
A6: 重庆两江交通规划勘察设计研究院有限公司 | B6: 技术服务合同书 | D6: 分包合同 | E6: 2000000 | J6: =SUM(E6:I6) -> 2000000
A7: 四川德维工程管理咨询有限公司 | B7: 工程造价咨询合同 | D7: 分包合同 | E7: 200000 | J7: =E7 -> 200000
A8: 表二：汇总表
A9: 单位名称 | B9: 累计验工计价 | H9: 累计开票 | N9: 累计收入或成本 | T9: 累计收款/付款 | U9: 银行账户余额 | V9: 工程施工预计总收入 | W9: 工程施工预计总成本
B10: 勘察设计 | C10: 工程施工 | D10: 设备采购 | E10: 业主承担管理费 | F10: 服务费 | G10: 合计 | H10: 勘察设计 | I10: 工程施工 | J10: 设备采购 | K10: 业主承担管理费 | L10: 服务费 | M10: 合计 | N10: 勘察设计 | O10: 工程施工 | P10: 设备采购 | Q10: 业主承担管理费 | R10: 服务费 | S10: 合计
A11: 重庆碧水源建设项目管理有限责任公司 | B11: =SUMIFS($E$20:$E$46,$D$20:$D$46,$B$10,$A$20:$A$46,$A$11) -> 2933770.4 | C11: =SUMIFS($E$20:$E$46,$D$20:$D$46,C10,$A$20:$A$46,A11) -> 1.16656e+08 | D11: =SUMIFS($E$20:$E$46,$D$20:$D$46,D10,$A$20:$A$46,A11) -> 0 | E11: =SUMIFS($E$20:$E$46,$D$20:$D$46,E10,$A$20:$A$46,A11) -> 0 | F11: =SUMIFS($E$20:$E$46,$D$20:$D$46,F10,$A$20:$A$46,A11) -> 0 | G11: =SUM(B11:F11) -> 1.1958977e+08 | H11: =SUMIFS($V$20:$V$46,$R$20:$R$46,$H$10,$P$20:$P$46,$A$11) -> 2933770.4 | I11: =SUMIFS($V$20:$V$46,$R$20:$R$46,I10,$P$20:$P$46,$A$11) -> 1.16656e+08 | J11: =SUMIFS($V$20:$V$46,$R$20:$R$46,$J$10,$P$20:$P$46,$A$11) -> 0 | K11: =SUMIFS($V$20:$V$46,$R$20:$R$46,$K$10,$P$20:$P$46,$A$11) -> 0 | L11: =SUMIFS($V$20:$V$46,$R$20:$R$46,$L$10,$P$20:$P$46,$A$11) -> 0 | M11: =SUM(H11:L11) -> 1.1958977e+08 | N11: =SUMIFS($O$20:$O$45,$N$20:$N$45,N10,$L$20:$L$45,A11) -> 2767707.9 | O11: =SUMIFS($O$20:$O$45,$N$20:$N$45,O10,$L$20:$L$45,A11) -> 1.0622063e+08 | P11: =SUMIFS($O$20:$O$45,$N$20:$N$45,P10,$L$20:$L$45,A11) -> 0 | Q11: =SUMIFS($O$20:$O$45,$N$20:$N$45,Q10,$L$20:$L$45,A11) -> 0 | R11: =SUMIFS($O$20:$O$45,$N$20:$N$45,R10,$L$20:$L$45,A11) -> 0 | S11: =SUM(N11:R11) -> 1.0898834e+08 | T11: =SUMIF($Z$20:$Z$46,A11,$AE$20:$AE$46) -> 1.1958977e+08 | V11: =106220633.37 -> 1.0622063e+08 | W11: 1.0324322e+08
A12: 重庆对外建设（集团）有限公司 | B12: =SUMIFS($E$51:$E$76,$D$51:$D$76,B10,$A$51:$A$76,A12) -> 0 | C12: =SUMIFS($E$51:$E$76,$D$51:$D$76,C10,$A$51:$A$76,A12) -> 1.134038e+08 | D12: =SUMIFS($E$51:$E$76,$D$51:$D$76,D10,$A$51:$A$76,A12) -> 0 | E12: =SUMIFS($E$51:$E$76,$D$51:$D$76,E10,$A$51:$A$76,A12) -> 0 | F12: =SUMIFS($E$51:$E$76,$D$51:$D$76,F10,$A$51:$A$76,A12) -> 0 | G12: =SUM(B12:F12) -> 1.134038e+08 | H12: =SUMIFS($R$51:$R$76,$N$51:$N$76,H10,$L$51:$L$76,A12) -> 0 | I12: =SUMIFS($R$51:$R$76,$N$51:$N$76,I10,$L$51:$L$76,A12) -> 1.134038e+08 | J12: =SUMIFS($R$51:$R$76,$N$51:$N$76,J10,$L$51:$L$76,A12) -> 0 | K12: =SUMIFS($R$51:$R$76,$N$51:$N$76,K10,$L$51:$L$76,A12) -> 0 | L12: =SUMIFS($R$51:$R$76,$N$51:$N$76,L10,$L$51:$L$76,A12) -> 0 | M12: =SUM(H12:L12) -> 1.134038e+08 | N12: =SUMIFS($G$51:$G$76,$D$51:$D$76,N10,$A$51:$A$76,A12) -> 0 | O12: =SUMIFS($G$51:$G$76,$D$51:$D$76,$O$10,$A$51:$A$76,A12) -> 1.0324322e+08 | P12: =SUMIFS($G$51:$G$76,$D$51:$D$76,$P$10,$A$51:$A$76,A12) -> 0 | Q12: =SUMIFS($G$51:$G$76,$D$51:$D$76,$Q$10,$A$51:$A$76,A12) -> 0 | R12: =SUMIFS($G$51:$G$76,$D$51:$D$76,$R$10,$A$51:$A$76,A12) -> 0 | S12: =SUM(N12:R12) -> 1.0324322e+08 | T12: =SUMIF($V$51:$V$75,A12,$AA$51:$AA$76) -> 1.134038e+08
A13: 重庆两江交通规划勘察设计研究院有限公司 | B13: =SUMIFS($E$51:$E$76,$D$51:$D$76,B10,$A$51:$A$76,A13) -> 1550000 | C13: =SUMIFS($E$51:$E$76,$D$51:$D$76,C10,$A$51:$A$76,A13) -> 0 | D13: =SUMIFS($E$51:$E$76,$D$51:$D$76,D10,$A$51:$A$76,A13) -> 0 | E13: =SUMIFS($E$51:$E$76,$D$51:$D$76,E10,$A$51:$A$76,A13) -> 0 | F13: =SUMIFS($E$51:$E$76,$D$51:$D$76,F10,$A$51:$A$76,A13) -> 0 | G13: =SUM(B13:F13) -> 1550000 | H13: =SUMIFS($R$51:$R$76,$N$51:$N$76,H10,$L$51:$L$76,A13) -> 1550000 | I13: =SUMIFS($R$51:$R$76,$N$51:$N$76,I10,$L$51:$L$76,A13) -> 0 | J13: =SUMIFS($R$51:$R$76,$N$51:$N$76,J10,$L$51:$L$76,A13) -> 0 | K13: =SUMIFS($R$51:$R$76,$N$51:$N$76,K10,$L$51:$L$76,A13) -> 0 | L13: =SUMIFS($R$51:$R$76,$N$51:$N$76,L10,$L$51:$L$76,A13) -> 0 | M13: =SUM(H13:L13) -> 1550000 | N13: =SUMIFS($G$51:$G$76,$D$51:$D$76,$N$10,$A$51:$A$76,A13) -> 1462264.2 | O13: =SUMIFS($G$51:$G$76,$D$51:$D$76,$O$10,$A$51:$A$76,A13) -> 0 | P13: =SUMIFS($G$51:$G$76,$D$51:$D$76,$P$10,$A$51:$A$76,A13) -> 0 | Q13: =SUMIFS($G$51:$G$76,$D$51:$D$76,$Q$10,$A$51:$A$76,A13) -> 0 | R13: =SUMIFS($G$51:$G$76,$D$51:$D$76,$R$10,$A$51:$A$76,A13) -> 0 | S13: =SUM(N13:R13) -> 1462264.2 | T13: =SUMIF($V$51:$V$75,A13,$AA$51:$AA$76) -> 1550000
A14: 四川德维工程管理咨询有限公司 | B14: =SUMIFS($E$51:$E$76,$D$51:$D$76,B11,$A$51:$A$76,A14) -> 0 | C14: =SUMIFS($E$51:$E$76,$D$51:$D$76,C11,$A$51:$A$76,A14) -> 0 | D14: =SUMIFS($E$51:$E$76,$D$51:$D$76,D11,$A$51:$A$76,A14) -> 0 | E14: =SUMIFS($E$51:$E$76,$D$51:$D$76,E11,$A$51:$A$76,A14) -> 0 | F14: =SUMIFS($E$51:$E$76,$D$51:$D$76,F11,$A$51:$A$76,A14) -> 0 | G14: =SUM(B14:F14) -> 0 | H14: =SUMIFS($R$51:$R$76,$N$51:$N$76,H10,$L$51:$L$76,A14) -> 0 | I14: =SUMIFS($R$51:$R$76,$N$51:$N$76,I10,$L$51:$L$76,A14) -> 200000 | J14: =SUMIFS($R$51:$R$76,$N$51:$N$76,J11,$L$51:$L$76,A14) -> 0 | K14: =SUMIFS($R$51:$R$76,$N$51:$N$76,K11,$L$51:$L$76,A14) -> 0 | L14: =SUMIFS($R$51:$R$76,$N$51:$N$76,L11,$L$51:$L$76,A14) -> 0 | M14: =SUM(H14:L14) -> 200000 | N14: =SUMIFS($G$51:$G$76,$D$51:$D$76,$N$10,$A$51:$A$76,A14) -> 188679.25 | O14: =SUMIFS($G$51:$G$76,$D$51:$D$76,$O$10,$A$51:$A$76,A14) -> 0 | P14: =SUMIFS($G$51:$G$76,$D$51:$D$76,$P$10,$A$51:$A$76,A14) -> 0 | Q14: =SUMIFS($G$51:$G$76,$D$51:$D$76,$Q$10,$A$51:$A$76,A14) -> 0 | R14: =SUMIFS($G$51:$G$76,$D$51:$D$76,$R$10,$A$51:$A$76,A14) -> 0 | S14: =SUM(N14:R14) -> 188679.25 | T14: =SUMIF($V$51:$V$76,A14,$AA$51:$AA$76) -> 200000
G15: =G12+G13-C48 -> -200000 | M15: =M12+M13-R48 -> -200000 | S15: =S12+S13-G48 -> -188679.25 | T15: =T12+T13-AA48 -> -200000
A17: 表三：业主基础明细表 | C17: =SUM(C20:C44) -> 1.1958977e+08 | E17: =SUM(E20:E45) -> 1.1958977e+08 | G17: =SUM(G20:G45) -> 1.0898834e+08 | H17: =SUM(H20:H45) -> 10601433 | O17: =SUM(O20:O45) -> 1.0898834e+08 | V17: =SUM(V20:V45) -> 1.1958977e+08 | W17: =SUM(W20:W45) -> 1.0898834e+08 | X17: =SUM(X20:X45) -> 10601433 | AE17: =SUM(AE20:AE45) -> 1.1958977e+08
A18: 业主结算明细 | L18: 收入确认表 | P18: 开票明细表（可按开票时间汇总登记） | Z18: 收款明细
A19: 业主名称 | B19: 验工时间 | C19: 验工计价 | D19: 结算内容 | E19: 列账金额 | F19: 税率 | G19: 不含税金额(注意与账上保持一致） | H19: 税额(注意与账上保持一致） | I19: 列账凭证时间 | J19: 预付款转回 | K19: 罚没等其他金额 | L19: 业主名称 | M19: 凭证时间 | N19: 收入类型 | O19: 确认金额 | P19: 业主名称 | Q19: 凭证时间 | R19: 开票内容 | S19: 开票时间 | T19: 发票号码 | U19: 发票代码 | V19: 发票金额 | W19: 不含税金额 | X19: 税额 | Y19: 税率 | Z19: 单位名称 | AA19: 凭证日期 | AB19: 收款账户类型 | AC19: 收款账户名称 | AD19: 收款账户银行账号 | AE19: 收款金额 | AF19: 收款性质 | AG19: 收款备注
A20: 重庆碧水源建设项目管理有限责任公司 | C20: 11090000 | D20: 工程施工 | E20: 11090000 | F20: 0.11 | G20: =ROUND(E20/(1+F20),2) -> 9990991 | H20: =C20-G20 -> 1099009 | I20: 43089 | L20: 重庆碧水源建设项目管理有限责任公司 | M20: 43089 | N20: 工程施工 | O20: 9990991 | P20: 重庆碧水源建设项目管理有限责任公司 | Q20: 43089 | R20: 工程施工 | V20: 11090000 | W20: =ROUND(V20/(1+Y20),2) -> 9990991 | X20: =V20-W20 -> 1099009 | Y20: 0.11 | Z20: 重庆碧水源建设项目管理有限责任公司 | AA20: 44742 | AB20: 专户 | AC20: 中铁二院武隆污水厂项目部 | AE20: 1.16656e+08
A21: 重庆碧水源建设项目管理有限责任公司 | C21: 1500000 | D21: 工程施工 | E21: 1500000 | F21: 0.11 | G21: =ROUND(E21/(1+F21),2) -> 1351351.4 | H21: =C21-G21 -> 148648.65 | I21: 43089 | L21: 重庆碧水源建设项目管理有限责任公司 | M21: 43089 | N21: 工程施工 | O21: 1351351.4 | P21: 重庆碧水源建设项目管理有限责任公司 | Q21: 43089 | R21: 工程施工 | V21: 1500000 | W21: =ROUND(V21/(1+Y21),2) -> 1351351.4 | X21: =V21-W21 -> 148648.65 | Y21: 0.11 | Z21: 重庆碧水源建设项目管理有限责任公司 | AA21: 44742 | AB21: 专户 | AC21: 中铁二院武隆污水厂项目部 | AE21: 1911951.6
A22: 重庆碧水源建设项目管理有限责任公司 | C22: 19240000 | D22: 工程施工 | E22: 19240000 | F22: 0.11 | G22: =ROUND(E22/(1+F22),2) -> 17333333 | H22: =C22-G22 -> 1906666.7 | I22: 43139 | L22: 重庆碧水源建设项目管理有限责任公司 | M22: 43139 | N22: 工程施工 | O22: 17333333 | P22: 重庆碧水源建设项目管理有限责任公司 | Q22: 43139 | R22: 工程施工 | V22: 19240000 | W22: =ROUND(V22/(1+Y22),2) -> 17333333 | X22: =V22-W22 -> 1906666.7 | Y22: 0.11 | Z22: 重庆碧水源建设项目管理有限责任公司 | AA22: 44742 | AB22: 专户 | AC22: 中铁二院武隆污水厂项目部 | AE22: 1021818.2
A23: 重庆碧水源建设项目管理有限责任公司 | C23: 1950000 | D23: 勘察设计 | E23: 1950000 | F23: 0.06 | G23: =ROUND(E23/(1+F23),2) -> 1839622.6 | H23: =C23-G23 -> 110377.36 | I23: 43139 | L23: 重庆碧水源建设项目管理有限责任公司 | M23: 43139 | N23: 勘察设计 | O23: 1839622.6 | P23: 重庆碧水源建设项目管理有限责任公司 | Q23: 43139 | R23: 勘察设计 | V23: 1950000 | W23: =ROUND(V23/(1+Y23),2) -> 1839622.6 | X23: =V23-W23 -> 110377.36 | Y23: 0.06
A24: 重庆碧水源建设项目管理有限责任公司 | C24: 13500000 | D24: 工程施工 | E24: 13500000 | F24: 0.1 | G24: =ROUND(E24/(1+F24),2) -> 12272727 | H24: =C24-G24 -> 1227272.7 | I24: 43300 | L24: 重庆碧水源建设项目管理有限责任公司 | M24: 43300 | N24: 工程施工 | O24: 12272727 | P24: 重庆碧水源建设项目管理有限责任公司 | Q24: 43300 | R24: 工程施工 | V24: 13500000 | W24: =ROUND(V24/(1+Y24),2) -> 12272727 | X24: =V24-W24 -> 1227272.7 | Y24: 0.1
A25: 重庆碧水源建设项目管理有限责任公司 | C25: 7500000 | D25: 工程施工 | E25: 7500000 | F25: 0.1 | G25: =ROUND(E25/(1+F25),2) -> 6818181.8 | H25: =C25-G25 -> 681818.18 | I25: 43395 | L25: 重庆碧水源建设项目管理有限责任公司 | M25: 43395 | N25: 工程施工 | O25: 6818181.8 | P25: 重庆碧水源建设项目管理有限责任公司 | Q25: 43395 | R25: 工程施工 | V25: 7500000 | W25: =ROUND(V25/(1+Y25),2) -> 6818181.8 | X25: =V25-W25 -> 681818.18 | Y25: 0.1
A26: 重庆碧水源建设项目管理有限责任公司 | C26: 6000000 | D26: 工程施工 | E26: 6000000 | F26: 0.1 | G26: =ROUND(E26/(1+F26),2) -> 5454545.5 | H26: =C26-G26 -> 545454.55 | I26: 43444 | L26: 重庆碧水源建设项目管理有限责任公司 | M26: 43444 | N26: 工程施工 | O26: 5454545.5 | P26: 重庆碧水源建设项目管理有限责任公司 | Q26: 43444 | R26: 工程施工 | V26: 6000000 | W26: =ROUND(V26/(1+Y26),2) -> 5454545.5 | X26: =V26-W26 -> 545454.55 | Y26: 0.1
A27: 重庆碧水源建设项目管理有限责任公司 | C27: 325000 | D27: 勘察设计 | E27: 325000 | F27: 0.06 | G27: =ROUND(E27/(1+F27),2) -> 306603.77 | H27: =C27-G27 -> 18396.23 | I27: 43486 | L27: 重庆碧水源建设项目管理有限责任公司 | M27: 43486 | N27: 勘察设计 | O27: 306603.77 | P27: 重庆碧水源建设项目管理有限责任公司 | Q27: 43486 | R27: 勘察设计 | V27: 325000 | W27: =ROUND(V27/(1+Y27),2) -> 306603.77 | X27: =V27-W27 -> 18396.23 | Y27: 0.06
A28: 重庆碧水源建设项目管理有限责任公司 | C28: 6000000 | D28: 工程施工 | E28: 6000000 | F28: 0.1 | G28: =ROUND(E28/(1+F28),2) -> 5454545.5 | H28: =C28-G28 -> 545454.55 | I28: 43488 | L28: 重庆碧水源建设项目管理有限责任公司 | M28: 43488 | N28: 工程施工 | O28: 5454545.5 | P28: 重庆碧水源建设项目管理有限责任公司 | Q28: 43488 | R28: 工程施工 | V28: 6000000 | W28: =ROUND(V28/(1+Y28),2) -> 5454545.5 | X28: =V28-W28 -> 545454.55 | Y28: 0.1
A29: 重庆碧水源建设项目管理有限责任公司 | C29: 220000 | D29: 工程施工 | E29: 220000 | F29: 0.1 | G29: =ROUND(E29/(1+F29),2) -> 200000 | H29: =C29-G29 -> 20000 | I29: 43522 | L29: 重庆碧水源建设项目管理有限责任公司 | M29: 43522 | N29: 工程施工 | O29: 200000 | P29: 重庆碧水源建设项目管理有限责任公司 | Q29: 43522 | R29: 工程施工 | V29: 220000 | W29: =ROUND(V29/(1+Y29),2) -> 200000 | X29: =V29-W29 -> 20000 | Y29: 0.1
A30: 重庆碧水源建设项目管理有限责任公司 | C30: 7940000 | D30: 工程施工 | E30: 7940000 | F30: 0.09 | G30: =ROUND(E30/(1+F30),2) -> 7284403.7 | H30: =C30-G30 -> 655596.33 | I30: 43619 | L30: 重庆碧水源建设项目管理有限责任公司 | M30: 43619 | N30: 工程施工 | O30: 7284403.7 | P30: 重庆碧水源建设项目管理有限责任公司 | Q30: 43619 | R30: 工程施工 | V30: 7940000 | W30: =ROUND(V30/(1+Y30),2) -> 7284403.7 | X30: =V30-W30 -> 655596.33 | Y30: 0.09
A31: 重庆碧水源建设项目管理有限责任公司 | C31: 2790560 | D31: 工程施工 | E31: 2790560 | F31: 0.09 | G31: =ROUND(E31/(1+F31),2) -> 2560146.8 | H31: =C31-G31 -> 230413.21 | I31: 43647 | L31: 重庆碧水源建设项目管理有限责任公司 | M31: 43647 | N31: 工程施工 | O31: 2560146.8 | P31: 重庆碧水源建设项目管理有限责任公司 | Q31: 43647 | R31: 工程施工 | V31: 2790560 | W31: =ROUND(V31/(1+Y31),2) -> 2560146.8 | X31: =V31-W31 -> 230413.21 | Y31: 0.09
A32: 重庆碧水源建设项目管理有限责任公司 | C32: 9720000 | D32: 工程施工 | E32: 9720000 | F32: 0.09 | G32: =ROUND(E32/(1+F32),2) -> 8917431.2 | H32: =C32-G32 -> 802568.81 | I32: 43738 | L32: 重庆碧水源建设项目管理有限责任公司 | M32: 43738 | N32: 工程施工 | O32: 8917431.2 | P32: 重庆碧水源建设项目管理有限责任公司 | Q32: 43738 | R32: 工程施工 | V32: 9720000 | W32: =ROUND(V32/(1+Y32),2) -> 8917431.2 | X32: =V32-W32 -> 802568.81 | Y32: 0.09
A33: 重庆碧水源建设项目管理有限责任公司 | C33: 697640 | D33: 工程施工 | E33: 697640 | F33: 0.09 | G33: =ROUND(E33/(1+F33),2) -> 640036.7 | H33: =C33-G33 -> 57603.3 | I33: 43796 | L33: 重庆碧水源建设项目管理有限责任公司 | M33: 43796 | N33: 工程施工 | O33: 640036.7 | P33: 重庆碧水源建设项目管理有限责任公司 | Q33: 43796 | R33: 工程施工 | V33: 697640 | W33: =ROUND(V33/(1+Y33),2) -> 640036.7 | X33: =V33-W33 -> 57603.3 | Y33: 0.09
A34: 重庆碧水源建设项目管理有限责任公司 | C34: 3420000 | D34: 工程施工 | E34: 3420000 | F34: 0.09 | G34: =ROUND(E34/(1+F34),2) -> 3137614.7 | H34: =C34-G34 -> 282385.32 | I34: 43921 | L34: 重庆碧水源建设项目管理有限责任公司 | M34: 43921 | N34: 工程施工 | O34: 3137614.7 | P34: 重庆碧水源建设项目管理有限责任公司 | Q34: 43921 | R34: 工程施工 | V34: 3420000 | W34: =ROUND(V34/(1+Y34),2) -> 3137614.7 | X34: =V34-W34 -> 282385.32 | Y34: 0.09
... A40: 重庆碧水源建设项目管理有限责任公司 | C40: 10142759 | D40: 工程施工 | E40: 10142759 | F40: 0.09 | G40: =ROUND(E40/(1+F40),2) -> 9305283.1 | H40: =C40-G40 -> 837475.48 | I40: 45190 | L40: 重庆碧水源建设项目管理有限责任公司 | M40: 44561 | N40: 工程施工 | O40: -2709143.8 | P40: 重庆碧水源建设项目管理有限责任公司 | Q40: 44798 | R40: 勘察设计 | V40: 549054.08 | W40: =ROUND(V40/(1+Y40),2) -> 517975.55 | X40: =V40-W40 -> 31078.53 | Y40: 0.06
L41: 重庆碧水源建设项目管理有限责任公司 | M41: 44561 | N41: 勘察设计 | O41: 103505.95
L42: 重庆碧水源建设项目管理有限责任公司 | M42: 44798 | N42: 勘察设计 | O42: 517975.55
L43: 重庆碧水源建设项目管理有限责任公司 | M43: 44926 | N43: 工程施工 | O43: 8528024.7
A48: 表四：分包方基础明细表 | C48: =SUM(C51:C75) -> 1.151538e+08 | E48: =SUM(E51:E75) -> 1.151538e+08 | G48: =SUM(G51:G75) -> 1.0489416e+08 | H48: =SUM(H51:H75) -> 10259639 | J48: =SUM(J51:J75) -> 0 | K48: =SUM(K51:K75) -> 0 | R48: =SUM(R51:R75) -> 1.151538e+08 | S48: =SUM(S51:S75) -> 1.0489416e+08 | T48: =SUM(T51:T75) -> 10259639 | AA48: =SUM(AA51:AA75) -> 1.151538e+08
A49: 分包（采购）结算明细表 | L49: 分包（采购）发票明细表开票明细表（可按开票时间汇总登记） | V49: 分包（采购）付款明细表
A50: 单位名称 | B50: 验工时间 | C50: 验工计价 | D50: 结算内容 | E50: 金额 | F50: 税率 | G50: 不含税金额(注意与账上保持一致） | H50: 税额(注意与账上保持一致） | I50: 列账凭证时间 | J50: 预付款转回 | K50: 罚没等其他金额 | L50: 单位名称 | M50: 凭证时间 | N50: 开票内容 | O50: 开票时间 | P50: 发票号码 | Q50: 发票代码 | R50: 发票金额 | S50: 不含税金额 | T50: 税额 | U50: 税率 | V50: 单位名称 | W50: 凭证日期 | X50: 付款账户类型 | Y50: 付款账户名称 | Z50: 付款账户银行账号 | AA50: 付款金额 | AB50: 付款性质 | AC50: 付款备注
A51: 重庆对外建设（集团）有限公司 | C51: 1500000 | D51: 工程施工 | E51: 1500000 | F51: 0.11 | G51: =ROUND(E51/(1+F51),2) -> 1351351.4 | H51: =C51-G51 -> 148648.65 | I51: 43118 | L51: 重庆对外建设（集团）有限公司 | M51: 43118 | N51: 工程施工 | R51: 1500000 | S51: =ROUND(R51/(1+U51),2) -> 1351351.4 | T51: =R51-S51 -> 148648.65 | U51: 0.11 | V51: 重庆对外建设（集团）有限公司 | W51: 44818 | AA51: 1.134038e+08 | AB51: 工程施工
A52: 重庆两江交通规划勘察设计研究院有限公司 | C52: 950000 | D52: 勘察设计 | E52: 950000 | F52: 0.06 | G52: =ROUND(E52/(1+F52),2) -> 896226.42 | H52: =C52-G52 -> 53773.58 | I52: 43179 | L52: 重庆两江交通规划勘察设计研究院有限公司 | M52: 43179 | N52: 勘察设计 | R52: 950000 | S52: =ROUND(R52/(1+U52),2) -> 896226.42 | T52: =R52-S52 -> 53773.58 | U52: 0.06 | V52: 重庆两江交通规划勘察设计研究院有限公司 | W52: 44818 | AA52: 1550000 | AB52: 勘察设计
A53: 重庆对外建设（集团）有限公司 | C53: 10812750 | D53: 工程施工 | E53: 10812750 | F53: 0.11 | G53: =ROUND(E53/(1+F53),2) -> 9741216.2 | H53: =C53-G53 -> 1071533.8 | I53: 43179 | L53: 重庆对外建设（集团）有限公司 | M53: 43179 | N53: 工程施工 | R53: 10812750 | S53: =ROUND(R53/(1+U53),2) -> 9741216.2 | T53: =R53-S53 -> 1071533.8 | U53: 0.11 | V53: 四川德维工程管理咨询有限公司 | W53: 44818 | AA53: 200000 | AB53: 勘察设计
A54: 重庆对外建设（集团）有限公司 | C54: 14285700 | D54: 工程施工 | E54: 14285700 | F54: 0.11 | G54: =ROUND(E54/(1+F54),2) -> 12870000 | H54: =C54-G54 -> 1415700 | I54: 43179 | L54: 重庆对外建设（集团）有限公司 | M54: 43179 | N54: 工程施工 | R54: 14285700 | S54: =ROUND(R54/(1+U54),2) -> 12870000 | T54: =R54-S54 -> 1415700 | U54: 0.11
A55: 重庆对外建设（集团）有限公司 | C55: 4954300 | D55: 工程施工 | E55: 4954300 | F55: 0.11 | G55: =ROUND(E55/(1+F55),2) -> 4463333.3 | H55: =C55-G55 -> 490966.67 | I55: 43208 | L55: 重庆对外建设（集团）有限公司 | M55: 43208 | N55: 工程施工 | R55: 4954300 | S55: =ROUND(R55/(1+U55),2) -> 4463333.3 | T55: =R55-S55 -> 490966.67 | U55: 0.11
A56: 重庆对外建设（集团）有限公司 | C56: 13240840 | D56: 工程施工 | E56: 13240840 | F56: 0.1 | G56: =ROUND(E56/(1+F56),2) -> 12037127 | H56: =C56-G56 -> 1203712.7 | I56: 43343 | L56: 重庆对外建设（集团）有限公司 | M56: 43343 | N56: 工程施工 | R56: 13240840 | S56: =ROUND(R56/(1+U56),2) -> 12037127 | T56: =R56-S56 -> 1203712.7 | U56: 0.1
A57: 重庆对外建设（集团）有限公司 | C57: 7275000 | D57: 工程施工 | E57: 7275000 | F57: 0.1 | G57: =ROUND(E57/(1+F57),2) -> 6613636.4 | H57: =C57-G57 -> 661363.64 | I57: 43432 | L57: 重庆对外建设（集团）有限公司 | M57: 43432 | N57: 工程施工 | R57: 7275000 | S57: =ROUND(R57/(1+U57),2) -> 6613636.4 | T57: =R57-S57 -> 661363.64 | U57: 0.1
A58: 重庆对外建设（集团）有限公司 | C58: 5820000 | D58: 工程施工 | E58: 5820000 | F58: 0.1 | G58: =ROUND(E58/(1+F58),2) -> 5290909.1 | H58: =C58-G58 -> 529090.91 | I58: 43460 | L58: 重庆对外建设（集团）有限公司 | M58: 43460 | N58: 工程施工 | R58: 5820000 | S58: =ROUND(R58/(1+U58),2) -> 5290909.1 | T58: =R58-S58 -> 529090.91 | U58: 0.1
A59: 重庆对外建设（集团）有限公司 | C59: 6000000 | D59: 工程施工 | E59: 6000000 | F59: 0.1 | G59: =ROUND(E59/(1+F59),2) -> 5454545.5 | H59: =C59-G59 -> 545454.55 | I59: 43488 | L59: 重庆对外建设（集团）有限公司 | M59: 43488 | N59: 工程施工 | R59: 6000000 | S59: =ROUND(R59/(1+U59),2) -> 5454545.5 | T59: =R59-S59 -> 545454.55 | U59: 0.1
A60: 重庆对外建设（集团）有限公司 | C60: 33400 | D60: 工程施工 | E60: 33400 | F60: 0.1 | G60: =ROUND(E60/(1+F60),2) -> 30363.64 | H60: =C60-G60 -> 3036.36 | I60: 43522 | L60: 重庆对外建设（集团）有限公司 | M60: 43522 | N60: 工程施工 | R60: 33400 | S60: =ROUND(R60/(1+U60),2) -> 30363.64 | T60: =R60-S60 -> 3036.36 | U60: 0.1
A61: 四川德维工程管理咨询有限公司 | C61: 200000 | D61: 勘察设计 | E61: 200000 | F61: 0.06 | G61: =ROUND(E61/(1+F61),2) -> 188679.25 | H61: =C61-G61 -> 11320.75 | I61: 43553 | L61: 四川德维工程管理咨询有限公司 | M61: 43553 | N61: 工程施工 | R61: 200000 | S61: =ROUND(R61/(1+U61),2) -> 188679.25 | T61: =R61-S61 -> 11320.75 | U61: 0.06
A62: 重庆对外建设（集团）有限公司 | C62: 650000 | D62: 工程施工 | E62: 650000 | F62: 0.1 | G62: =ROUND(E62/(1+F62),2) -> 590909.09 | H62: =C62-G62 -> 59090.91 | I62: 43553 | L62: 重庆对外建设（集团）有限公司 | M62: 43553 | N62: 工程施工 | R62: 650000 | S62: =ROUND(R62/(1+U62),2) -> 590909.09 | T62: =R62-S62 -> 59090.91 | U62: 0.1
A63: 重庆对外建设（集团）有限公司 | C63: 7940000 | D63: 工程施工 | E63: 7940000 | F63: 0.09 | G63: =ROUND(E63/(1+F63),2) -> 7284403.7 | H63: =C63-G63 -> 655596.33 | I63: 43619 | L63: 重庆对外建设（集团）有限公司 | M63: 43619 | N63: 工程施工 | R63: 7940000 | S63: =ROUND(R63/(1+U63),2) -> 7284403.7 | T63: =R63-S63 -> 655596.33 | U63: 0.09
A64: 重庆对外建设（集团）有限公司 | C64: 2706843.2 | D64: 工程施工 | E64: 2706843.2 | F64: 0.09 | G64: =ROUND(E64/(1+F64),2) -> 2483342.4 | H64: =C64-G64 -> 223500.81 | I64: 43690 | L64: 重庆对外建设（集团）有限公司 | M64: 43690 | N64: 工程施工 | R64: 2706843.2 | S64: =ROUND(R64/(1+U64),2) -> 2483342.4 | T64: =R64-S64 -> 223500.81 | U64: 0.09
A65: 重庆对外建设（集团）有限公司 | C65: 9622800 | D65: 工程施工 | E65: 9622800 | F65: 0.09 | G65: =ROUND(E65/(1+F65),2) -> 8828256.9 | H65: =C65-G65 -> 794543.12 | I65: 43738 | L65: 重庆对外建设（集团）有限公司 | M65: 43738 | N65: 工程施工 | R65: 9622800 | S65: =ROUND(R65/(1+U65),2) -> 8828256.9 | T65: =R65-S65 -> 794543.12 | U65: 0.09
... A71: 重庆对外建设（集团）有限公司 | C71: 6261394 | D71: 工程施工 | E71: 6261394 | F71: 0.09 | G71: =ROUND(E71/(1+F71),2) -> 5744398.1 | H71: =C71-G71 -> 516995.83 | I71: 44552 | L71: 重庆对外建设（集团）有限公司 | M71: 44782 | N71: 工程施工 | R71: 7765836.3 | S71: =ROUND(R71/(1+U71),2) -> 7124620.5 | T71: =R71-S71 -> 641215.84 | U71: 0.09
A72: 重庆对外建设（集团）有限公司 | C72: 8378336.3 | D72: 工程施工 | E72: 8378336.3 | F72: 0.09 | G72: =ROUND(E72/(1+F72),2) -> 7686547.1 | H72: =C72-G72 -> 691789.24 | I72: 44926 | L72: 重庆对外建设（集团）有限公司 | M72: 44552 | N72: 工程施工 | R72: 6261394 | S72: =ROUND(R72/(1+U72),2) -> 5744398.1 | T72: =R72-S72 -> 516995.83 | U72: 0.09 | W72: 0
A73: 重庆对外建设（集团）有限公司 | C73: -198476.2 | D73: 工程施工 | E73: -198476.2 | F73: 0.09 | G73: =ROUND(E73/(1+F73),2) -> -182088.26 | H73: =C73-G73 -> -16387.94 | I73: 45288 | L73: 重庆对外建设（集团）有限公司 | M73: 45222 | N73: 工程施工 | R73: 414023.8 | S73: =ROUND(R73/(1+U73),2) -> 379838.35 | T73: =R73-S73 -> 34185.45 | U73: 0.09
A78: 表五：预缴税款情况统计表
A79: 凭证号/时间 | B79: 销售额 | C79: 扣除金额 | D79: 增值税 | E79: 城市维护建设税 | F79: 教育费附加 | G79: 地方教育费附加 | H79: 印花税 | I79: 企业所得税 | J79: 个人所得税 | K79: 其他税金 | L79: 合计 | M79: 备注
B80: 11090000 | D80: 199819.82 | E80: 13987.39 | F80: 5994.59 | G80: 3996.4 | H80: 39573.8 | I80: 19981.98 | J80: 320677.61 | L80: =SUM(D80:K80) -> 604031.59
B81: 19240000 | C81: 19240000 | I81: 34666.67 | L81: =SUM(D81:K81) -> 34666.67
B82: -10812750 | D82: -194824.32 | E82: -13637.7 | F82: -13637.7 | G82: -3896.49 | L82: =SUM(D82:K82) -> -225996.21
B83: 13500000 | C83: 13240840 | D83: 4712 | E83: 329.84 | F83: 141.36 | G83: 94.24 | I83: 24545.45 | L83: =SUM(D83:K83) -> 29822.89
B84: 7500000 | C84: 7275000 | D84: 4090.91 | E84: 286.36 | F84: 122.73 | G84: 81.82 | I84: 13636.36 | L84: =SUM(D84:K84) -> 18218.18
B85: 6000000 | C85: 5820000 | D85: 3272.73 | E85: 229.09 | F85: 98.18 | G85: 65.45 | I85: 10909.09 | L85: =SUM(D85:K85) -> 14574.54
I86: 10909.09 | L86: =SUM(D86:K86) -> 10909.09
B87: 220000 | C87: 33400 | D87: 3392.73 | E87: 237.49 | F87: 101.78 | G87: 67.85 | I87: 400 | L87: =SUM(D87:K87) -> 4199.85
I88: 14568.81 | L88: =SUM(D88:K88) -> 14568.81
B89: 2790560 | C89: 2706843.2 | D89: 1536.09 | E89: 107.53 | F89: 46.08 | G89: 30.72 | I89: 5120.29 | L89: =SUM(D89:K89) -> 6840.71
B90: 9720000 | C90: 9622800 | D90: 1783.49 | E90: 124.84 | F90: 53.5 | G90: 35.67 | I90: 17834.86 | L90: =SUM(D90:K90) -> 19832.36
B91: 697640 | C91: 676710.8 | D91: 384.02 | E91: 26.88 | F91: 11.52 | G91: 7.68 | I91: 1280.07 | L91: =SUM(D91:K91) -> 1710.17
B92: 3420000 | C92: 3317400 | D92: 1882.57 | E92: 131.78 | F92: 56.48 | G92: 37.65 | I92: 6275.23 | L92: =SUM(D92:K92) -> 8383.71
B93: 1300000 | C93: 1261000 | D93: 715.6 | E93: 50.09 | F93: 21.47 | G93: 14.31 | I93: 2385.32 | L93: =SUM(D93:K93) -> 3186.79
B94: 9140000 | C94: 8865800 | D94: 5031.19 | E94: 352.18 | F94: 150.94 | G94: 100.62 | I94: 16770.64 | L94: =SUM(D94:K94) -> 22405.57
B95: 6455045.3 | C95: 6261394 | D95: 3553.24 | E95: 248.73 | F95: 106.6 | G95: 71.06 | L95: =SUM(D95:K95) -> 3979.63
L96: =SUM(D96:K96) -> 0
L97: =SUM(D97:K97) -> 0
A98: 合计 | B98: =SUM(B80:B97) -> 80260495 | C98: =SUM(C80:C97) -> 78321188 | D98: =SUM(D80:D97) -> 35350.07 | E98: =SUM(E80:E97) -> 2474.5 | F98: =SUM(F80:F97) -> -6732.47 | G98: =SUM(G80:G97) -> 706.98 | H98: =SUM(H80:H97) -> 39573.8 | I98: =SUM(I80:I97) -> 179283.86 | ... K98: =SUM(K80:K97) -> 0 | L98: =SUM(L80:L92) -> 541762.36 | M98: =SUM(M80:M92) -> 0
A100: 表六：间接费用、财务费用、附加费明细表
A101: 费用类型 | B101: 以前年度累计 | C101: 2023年 | D101: 2024年 | E101: 2025年 | F101: 2026年 | G101: 2027年 | H101: 2028年 | I101: 合计
A102: 间接费用 | B102: 460219.88 | I102: =SUM(B102:H102) -> 460219.88
A103: 财务费用 | B103: =B105-B104 -> -14843.77 | C103: =C105-C104 -> -10095.13 | D103: =D105-D104 -> -6220.62 | I103: =SUM(B103:H103) -> -31159.52
A104: 其中：利息收入 | B104: 20989.54 | C104: 11895.13 | D104: 8020.62 | I104: =SUM(B104:H104) -> 40905.29
A105: 手续费支出 | B105: 6145.77 | C105: 1800 | D105: 1800 | I105: =SUM(B105:H105) -> 9745.77
A106: 营业外收入 | I106: =SUM(B106:H106) -> 0
A107: 营业外支出 | I107: =SUM(B107:H107) -> 0
A110: 表七：往来类科目明细表
A111: 项目名称 | B111: 应收账款 | C111: 合同负债 | D111: 合同资产 | E111: 长期应收款 | F111: 其他应收款 | G111: 应付账款 | H111: 预付账款 | I111: 长期应付款 | J111: 其他应付款 | K111: 待转销项税额 | L111: 专业分包成本 | M111: 直接材料费 | N111: 合同结算-收入结转 | O111: 合同结算-价款结算 | P111: 工程施工结转 | Q111: 合同负债增值税 | R111: 应付账款-预付账款增值税
A112: =M4 -> 武隆污水处理厂二期扩建工程EPC | L112: 1.0489428e+08 | N112: 1.0622063e+08 | O112: 1.0622063e+08 | P112: 1.053545e+08
A115: 表八：施工收入、成本计算表
A116: 2024年合同工程施工收入、成本计算表
A118: =L4 -> 中铁二院武隆污水厂项目部 | H118: 金额：元
A119: 序号 | B119: 名称 | C119: 期初数 | D119: 1季度 | E119: 2季度 | F119: 3季度 | G119: 4季度 | H119: 开累数
A120: 1 | B120: 工程施工预计总收入 | H120: =V11 -> 1.0622063e+08
A121: 2 | B121: 工程施工预计总成本 | H121: =W11 -> 1.0324322e+08
A122: 3 | B122: 工程施工预计合同毛利 | H122: =H120-H121 -> 2977417.6
A123: 4 | B123: 工程施工确认营业成本 | D123: 0 | H123: =C123+D123+E123+F123+G123 -> 0
A124: 5 | B124: 工程施工确认营业收入 | D124: 0 | H124: =C124+D124+E124+F124+G124 -> 0
A125: 6 | B125: 完工百分比 | C125: =ROUND(C123/H121,10) -> 0 | D125: =ROUND((C123+D123)/H121,10) -> 0 | E125: =ROUND((C123+D123+E123)/H121,10) -> 0 | F125: =ROUND((C123+D123+E123+F123)/H121,10) -> 0 | G125: =ROUND((C123+D123+E123+F123+G123)/H121,10) -> 0
...

Sheet 攀枝花大渡口
A1: 表一：基础信息表
A2: 单位名称 | B2: 合同名称 | C2: 合同编号 | D2: 合同类型 | E2: 合同金额 | K2: 管理费比例 | L2: 共享系统部门名称 | M2: 共享系统项目名称 | N2: 合同签订单位 | O2: 项目管理单位 | P2: 业主财务联系人及电话 | Q2: 分包方财务联系人及电话 | R2: 项目部经理及电话 | S2: 合同开工日期 | T2: 预计竣工时间 | U2: 合同工期 | V2: 工程类型 | W2: 项目所在地（*省*市） | X2: 项目状态 | Y2: 工程进度款支付比例 | Z2: 勘察设计费支付比例 | AA2: 主管税务机构名称 | AB2: 税务管理员及电话 | AC2: 银行行号 | AD2: 开户行 | AE2: 银行行号 | AF2: 银行账户名称 | AG2: 银行账号 | AH2: 银行地址 | AI2: 银行联系人 | AJ2: 备注
E3: 勘察设计 | F3: 工程施工 | G3: 设备采购 | H3: 业主承担管理费 | I3: 技术服务等 | J3: 合计
A4: 攀枝花市水务（集团）有限公司 | B4: 攀枝花市大渡口污水处理厂提标升级改造工程项目勘察设计材料及设备采购施工总承包 | C4: 2019-生环院(总包)-001 | D4: 总包合同 | E4: 1520000 | F4: =26900000-G4-E4 -> 13053600 | G4: 12326400 | J4: =SUM(E4:I4) -> 26900000 | K4: =(F4-F5)/F4 -> 0.022 | L4: 中铁二院攀枝花市大渡口污水处理厂提标升级改造工程EPC项目部 | M4: 攀枝花市大渡口污水处理厂提标升级改造工程项目勘察设计材料及设备采购施工总承包 | N4: 经计部 | O4: 生态环境院 | V4: 市政 | W4: 四川省攀枝花市 | X4: 收尾 | Y4: 0.9 | Z4: 0.8
A5: 四川锐信路桥工程有限公司 | B5: 攀枝花市大渡口污水处理厂提标升级改造工程勘察设计-材料及设备采购-施工总承包项目联合体补充协议 | C5: 2019-生环院(分包)(总包)-004 | D5: 分包合同 | F5: =13053600*0.978 -> 12766421 | J5: =SUM(E5:I5) -> 12766421
A6: 冶金工业部华东勘察基础工程总公司成都分公司 | B6: 攀枝花市大渡口污水处理厂提标升级改造工程详勘 | C6: 2019-生环院(自揽外包)(总包)-009 | D6: 分包合同 | E6: 220000 | J6: =SUM(E6:I6) -> 220000
A7: 上海恒实环保能源（集团）有限公司 | B7: 攀枝花市大渡口污水处理厂提标升级改造工程设备采购及伴随服务合同 | C7: 2019-生环院(分包)(总包)-005 | D7: 分包合同 | G7: =12326400*0.978 -> 12055219 | J7: =SUM(E7:I7) -> 12055219
A9: 表二：汇总表
A10: 单位名称 | B10: 累计验工计价 | H10: 累计开票 | N10: 累计收入或成本 | T10: 累计收款/付款 | U10: 银行账户余额 | V10: 工程施工预计总收入 | W10: 工程施工预计总成本
B11: 勘察设计 | C11: 工程施工 | D11: 设备采购 | E11: 业主承担管理费 | F11: 服务费 | G11: 合计 | H11: 勘察设计 | I11: 工程施工 | J11: 设备采购 | K11: 业主承担管理费 | L11: 服务费 | M11: 合计 | N11: 勘察设计 | O11: 工程施工 | P11: 设备采购 | Q11: 业主承担管理费 | R11: 服务费 | S11: 合计
A12: 攀枝花市水务（集团）有限公司 | B12: =SUMIFS($E$21:$E$47,$D$21:$D$47,$B$11,$A$21:$A$47,$A$12) -> 1520000 | C12: =SUMIFS($E$21:$E$47,$D$21:$D$47,C11,$A$21:$A$47,A12) -> 8466630 | D12: =SUMIFS($E$21:$E$47,$D$21:$D$47,D11,$A$21:$A$47,A12) -> 11849105 | E12: =SUMIFS($E$21:$E$47,$D$21:$D$47,E11,$A$21:$A$47,A12) -> 0 | F12: =SUMIFS($E$21:$E$47,$D$21:$D$47,F11,$A$21:$A$47,A12) -> 0 | G12: =SUM(B12:F12) -> 21835735 | H12: =SUMIFS($V$21:$V$47,$R$21:$R$47,$H$11,$P$21:$P$47,$A$12) -> 1216000 | I12: =SUMIFS($V$21:$V$47,$R$21:$R$47,I11,$P$21:$P$47,$A$12) -> 8788345 | J12: =SUMIFS($V$21:$V$47,$R$21:$R$47,$J$11,$P$21:$P$47,$A$12) -> 11849105 | K12: =SUMIFS($V$21:$V$47,$R$21:$R$47,$K$11,$P$21:$P$47,$A$12) -> 0 | L12: =SUMIFS($V$21:$V$47,$R$21:$R$47,$L$11,$P$21:$P$47,$A$12) -> 0 | M12: =SUM(H12:L12) -> 21853450 | N12: =SUMIFS($O$21:$O$46,$N$21:$N$46,N11,$L$21:$L$46,A12) -> 1433932.3 | O12: =SUMIFS($O$21:$O$46,$N$21:$N$46,O11,$L$21:$L$46,A12) -> 10512226 | P12: =SUMIFS($O$21:$O$46,$N$21:$N$46,P11,$L$21:$L$46,A12) -> 10485934 | Q12: =SUMIFS($O$21:$O$46,$N$21:$N$46,Q11,$L$21:$L$46,A12) -> 0 | R12: =SUMIFS($O$21:$O$46,$N$21:$N$46,R11,$L$21:$L$46,A12) -> 0 | S12: =SUM(N12:R12) -> 22432092 | T12: =SUMIF($Z$21:$Z$47,A12,$AE$21:$AE$47) -> 21853450 | V12: =F4/1.09 -> 11975780 | W12: =(F5+F7)/1.09 -> 11712313 | X12: 11975780 | Y12: 11712313
A13: 四川锐信路桥工程有限公司 | B13: =SUMIFS($E$52:$E$77,$D$52:$D$77,B11,$A$52:$A$77,A13) -> 0 | C13: =SUMIFS($E$52:$E$77,$D$52:$D$77,C11,$A$52:$A$77,A13) -> 10060410 | D13: =SUMIFS($E$52:$E$77,$D$52:$D$77,D11,$A$52:$A$77,A13) -> 0 | E13: =SUMIFS($E$52:$E$77,$D$52:$D$77,E11,$A$52:$A$77,A13) -> 0 | F13: =SUMIFS($E$52:$E$77,$D$52:$D$77,F11,$A$52:$A$77,A13) -> 0 | G13: =SUM(B13:F13) -> 10060410 | H13: =SUMIFS($R$52:$R$77,$N$52:$N$77,H11,$L$52:$L$77,A13) -> 0 | I13: =SUMIFS($R$52:$R$77,$N$52:$N$77,I11,$L$52:$L$77,A13) -> 9744771.5 | J13: =SUMIFS($R$52:$R$77,$N$52:$N$77,J11,$L$52:$L$77,A13) -> 0 | K13: =SUMIFS($R$52:$R$77,$N$52:$N$77,K11,$L$52:$L$77,A13) -> 0 | L13: =SUMIFS($R$52:$R$77,$N$52:$N$77,L11,$L$52:$L$77,A13) -> 0 | M13: =SUM(H13:L13) -> 9744771.5 | N13: =SUMIFS($G$52:$G$77,$D$52:$D$77,N11,$A$52:$A$77,A13) -> 0 | O13: =SUMIFS($G$52:$G$77,$D$52:$D$77,$O$11,$A$52:$A$77,A13) -> 9229734.4 | P13: =SUMIFS($G$52:$G$77,$D$52:$D$77,$P$11,$A$52:$A$77,A13) -> 0 | Q13: =SUMIFS($G$52:$G$77,$D$52:$D$77,$Q$11,$A$52:$A$77,A13) -> 0 | R13: =SUMIFS($G$52:$G$77,$D$52:$D$77,$R$11,$A$52:$A$77,A13) -> 0 | S13: =SUM(N13:R13) -> 9229734.4 | T13: =SUMIF($V$52:$V$77,A13,$AA$52:$AA$77) -> 9744771.5
A14: 冶金工业部华东勘察基础工程总公司成都分公司 | B14: =SUMIFS($E$52:$E$77,$D$52:$D$77,B11,$A$52:$A$77,A14) -> 220000 | C14: =SUMIFS($E$52:$E$77,$D$52:$D$77,C11,$A$52:$A$77,A14) -> 0 | D14: =SUMIFS($E$52:$E$77,$D$52:$D$77,D11,$A$52:$A$77,A14) -> 0 | E14: =SUMIFS($E$52:$E$77,$D$52:$D$77,E11,$A$52:$A$77,A14) -> 0 | F14: =SUMIFS($E$52:$E$77,$D$52:$D$77,F11,$A$52:$A$77,A14) -> 0 | G14: =SUM(B14:F14) -> 220000 | H14: =SUMIFS($R$52:$R$77,$N$52:$N$77,H11,$L$52:$L$77,A14) -> 220000 | I14: =SUMIFS($R$52:$R$77,$N$52:$N$77,I11,$L$52:$L$77,A14) -> 0 | J14: =SUMIFS($R$52:$R$77,$N$52:$N$77,J11,$L$52:$L$77,A14) -> 0 | K14: =SUMIFS($R$52:$R$77,$N$52:$N$77,K11,$L$52:$L$77,A14) -> 0 | L14: =SUMIFS($R$52:$R$77,$N$52:$N$77,L11,$L$52:$L$77,A14) -> 0 | M14: =SUM(H14:L14) -> 220000 | N14: =SUMIFS($G$52:$G$77,$D$52:$D$77,$N$11,$A$52:$A$77,A14) -> 207547.16 | O14: =SUMIFS($G$52:$G$77,$D$52:$D$77,$O$11,$A$52:$A$77,A14) -> 0 | P14: =SUMIFS($G$52:$G$77,$D$52:$D$77,$P$11,$A$52:$A$77,A14) -> 0 | Q14: =SUMIFS($G$52:$G$77,$D$52:$D$77,$Q$11,$A$52:$A$77,A14) -> 0 | R14: =SUMIFS($G$52:$G$77,$D$52:$D$77,$R$11,$A$52:$A$77,A14) -> 0 | S14: =SUM(N14:R14) -> 207547.16 | T14: =SUMIF($V$52:$V$77,A14,$AA$52:$AA$77) -> 220000 | AG14: 21853450
A15: 上海恒实环保能源（集团）有限公司 | B15: =SUMIFS($E$52:$E$77,$D$52:$D$77,B12,$A$52:$A$77,A15) -> 0 | C15: =SUMIFS($E$52:$E$77,$D$52:$D$77,C12,$A$52:$A$77,A15) -> 0 | D15: =SUMIFS($E$52:$E$77,$D$52:$D$77,D11,$A$52:$A$77,A15) -> 10438655 | E15: =SUMIFS($E$52:$E$77,$D$52:$D$77,E12,$A$52:$A$77,A15) -> 0 | F15: =SUMIFS($E$52:$E$77,$D$52:$D$77,F12,$A$52:$A$77,A15) -> 0 | G15: =SUM(B15:F15) -> 10438655 | H15: =SUMIFS($R$52:$R$77,$N$52:$N$77,H11,$L$52:$L$77,A15) -> 0 | I15: =SUMIFS($R$52:$R$77,$N$52:$N$77,I12,$L$52:$L$77,A15) -> 0 | J15: =SUMIFS($R$52:$R$77,$N$52:$N$77,J11,$L$52:$L$77,A15) -> 10438655 | K15: =SUMIFS($R$52:$R$77,$N$52:$N$77,K12,$L$52:$L$77,A15) -> 0 | L15: =SUMIFS($R$52:$R$77,$N$52:$N$77,L12,$L$52:$L$77,A15) -> 0 | M15: =SUM(H15:L15) -> 10438655 | N15: =SUMIFS($G$52:$G$77,$D$52:$D$77,$N$11,$A$52:$A$77,A15) -> 0 | O15: =SUMIFS($G$52:$G$77,$D$52:$D$77,$O$11,$A$52:$A$77,A15) -> 0 | P15: =SUMIFS($G$52:$G$77,$D$52:$D$77,$P$11,$A$52:$A$77,A15) -> 9237748.1 | Q15: =SUMIFS($G$52:$G$77,$D$52:$D$77,$Q$11,$A$52:$A$77,A15) -> 0 | R15: =SUMIFS($G$52:$G$77,$D$52:$D$77,$R$11,$A$52:$A$77,A15) -> 0 | S15: =SUM(N15:R15) -> 9237748.1 | T15: =SUMIF($V$52:$V$77,A15,$AA$52:$AA$77) -> 10438655
G16: =G13+G14-C49 -> -10438655 | M16: =M13+M14-R49 -> -10438655 | S16: =S13+S14-G49 -> -9237748.1 | T16: =T13+T14-AA49 -> -10438655
A18: 表三：业主基础明细表 | C18: =SUM(C21:C46) -> 21835735 | E18: =SUM(E21:E46) -> 21835735 | G18: =SUM(G21:G46) -> 19687416 | H18: =SUM(H21:H46) -> 2148318.6 | O18: =SUM(O21:O46) -> 22432092 | V18: =SUM(V21:V46) -> 21853450 | W18: =SUM(W21:W46) -> 19695805 | X18: =SUM(X21:X46) -> 2157644.7 | AE18: =SUM(AE21:AE46) -> 21853450 | AH18: 21531735 | AI18: =AE18-AH18 -> 321715
A19: 业主结算明细 | L19: 收入确认表 | P19: 开票明细表（可按开票时间汇总登记） | Z19: 收款明细
A20: 业主名称 | B20: 验工时间 | C20: 验工计价 | D20: 结算内容 | E20: 列账金额 | F20: 税率 | G20: 不含税金额(注意与账上保持一致） | H20: 税额(注意与账上保持一致） | I20: 列账凭证时间 | J20: 预付款转回 | K20: 罚没等其他金额 | L20: 业主名称 | M20: 凭证时间 | N20: 收入类型 | O20: 确认金额 | P20: 业主名称 | Q20: 凭证时间 | R20: 开票内容 | S20: 开票时间 | T20: 发票号码 | U20: 发票代码 | V20: 发票金额 | W20: 不含税金额 | X20: 税额 | Y20: 税率 | Z20: 单位名称 | AA20: 凭证日期 | AB20: 收款账户类型 | AC20: 收款账户名称 | AD20: 收款账户银行账号 | AE20: 收款金额 | AF20: 收款性质 | AG20: 收款备注
A21: 攀枝花市水务（集团）有限公司 | C21: 1520000 | D21: 勘察设计 | E21: 1520000 | F21: 0.06 | G21: 1433932.3 | H21: 86067.74 | L21: 攀枝花市水务（集团）有限公司 | M21: 43893 | N21: 勘察设计 | O21: 1147169.8 | P21: 攀枝花市水务（集团）有限公司 | Q21: 43664 | R21: 勘察设计 | V21: 1216000 | W21: =ROUND(V21/(1+Y21),2) -> 1147169.8 | X21: =V21-W21 -> 68830.19 | Y21: 0.06 | Z21: 攀枝花市水务（集团）有限公司 | AA21: 44681 | AB21: 专户 | AC21: 中铁二院攀枝花市大渡口污水处理厂提标升级改造工程EPC项目部 | AE21: 208000 | AF21: 勘察设计
A22: 攀枝花市水务（集团）有限公司 | C22: 8466630 | D22: 工程施工 | E22: 8466630 | F22: 0.09 | G22: =ROUND(E22/(1+F22),2) -> 7767550.5 | H22: =C22-G22 -> 699079.54 | L22: 攀枝花市水务（集团）有限公司 | M22: 44561 | N22: 工程施工 | O22: 9853643.5 | P22: 攀枝花市水务（集团）有限公司 | Q22: 43819 | R22: 工程施工 | V22: 8466630 | W22: =ROUND(V22/(1+Y22),2) -> 7767550.5 | X22: =V22-W22 -> 699079.54 | Y22: 0.09 | Z22: 攀枝花市水务（集团）有限公司 | AA22: 44681 | AB22: 专户 | AC22: 中铁二院攀枝花市大渡口污水处理厂提标升级改造工程EPC项目部 | AE22: 1008000 | AF22: 勘察设计
A23: 攀枝花市水务（集团）有限公司 | C23: 9549012.1 | D23: 设备采购 | E23: 9549012.1 | F23: 0.13 | G23: 8185840.7 | H23: 1363171.4 | L23: 攀枝花市水务（集团）有限公司 | M23: 44173 | N23: 设备采购 | O23: 8185840.7 | P23: 攀枝花市水务（集团）有限公司 | Q23: 43832 | R23: 设备采购 | V23: 11849105 | W23: 10485934 | X23: 1363171.4 | Y23: 0.13 | Z23: 攀枝花市水务（集团）有限公司 | AA23: 44681 | AB23: 专户 | AC23: 中铁二院攀枝花市大渡口污水处理厂提标升级改造工程EPC项目部 | AE23: 20637450 | AF23: 工程施工 | AH23: =AE23 -> 20637450
A24: 攀枝花市水务（集团）有限公司 | C24: 2300092.9 | D24: 设备采购 | E24: 2300092.9 | F24: 0.13 | G24: 2300092.9 | L24: 攀枝花市水务（集团）有限公司 | M24: 44173 | N24: 勘察设计 | O24: 286762.45 | P24: 攀枝花市水务（集团）有限公司 | Q24: 44003 | R24: 工程施工 | S24: 44578 | T24: 12781149 | U24: 5100213130 | V24: 321715 | W24: 295151.38 | X24: 26563.62
L25: 攀枝花市水务（集团）有限公司 | M25: 45657 | N25: 设备采购 | O25: 2300092.9
L26: 攀枝花市水务（集团）有限公司 | M26: 45657 | N26: 工程施工 | O26: 658582.43
A49: 表四：分包方基础明细表 | C49: =SUM(C52:C76) -> 20719065 | E49: =SUM(E52:E76) -> 20719065 | G49: =SUM(G52:G76) -> 18675030 | H49: =SUM(H52:H76) -> 2044035.8 | J49: =SUM(J52:J76) -> 0 | K49: =SUM(K52:K76) -> 0 | R49: =SUM(R52:R76) -> 20403427 | S49: =SUM(S52:S76) -> 18385453 | T49: =SUM(T52:T76) -> 2017974.2 | AA49: =SUM(AA52:AA76) -> 20403427 | AE49: 20403427
A50: 分包（采购）结算明细表 | L50: 分包（采购）发票明细表开票明细表（可按开票时间汇总登记） | V50: 分包（采购）付款明细表
A51: 单位名称 | B51: 验工时间 | C51: 验工计价 | D51: 结算内容 | E51: 金额 | F51: 税率 | G51: 不含税金额(注意与账上保持一致） | H51: 税额(注意与账上保持一致） | I51: 列账凭证时间 | J51: 预付款转回 | K51: 罚没等其他金额 | L51: 单位名称 | M51: 凭证时间 | N51: 开票内容 | O51: 开票时间 | P51: 发票号码 | Q51: 发票代码 | R51: 发票金额 | S51: 不含税金额 | T51: 税额 | U51: 税率 | V51: 单位名称 | W51: 凭证日期 | X51: 付款账户类型 | Y51: 付款账户名称 | Z51: 付款账户银行账号 | AA51: 付款金额 | AB51: 付款性质 | AC51: 付款备注
A52: 冶金工业部华东勘察基础工程总公司成都分公司 | C52: 220000 | D52: 勘察设计 | E52: 220000 | F52: 0.06 | G52: 207547.16 | H52: 12452.84 | I52: 43894 | L52: 冶金工业部华东勘察基础工程总公司成都分公司 | M52: 43668 | N52: 勘察设计 | R52: 220000 | S52: 207547.16 | T52: 12452.84 | U52: 0.06 | V52: 四川锐信路桥工程有限公司 | W52: 44712 | X52: 专户 | Y52: 中铁二院攀枝花市大渡口污水处理厂提标升级改造工程EPC项目部 | AA52: 9744771.5 | AB52: 工程施工
A53: 四川锐信路桥工程有限公司 | C53: 9430133.5 | D53: 工程施工 | E53: 9430133.5 | F53: 0.09 | G53: 8651499 | H53: 778634.48 | I53: 44173 | L53: 四川锐信路桥工程有限公司 | M53: 43894 | N53: 工程施工 | R53: 9744771.5 | S53: =ROUND(R53/(1+U53),2) -> 8940157.3 | T53: =R53-S53 -> 804614.16 | U53: 0.09 | V53: 上海恒实环保能源（集团）有限公司 | W53: 44712 | X53: 专户 | Y53: 中铁二院攀枝花市大渡口污水处理厂提标升级改造工程EPC项目部 | AA53: 10438655 | AB53: 设备采购 | AH53: =AA53+AA52 -> 20183427
A54: 上海恒实环保能源（集团）有限公司 | C54: 9223031.1 | D54: 设备采购 | E54: 9223031.1 | F54: 0.13 | G54: 8022123.9 | H54: 1200907.2 | I54: 44196 | L54: 上海恒实环保能源（集团）有限公司 | M54: 43894 | N54: 设备采购 | R54: 10438655 | S54: =ROUND(R54/(1+U54),2) -> 9237748.1 | T54: =R54-S54 -> 1200907.2 | U54: 0.13 | V54: 冶金工业部华东勘察基础工程总公司成都分公司 | W54: 44712 | X54: 专户 | Y54: 中铁二院攀枝花市大渡口污水处理厂提标升级改造工程EPC项目部 | AA54: 220000 | AB54: 勘察设计 | AH54: =AH23-AH53 -> 454023.17
A55: 上海恒实环保能源（集团）有限公司 | C55: 1215624.2 | D55: 设备采购 | E55: 1215624.2 | F55: 0.13 | G55: 1215624.2 | I55: 45616 | AH55: =AH54/AH23 -> 0.021999965
A56: 四川锐信路桥工程有限公司 | C56: 314638 | D56: 工程施工 | E56: 314638 | F56: 0.09 | G56: =ROUND(E56/(1+F56),2) -> 288658.72 | H56: =E56-G56 -> 25979.28 | I56: 45616
A57: 四川锐信路桥工程有限公司 | C57: 2125900 | D57: 工程施工 | E57: 2125900 | F57: 0.09 | G57: =ROUND(E57/(1+F57),2) -> 1950367 | H57: =E57-G57 -> 175533.03 | I57: 45616
A58: 四川锐信路桥工程有限公司 | C58: -1810261.4 | D58: 工程施工 | E58: -1810261.4 | F58: 0.09 | G58: =ROUND(E58/(1+F58),2) -> -1660790.3 | H58: =E58-G58 -> -149471.13 | I58: 45635
A79: 表五：预缴税款情况统计表
A80: 凭证号/时间 | B80: 销售额 | C80: 扣除金额 | D80: 增值税 | E80: 城市维护建设税 | F80: 教育费附加 | G80: 地方教育费附加 | H80: 印花税 | I80: 企业所得税 | J80: 个人所得税 | K80: 其他税金 | L80: 合计 | M80: 备注
B81: 26900000 | C81: 26900000 | H81: 8070 | L81: =SUM(D81:K81) -> 8070
L82: =SUM(D82:K82) -> 0
L83: =SUM(D83:K83) -> 0
L84: =SUM(D84:K84) -> 0
L85: =SUM(D85:K85) -> 0
L86: =SUM(D86:K86) -> 0
L87: =SUM(D87:K87) -> 0
L88: =SUM(D88:K88) -> 0
L89: =SUM(D89:K89) -> 0
L90: =SUM(D90:K90) -> 0
L91: =SUM(D91:K91) -> 0
L92: =SUM(D92:K92) -> 0
L93: =SUM(D93:K93) -> 0
A94: 合计 | B94: =SUM(B81:B93) -> 26900000 | C94: =SUM(C81:C93) -> 26900000 | D94: =SUM(D81:D93) -> 0 | E94: =SUM(E81:E93) -> 0 | F94: =SUM(F81:F93) -> 0 | G94: =SUM(G81:G93) -> 0 | H94: =SUM(H81:H93) -> 8070 | I94: =SUM(I81:I93) -> 0 | ... M94: =SUM(M81:M93) -> 0
A96: 表六：间接费用、财务费用、附加费明细表
A97: 费用类型 | B97: 以前年度累计 | C97: 2023年 | D97: 2024年 | E97: 2025年 | F97: 2026年 | G97: 2027年 | H97: 2028年 | I97: 合计
A98: 间接费用 | B98: 57664.54 | I98: =SUM(B98:H98) -> 57664.54
A99: 财务费用 | B99: =B101-B100 -> -8662.33 | C99: =C101-C100 -> -1130.73 | D99: =D101-D100 -> -367.18 | I99: =SUM(B99:H99) -> -10160.24
A100: 其中：利息收入 | B100: 11385.57 | C100: 1490.73 | D100: 1146.19 | I100: =SUM(B100:H100) -> 14022.49
A101: 手续费支出 | B101: 2723.24 | C101: 360 | D101: 779.01 | I101: =SUM(B101:H101) -> 3862.25
A102: 营业外收入 | I102: =SUM(B102:H102) -> 0
A103: 营业外支出 | I103: =SUM(B103:H103) -> 0
A106: 表七：往来类科目明细表
A107: 项目名称 | B107: 应收账款 | C107: 合同负债 | D107: 合同资产 | E107: 长期应收款 | F107: 其他应收款 | G107: 应付账款 | H107: 预付账款 | I107: 长期应付款 | J107: 其他应付款 | K107: 待转销项税额 | L107: 专业分包成本 | M107: 直接材料费 | N107: 合同结算-收入结转 | O107: 合同结算-价款结算 | P107: 工程施工结转 | Q107: 合同负债增值税 | R107: 应付账款-预付账款增值税
A108: =M4 -> 攀枝花市大渡口污水处理厂提标升级改造工程项目勘察设计材料及设备采购施工总承包 | B108: 304000 | C108: 321715 | G108: 656255.84 | H108: 314638 | K108: -9326.07 | L108: 17459405 | M108: 1215624.2 | N108: 10512226 | O108: 7767550.5 | P108: 18732694 | R108: 25979.28
A111: 表八：施工收入、成本计算表
A112: 2024年合同工程施工收入、成本计算表
A114: =L4 -> 中铁二院攀枝花市大渡口污水处理厂提标升级改造工程EPC项目部 | H114: 金额：元
A115: 序号 | B115: 名称 | C115: 期初数 | D115: 1季度 | E115: 2季度 | F115: 3季度 | G115: 4季度 | H115: 开累数
A116: 1 | B116: 工程施工预计总收入 | H116: =V12 -> 11975780
A117: 2 | B117: 工程施工预计总成本 | H117: =W12 -> 11712313
A118: 3 | B118: 工程施工预计合同毛利 | H118: =H116-H117 -> 263467.16
A119: 4 | B119: 工程施工确认营业成本 | D119: 0 | H119: =C119+D119+E119+F119+G119 -> 0
A120: 5 | B120: 工程施工确认营业收入 | D120: 0 | H120: =C120+D120+E120+F120+G120 -> 0
A121: 6 | B121: 完工百分比 | C121: =ROUND(C119/H117,10) -> 0 | D121: =ROUND((C119+D119)/H117,10) -> 0 | E121: =ROUND((C119+D119+E119)/H117,10) -> 0 | F121: =ROUND((C119+D119+E119+F119)/H117,10) -> 0 | G121: =ROUND((C119+D119+E119+F119+G119)/H117,10) -> 0
A122: 7 | B122: 确认营业毛利 | C122: =C120-C119 -> 0 | D122: =D120-D119 -> 0 | E122: =E120-E119 -> 0 | F122: =F120-F119 -> 0 | G122: =G120-G119 -> 0
A123: 8 | B123: 累计营业毛利 | C123: =C120-C119 -> 0 | D123: =C122+D122 -> 0 | E123: =C122+D122+E122 -> 0 | F123: =C122+D122+E122+F122 -> 0 | G123: =C122+D122+E122+F122+G122 -> 0
B125: 制表人： | G125: 项目部签字：
A127: 表九：数据校验
A128: 业主往来检验 | B128: 业主发票检验 | C128: 业主收入检验 | D128: 分包往来检验 | E128: 分包验工计价校验 | F128: 预缴税金检验 | G128: 两金指标
A129: =G12-T12-B108+C108-E108-F108-Q108-D108 -> 0 | B129: =H18-X18-K108+Q108 -> -2.9831426e-10 | C129: =SUMIFS($G$52:$G$77,$D$52:$D$77,C11)/H117*H116-O12 -> -1074869.7 | D129: =G13+G14-T13-T14-G108+H108-I108-J108+R108+G15-T15 -> 0 | E129: =C12*(1-K4)-C13-C14 -> -1780045.9 | F129: =(SUMIFS($V$21:$V$47,$R$21:$R$47,C11)-SUMIFS($R$52:$R$77,$N$52:$N$77,C11))/1.09*0.02-D94 -> -17549.11 | G129: =B108-C108+N108-O108 -> 2726960.5
A130: 应为零 | B130: 应为零 | C130: 应为零 | D130: 应为零 | E130: 应为零（正数为未验完，负数为超验） | F130: 应为零 | G130: 应尽量小，超过1000万预警
C131: =G53/W12*V12 -> 8846113.5
C132: =C131-O22 -> -1007530
C133: =C129-C132 -> -67339.71
E135: 17237.55
E136: 26563.62
E138: =E135-E136 -> -9326.07

Sheet 攀枝花小沙坝
A1: 表一：基础信息表
A2: 单位名称 | B2: 合同名称 | C2: 合同编号 | D2: 合同类型 | E2: 合同金额 | K2: 管理费比例 | L2: 共享系统部门名称 | M2: 共享系统项目名称 | N2: 合同签订单位 | O2: 项目管理单位 | P2: 业主财务联系人及电话 | Q2: 分包方财务联系人及电话 | R2: 项目部经理及电话 | S2: 合同开工日期 | T2: 预计竣工时间 | U2: 合同工期 | V2: 工程类型 | W2: 项目所在地（*省*市） | X2: 项目状态 | Y2: 工程进度款支付比例 | Z2: 勘察设计费支付比例 | AA2: 主管税务机构名称 | AB2: 税务管理员及电话 | AC2: 银行行号 | AD2: 开户行 | AE2: 银行行号 | AF2: 银行账户名称 | AG2: 银行账号 | AH2: 银行地址 | AI2: 银行联系人 | AJ2: 备注
E3: 勘察设计 | F3: 工程施工 | G3: 设备采购 | H3: 业主承担管理费 | I3: 技术服务等 | J3: 合计
A4: 攀枝花市水务（集团）有限公司 | B4: 攀枝花小沙坝污水处理厂改扩建工程 | C4: 2019-生环院(总包)-002 | D4: 总包合同 | E4: 3326600 | F4: =92179000-G4 -> 50118040 | G4: 42060960 | J4: =SUM(E4:I4) -> 95505600 | K4: =(F4-F5)/F4 -> 0.02 | L4: 中铁二院攀枝花小沙坝污水处理厂改扩建EPC项目部 | M4: 攀枝花小沙坝污水处理厂改扩建工程勘察-设计-采购-施工总承包合同 | N4: 经计部 | O4: 生态环境院 | V4: 市政 | W4: 四川省攀枝花市 | X4: 收尾 | Y4: 0.9 | Z4: 0.8
A5: 四川信纬建设集团有限公司 | B5: 攀枝花小沙坝污水处理厂改扩建工程勘察-设计-采购-施工总承包项目联合体补充协议 | C5: 2019-生环院(分包)(总包)-003 | D5: 分包合同 | F5: =50118040*0.98 -> 49115679 | J5: =SUM(E5:I5) -> 49115679
A6: 上海恒实环保能源（集团）有限公司 | B6: 攀枝花小沙坝污水处理厂改扩建工程项目设备采购及伴随服务合同 | C6: 2019-生环院(分包)(总包)-002 | D6: 分包合同 | G6: =(42060960)*0.98 -> 41219741 | J6: =SUM(E6:I6) -> 41219741
A7: 冶金工业部华东勘察基础工程总公司成都分公司 | B7: 攀枝花市小沙坝污水处理厂改扩建工程--建设工程勘察合同 | D7: 分包合同 | E7: 500000 | J7: =SUM(E7:I7) -> 500000
A8: 成都城格城乡规划设计有限公司 | B8: 攀枝花市小沙坝污水处理厂改扩建工程--建设工程勘察合同 | D8: 分包合同 | E8: 700000 | J8: =SUM(E8:I8) -> 700000
F9: =ROUND(F4/1.09,2) -> 45979853 | G9: =ROUND(G4/1.13,2) -> 37222088
A10: 表二：汇总表 | F10: =ROUND(F5/1.09,2) -> 45060256
A11: 单位名称 | B11: 累计验工计价 | H11: 累计开票 | N11: 累计收入或成本 | T11: 累计收款/付款 | U11: 银行账户余额 | V11: 工程施工预计总收入 | W11: 工程施工预计总成本
B12: 勘察设计 | C12: 工程施工 | D12: 设备采购 | E12: 业主承担管理费 | F12: 服务费 | G12: 合计 | H12: 勘察设计 | I12: 工程施工 | J12: 设备采购 | K12: 业主承担管理费 | L12: 服务费 | M12: 合计 | N12: 勘察设计 | O12: 工程施工 | P12: 设备采购 | Q12: 业主承担管理费 | R12: 服务费 | S12: 合计
A13: 攀枝花市水务（集团）有限公司 | B13: =SUMIFS($E$22:$E$48,$D$22:$D$48,$B$12,$A$22:$A$48,$A$13) -> 3326600 | C13: =SUMIFS($E$22:$E$48,$D$22:$D$48,C12,$A$22:$A$48,A13) -> 35095447 | D13: =SUMIFS($E$22:$E$48,$D$22:$D$48,D12,$A$22:$A$48,A13) -> 43362667 | E13: =SUMIFS($E$22:$E$48,$D$22:$D$48,E12,$A$22:$A$48,A13) -> 0 | F13: =SUMIFS($E$22:$E$48,$D$22:$D$48,F12,$A$22:$A$48,A13) -> 0 | G13: =SUM(B13:F13) -> 81784714 | H13: =SUMIFS($V$22:$V$48,$R$22:$R$48,$H$12,$P$22:$P$48,$A$13) -> 2661280 | I13: =SUMIFS($V$22:$V$48,$R$22:$R$48,I12,$P$22:$P$48,$A$13) -> 35095447 | J13: =SUMIFS($V$22:$V$48,$R$22:$R$48,$J$12,$P$22:$P$48,$A$13) -> 43362667 | K13: =SUMIFS($V$22:$V$48,$R$22:$R$48,$K$12,$P$22:$P$48,$A$13) -> 0 | L13: =SUMIFS($V$22:$V$48,$R$22:$R$48,$L$12,$P$22:$P$48,$A$13) -> 0 | M13: =SUM(H13:L13) -> 81119394 | N13: =SUMIFS($O$22:$O$47,$N$22:$N$47,N12,$L$22:$L$47,A13) -> 3138301.9 | O13: =SUMIFS($O$22:$O$47,$N$22:$N$47,O12,$L$22:$L$47,A13) -> 36052683 | P13: =SUMIFS($O$22:$O$47,$N$22:$N$47,P12,$L$22:$L$47,A13) -> 38374042 | Q13: =SUMIFS($O$22:$O$47,$N$22:$N$47,Q12,$L$22:$L$47,A13) -> 0 | R13: =SUMIFS($O$22:$O$47,$N$22:$N$47,R12,$L$22:$L$47,A13) -> 0 | S13: =SUM(N13:R13) -> 77565026 | T13: =SUMIF($Z$22:$Z$48,A13,$AE$22:$AE$48) -> 81119394 | V13: =F4/1.09 -> 45979853 | W13: =(F6+F8+F5+F7)/1.09 -> 45060256 | X13: 45979853 | Y13: 45060256
A14: 四川信纬建设集团有限公司 | B14: =SUMIFS($E$53:$E$78,$D$53:$D$78,B12,$A$53:$A$78,A14) -> 0 | C14: =SUMIFS($E$53:$E$78,$D$53:$D$78,C12,$A$53:$A$78,A14) -> 34581733 | D14: =SUMIFS($E$53:$E$78,$D$53:$D$78,D12,$A$53:$A$78,A14) -> 0 | E14: =SUMIFS($E$53:$E$78,$D$53:$D$78,E12,$A$53:$A$78,A14) -> 0 | F14: =SUMIFS($E$53:$E$78,$D$53:$D$78,F12,$A$53:$A$78,A14) -> 0 | G14: =SUM(B14:F14) -> 34581733 | H14: =SUMIFS($R$53:$R$78,$N$53:$N$78,H12,$L$53:$L$78,A14) -> 0 | I14: =SUMIFS($R$53:$R$78,$N$53:$N$78,I12,$L$53:$L$78,A14) -> 34442715 | J14: =SUMIFS($R$53:$R$78,$N$53:$N$78,J12,$L$53:$L$78,A14) -> 0 | K14: =SUMIFS($R$53:$R$78,$N$53:$N$78,K12,$L$53:$L$78,A14) -> 0 | L14: =SUMIFS($R$53:$R$78,$N$53:$N$78,L12,$L$53:$L$78,A14) -> 0 | M14: =SUM(H14:L14) -> 34442715 | N14: =SUMIFS($G$53:$G$78,$D$53:$D$78,N12,$A$53:$A$78,A14) -> 0 | O14: =SUMIFS($G$53:$G$78,$D$53:$D$78,$O$12,$A$53:$A$78,A14) -> 31726361 | P14: =SUMIFS($G$53:$G$78,$D$53:$D$78,$P$12,$A$53:$A$78,A14) -> 0 | Q14: =SUMIFS($G$53:$G$78,$D$53:$D$78,$Q$12,$A$53:$A$78,A14) -> 0 | R14: =SUMIFS($G$53:$G$78,$D$53:$D$78,$R$12,$A$53:$A$78,A14) -> 0 | S14: =SUM(N14:R14) -> 31726361 | T14: =SUMIF($V$53:$V$78,A14,$AA$53:$AA$78) -> 34442713
A15: 上海恒实环保能源（集团）有限公司 | B15: =SUMIFS($E$53:$E$78,$D$53:$D$78,B12,$A$53:$A$78,A15) -> 0 | C15: =SUMIFS($E$53:$E$78,$D$53:$D$78,C12,$A$53:$A$78,A15) -> 0 | D15: =SUMIFS($E$53:$E$78,$D$53:$D$78,D12,$A$53:$A$78,A15) -> 41138898 | E15: =SUMIFS($E$53:$E$78,$D$53:$D$78,E12,$A$53:$A$78,A15) -> 0 | F15: =SUMIFS($E$53:$E$78,$D$53:$D$78,F12,$A$53:$A$78,A15) -> 0 | G15: =SUM(B15:F15) -> 41138898 | H15: =SUMIFS($R$53:$R$78,$N$53:$N$78,H12,$L$53:$L$78,A15) -> 0 | I15: =SUMIFS($R$53:$R$78,$N$53:$N$78,I12,$L$53:$L$78,A15) -> 0 | J15: =SUMIFS($R$53:$R$78,$N$53:$N$78,J12,$L$53:$L$78,A15) -> 42446237 | K15: =SUMIFS($R$53:$R$78,$N$53:$N$78,K12,$L$53:$L$78,A15) -> 0 | L15: =SUMIFS($R$53:$R$78,$N$53:$N$78,L12,$L$53:$L$78,A15) -> 0 | M15: =SUM(H15:L15) -> 42446237 | N15: =SUMIFS($G$53:$G$78,$D$53:$D$78,$N$12,$A$53:$A$78,A15) -> 0 | O15: =SUMIFS($G$53:$G$78,$D$53:$D$78,$O$12,$A$53:$A$78,A15) -> 0 | P15: =SUMIFS($G$53:$G$78,$D$53:$D$78,$P$12,$A$53:$A$78,A15) -> 37334991 | Q15: =SUMIFS($G$53:$G$78,$D$53:$D$78,$Q$12,$A$53:$A$78,A15) -> 0 | R15: =SUMIFS($G$53:$G$78,$D$53:$D$78,$R$12,$A$53:$A$78,A15) -> 0 | S15: =SUM(N15:R15) -> 37334991 | T15: =SUMIF($V$53:$V$78,A15,$AA$53:$AA$78) -> 42446237
A16: 冶金工业部华东勘察基础工程总公司成都分公司 | B16: =SUMIFS($E$53:$E$78,$D$53:$D$78,B12,$A$53:$A$78,A16) -> 500000 | C16: =SUMIFS($E$53:$E$78,$D$53:$D$78,C12,$A$53:$A$78,A16) -> 0 | D16: =SUMIFS($E$53:$E$78,$D$53:$D$78,D13,$A$53:$A$78,A16) -> 0 | E16: =SUMIFS($E$53:$E$78,$D$53:$D$78,E13,$A$53:$A$78,A16) -> 0 | F16: =SUMIFS($E$53:$E$78,$D$53:$D$78,F13,$A$53:$A$78,A16) -> 0 | G16: =SUM(B16:F16) -> 500000 | H16: =SUMIFS($R$53:$R$78,$N$53:$N$78,H13,$L$53:$L$78,A16) -> 0 | I16: =SUMIFS($R$53:$R$78,$N$53:$N$78,I13,$L$53:$L$78,A16) -> 0 | J16: =SUMIFS($R$53:$R$78,$N$53:$N$78,J13,$L$53:$L$78,A16) -> 0 | K16: =SUMIFS($R$53:$R$78,$N$53:$N$78,K13,$L$53:$L$78,A16) -> 0 | L16: =SUMIFS($R$53:$R$78,$N$53:$N$78,L13,$L$53:$L$78,A16) -> 0 | M16: =SUM(H16:L16) -> 0 | N16: =SUMIFS($G$53:$G$78,$D$53:$D$78,$N$12,$A$53:$A$78,A16) -> 471698.11 | O16: =SUMIFS($G$53:$G$78,$D$53:$D$78,$O$12,$A$53:$A$78,A16) -> 0 | P16: =SUMIFS($G$53:$G$78,$D$53:$D$78,$P$12,$A$53:$A$78,A16) -> 0 | Q16: =SUMIFS($G$53:$G$78,$D$53:$D$78,$Q$12,$A$53:$A$78,A16) -> 0 | R16: =SUMIFS($G$53:$G$78,$D$53:$D$78,$R$12,$A$53:$A$78,A16) -> 0 | S16: =SUM(N16:R16) -> 471698.11 | T16: =SUMIF($V$53:$V$78,A16,$AA$53:$AA$78) -> 500000
A17: 成都城格城乡规划设计有限公司 | B17: =SUMIFS($E$53:$E$78,$D$53:$D$78,B12,$A$53:$A$78,A17) -> 630000 | C17: =SUMIFS($E$53:$E$78,$D$53:$D$78,C14,$A$53:$A$78,A17) -> 0 | D17: =SUMIFS($E$53:$E$78,$D$53:$D$78,D12,$A$53:$A$78,A17) -> 0 | E17: =SUMIFS($E$53:$E$78,$D$53:$D$78,E14,$A$53:$A$78,A17) -> 0 | F17: =SUMIFS($E$53:$E$78,$D$53:$D$78,F14,$A$53:$A$78,A17) -> 0 | G17: =SUM(B17:F17) -> 630000 | H17: =SUMIFS($R$53:$R$78,$N$53:$N$78,H14,$L$53:$L$78,A17) -> 0 | I17: =SUMIFS($R$53:$R$78,$N$53:$N$78,I14,$L$53:$L$78,A17) -> 0 | J17: =SUMIFS($R$53:$R$78,$N$53:$N$78,J14,$L$53:$L$78,A17) -> 0 | K17: =SUMIFS($R$53:$R$78,$N$53:$N$78,K14,$L$53:$L$78,A17) -> 0 | L17: =SUMIFS($R$53:$R$78,$N$53:$N$78,L14,$L$53:$L$78,A17) -> 0 | M17: =SUM(H17:L17) -> 0 | N17: =SUMIFS($G$53:$G$78,$D$53:$D$78,$N$12,$A$53:$A$78,A17) -> 594339.62 | O17: =SUMIFS($G$53:$G$78,$D$53:$D$78,$O$12,$A$53:$A$78,A17) -> 0 | P17: =SUMIFS($G$53:$G$78,$D$53:$D$78,$P$12,$A$53:$A$78,A17) -> 0 | Q17: =SUMIFS($G$53:$G$78,$D$53:$D$78,$Q$12,$A$53:$A$78,A17) -> 0 | R17: =SUMIFS($G$53:$G$78,$D$53:$D$78,$R$12,$A$53:$A$78,A17) -> 0 | S17: =SUM(N17:R17) -> 594339.62 | T17: =SUMIF($V$53:$V$78,A17,$AA$53:$AA$78) -> 630000
A19: 表三：业主基础明细表 | C19: =SUM(C22:C47) -> 81784714 | E19: =SUM(E22:E47) -> 81784714 | G19: =SUM(G22:G47) -> 73710001 | H19: =SUM(H22:H47) -> 8074712.7 | O19: =SUM(O22:O47) -> 77565026 | V19: =SUM(V22:V47) -> 81119394 | W19: =SUM(W22:W47) -> 73082341 | X19: =SUM(X22:X47) -> 8037053.1 | AE19: =SUM(AE22:AE47) -> 81119394 | AH19: 81119394
A20: 业主结算明细 | L20: 收入确认表 | P20: 开票明细表（可按开票时间汇总登记） | Z20: 收款明细
A21: 业主名称 | B21: 验工时间 | C21: 验工计价 | D21: 结算内容 | E21: 列账金额 | F21: 税率 | G21: 不含税金额(注意与账上保持一致） | H21: 税额(注意与账上保持一致） | I21: 列账凭证时间 | J21: 预付款转回 | K21: 罚没等其他金额 | L21: 业主名称 | M21: 凭证时间 | N21: 收入类型 | O21: 确认金额 | P21: 业主名称 | Q21: 凭证时间 | R21: 开票内容 | S21: 开票时间 | T21: 发票号码 | U21: 发票代码 | V21: 发票金额 | W21: 不含税金额 | X21: 税额 | Y21: 税率 | Z21: 单位名称 | AA21: 凭证日期 | AB21: 收款账户类型 | AC21: 收款账户名称 | AD21: 收款账户银行账号 | AE21: 收款金额 | AF21: 收款性质 | AG21: 收款备注
A22: 攀枝花市水务（集团）有限公司 | C22: 3326600 | D22: 勘察设计 | E22: 3326600 | F22: 0.06 | G22: =E22-H22 -> 3138301.9 | H22: 188298.12 | I22: 43664 | L22: 攀枝花市水务（集团）有限公司 | M22: 43762 | N22: 勘察设计 | O22: 2510641.5 | P22: 攀枝花市水务（集团）有限公司 | Q22: 43762 | R22: 勘察设计 | V22: 2661280 | W22: =ROUND(V22/(1+Y22),2) -> 2510641.5 | X22: =V22-W22 -> 150638.49 | Y22: 0.06 | Z22: 攀枝花市水务（集团）有限公司 | AA22: 44347 | AB22: 专户 | AC22: 中铁二院攀枝花小沙坝污水处理厂改扩建EPC项目部 | AE22: 690320 | AF22: 勘察设计
A23: 攀枝花市水务（集团）有限公司 | C23: 35095447 | D23: 工程施工 | E23: 35095447 | F23: 0.09 | G23: =ROUND(E23/(1+F23),2) -> 32197658 | H23: =C23-G23 -> 2897789.2 | I23: 43819 | L23: 攀枝花市水务（集团）有限公司 | M23: 44173 | N23: 工程施工 | O23: 32197658 | P23: 攀枝花市水务（集团）有限公司 | Q23: 43851 | R23: 工程施工 | V23: 35095447 | W23: =ROUND(V23/(1+Y23),2) -> 32197658 | X23: =V23-W23 -> 2897789.2 | Y23: 0.09 | Z23: 攀枝花市水务（集团）有限公司 | AA23: 44347 | AB23: 专户 | AC23: 中铁二院攀枝花小沙坝污水处理厂改扩建EPC项目部 | AE23: 1970960 | AF23: 勘察设计
A24: 攀枝花市水务（集团）有限公司 | C24: 35078952 | D24: 设备采购 | E24: 35078952 | F24: 0.13 | G24: 30090326 | H24: 4988625.4 | I24: 43832 | L24: 攀枝花市水务（集团）有限公司 | M24: 44561 | N24: 设备采购 | O24: 30090326 | P24: 攀枝花市水务（集团）有限公司 | Q24: 43798 | R24: 设备采购 | V24: 43362667 | W24: =ROUND(V24/(1+Y24),2) -> 38374042 | X24: =V24-W24 -> 4988625.4 | Y24: 0.13 | Z24: 攀枝花市水务（集团）有限公司 | AA24: 44347 | AB24: 专户 | AC24: 中铁二院攀枝花小沙坝污水处理厂改扩建EPC项目部 | AE24: 78458114 | AF24: 工程施工
A25: 攀枝花市水务（集团）有限公司 | C25: 8283715.4 | D25: 设备采购 | E25: 8283715.4 | F25: 0.13 | G25: 8283715.4 | I25: 44003 | L25: 攀枝花市水务（集团）有限公司 | M25: 44173 | N25: 勘察设计 | O25: 627660.38
L26: 攀枝花市水务（集团）有限公司 | M26: 44173 | N26: 工程施工 | O26: 3710093
L27: 攀枝花市水务（集团）有限公司 | M27: 45657 | N27: 设备采购 | O27: 8283715.4
L28: 攀枝花市水务（集团）有限公司 | M28: 45657 | N28: 工程施工 | O28: 144932.04
A50: 表四：分包方基础明细表 | C50: =SUM(C53:C77) -> 76850631 | E50: =SUM(E53:E77) -> 76850631 | G50: =SUM(G53:G77) -> 70127390 | H50: =SUM(H53:H77) -> 6723241.7 | J50: =SUM(J53:J77) -> 0 | K50: =SUM(K53:K77) -> 0 | R50: =SUM(R53:R77) -> 78018952 | S50: =SUM(S53:S77) -> 70227900 | T50: =SUM(T53:T77) -> 7791051.6 | AA50: =SUM(AA53:AA77) -> 78018950 | AH50: 78018950
A51: 分包（采购）结算明细表 | L51: 分包（采购）发票明细表开票明细表（可按开票时间汇总登记） | V51: 分包（采购）付款明细表
A52: 单位名称 | B52: 验工时间 | C52: 验工计价 | D52: 结算内容 | E52: 金额 | F52: 税率 | G52: 不含税金额(注意与账上保持一致） | H52: 税额(注意与账上保持一致） | I52: 列账凭证时间 | J52: 预付款转回 | K52: 罚没等其他金额 | L52: 单位名称 | M52: 凭证时间 | N52: 开票内容 | O52: 开票时间 | P52: 发票号码 | Q52: 发票代码 | R52: 发票金额 | S52: 不含税金额 | T52: 税额 | U52: 税率 | V52: 单位名称 | W52: 凭证日期 | X52: 付款账户类型 | Y52: 付款账户名称 | Z52: 付款账户银行账号 | AA52: 付款金额 | AB52: 付款性质 | AC52: 付款备注
A53: 成都城格城乡规划设计有限公司 | C53: 630000 | D53: 勘察设计 | E53: 630000 | F53: 0.06 | G53: =ROUND(E53/(1+F53),2) -> 594339.62 | H53: =C53-G53 -> 35660.38 | I53: 43726 | L53: 成都城格城乡规划设计有限公司 | M53: 43815 | N53: 勘察设计 | R53: 630000 | S53: =ROUND(R53/(1+U53),2) -> 594339.62 | T53: =R53-S53 -> 35660.38 | U53: 0.06 | V53: 四川信纬建设集团有限公司 | W53: 44500 | X53: 专户 | Y53: 中铁二院攀枝花小沙坝污水处理厂改扩建EPC项目部 | AA53: 34442713 | AB53: 工程施工 | AH53: =AA53+AA54 -> 76888950
A54: 冶金工业部华东勘察基础工程总公司成都分公司 | C54: 500000 | D54: 勘察设计 | E54: 500000 | F54: 0.06 | G54: =ROUND(E54/(1+F54),2) -> 471698.11 | H54: =C54-G54 -> 28301.89 | I54: 43850 | L54: 冶金工业部华东勘察基础工程总公司成都分公司 | M54: 43815 | N54: 勘察设计 | R54: 500000 | S54: =ROUND(R54/(1+U54),2) -> 471698.11 | T54: =R54-S54 -> 28301.89 | U54: 0.06 | V54: 上海恒实环保能源（集团）有限公司 | W54: 44500 | X54: 专户 | Y54: 中铁二院攀枝花小沙坝污水处理厂改扩建EPC项目部 | AA54: 42446237 | AB54: 设备采购
A55: 四川信纬建设集团有限公司 | C55: 34442715 | D55: 工程施工 | E55: 34442715 | F55: 0.09 | G55: =ROUND(E55/(1+F55),2) -> 31598821 | H55: =C55-G55 -> 2843893.9 | I55: 43892 | L55: 四川信纬建设集团有限公司 | M55: 44465 | N55: 工程施工 | R55: 34442715 | S55: =ROUND(R55/(1+U55),2) -> 31598821 | T55: =R55-S55 -> 2843893.9 | U55: 0.09 | V55: 冶金工业部华东勘察基础工程总公司成都分公司 | W55: 44500 | X55: 专户 | Y55: 中铁二院攀枝花小沙坝污水处理厂改扩建EPC项目部 | AA55: 500000 | AB55: 勘察设计 | AH55: =AE19-AA50 -> 3100443.8
A56: 上海恒实环保能源（集团）有限公司 | C56: 33064730 | D56: 设备采购 | E56: 33064730 | F56: 0.13 | G56: =ROUND(E56/(1+F56),2) -> 29260823 | H56: =C56-G56 -> 3803907 | I56: 44064 | L56: 上海恒实环保能源（集团）有限公司 | M56: 43815 | N56: 设备采购 | R56: 42446237 | S56: =ROUND(R56/(1+U56),2) -> 37563042 | T56: =R56-S56 -> 4883195.4 | U56: 0.13 | V56: 成都城格城乡规划设计有限公司 | W56: 44500 | X56: 专户 | Y56: 中铁二院攀枝花小沙坝污水处理厂改扩建EPC项目部 | AA56: 630000 | AB56: 勘察设计
A57: 上海恒实环保能源（集团）有限公司 | C57: 8074168.2 | D57: 设备采购 | E57: 8074168.2 | F57: 0.13 | G57: 8074168.2 | I57: 44127
A58: 四川信纬建设集团有限公司 | C58: 4397500 | D58: 工程施工 | E58: 4397500 | F58: 0.09 | G58: =ROUND(E58/(1+F58),2) -> 4034403.7 | H58: =C58-G58 -> 363096.33 | I58: 44166
A59: 四川信纬建设集团有限公司 | C59: -4258481.2 | D59: 工程施工 | E59: -4258481.2 | F59: 0.09 | G59: =ROUND(E59/(1+F59),2) -> -3906863.5 | H59: =C59-G59 -> -351617.71 | I59: 44432
A60: 四川信纬建设集团有限公司
A80: 表五：预缴税款情况统计表
A81: 凭证号/时间 | B81: 销售额 | C81: 扣除金额 | D81: 增值税 | E81: 城市维护建设税 | F81: 教育费附加 | G81: 地方教育费附加 | H81: 印花税 | I81: 企业所得税 | J81: 个人所得税 | K81: 其他税金 | L81: 合计 | M81: 备注
D82: 11976.73 | E82: 838.38 | F82: 359.3 | G82: 239.54 | H82: 28651.68 | L82: =SUM(D82:K82) -> 42065.63
L83: =SUM(D83:K83) -> 0
L84: =SUM(D84:K84) -> 0
L85: =SUM(D85:K85) -> 0
L86: =SUM(D86:K86) -> 0
L87: =SUM(D87:K87) -> 0
L88: =SUM(D88:K88) -> 0
L89: =SUM(D89:K89) -> 0
L90: =SUM(D90:K90) -> 0
L91: =SUM(D91:K91) -> 0
L92: =SUM(D92:K92) -> 0
L93: =SUM(D93:K93) -> 0
L94: =SUM(D94:K94) -> 0
A95: 合计 | B95: =SUM(B82:B94) -> 0 | C95: =SUM(C82:C94) -> 0 | D95: =SUM(D82:D94) -> 11976.73 | E95: =SUM(E82:E94) -> 838.38 | F95: =SUM(F82:F94) -> 359.3 | G95: =SUM(G82:G94) -> 239.54 | H95: =SUM(H82:H94) -> 28651.68 | I95: =SUM(I82:I94) -> 0 | ... M95: =SUM(M82:M94) -> 0
A97: 表六：间接费用、财务费用、附加费明细表
A98: 费用类型 | B98: 以前年度累计 | C98: 2023年 | D98: 2024年 | E98: 2025年 | F98: 2026年 | G98: 2027年 | H98: 2028年 | I98: 合计
A99: 间接费用 | B99: 396012.18 | I99: =SUM(B99:H99) -> 396012.18
A100: 财务费用 | B100: =B102-B101 -> -24076.46 | C100: =C102-C101 -> 78.11 | D100: =D102-D101 -> 563.07 | I100: =SUM(B100:H100) -> -23435.28
A101: 其中：利息收入 | B101: 28117.39 | C101: 281.89 | D101: 215.94 | I101: =SUM(B101:H101) -> 28615.22
A102: 手续费支出 | B102: 4040.93 | C102: 360 | D102: 779.01 | I102: =SUM(B102:H102) -> 5179.94
A103: 营业外收入 | I103: =SUM(B103:H103) -> 0
A104: 营业外支出 | I104: =SUM(B104:H104) -> 0
A107: 表七：往来类科目明细表
A108: 项目名称 | B108: 应收账款 | C108: 合同负债 | D108: 合同资产 | E108: 长期应收款 | F108: 其他应收款 | G108: 应付账款 | H108: 预付账款 | I108: 长期应付款 | J108: 其他应付款 | K108: 待转销项税额 | L108: 专业分包成本 | M108: 直接材料费 | N108: 合同结算-收入结转 | O108: 合同结算-价款结算 | P108: 工程施工结转 | Q108: 合同负债增值税 | R108: 应付账款-预付账款增值税
A109: =M4 -> 攀枝花小沙坝污水处理厂改扩建工程勘察-设计-采购-施工总承包合同 | B109: 665320 | G109: 139020.43 | H109: 1307339.1 | K109: 37659.62 | L109: 62281272 | M109: 8074168.2 | N109: 36052683 | O109: 32197658 | P109: 70751453
A112: 表八：施工收入、成本计算表
A113: 2024年合同工程施工收入、成本计算表
A115: =L4 -> 中铁二院攀枝花小沙坝污水处理厂改扩建EPC项目部 | H115: 金额：元
A116: 序号 | B116: 名称 | C116: 期初数 | D116: 1季度 | E116: 2季度 | F116: 3季度 | G116: 4季度 | H116: 开累数
A117: 1 | B117: 工程施工预计总收入 | H117: =V13 -> 45979853
A118: 2 | B118: 工程施工预计总成本 | H118: =W13 -> 45060256
A119: 3 | B119: 工程施工预计合同毛利 | H119: =H117-H118 -> 919597.06
A120: 4 | B120: 工程施工确认营业成本 | D120: 0 | H120: =C120+D120+E120+F120+G120 -> 0
A121: 5 | B121: 工程施工确认营业收入 | D121: 0 | H121: =C121+D121+E121+F121+G121 -> 0
A122: 6 | B122: 完工百分比 | C122: =ROUND(C120/H118,10) -> 0 | D122: =ROUND((C120+D120)/H118,10) -> 0 | E122: =ROUND((C120+D120+E120)/H118,10) -> 0 | F122: =ROUND((C120+D120+E120+F120)/H118,10) -> 0 | G122: =ROUND((C120+D120+E120+F120+G120)/H118,10) -> 0
A123: 7 | B123: 确认营业毛利 | C123: =C121-C120 -> 0 | D123: =D121-D120 -> 0 | E123: =E121-E120 -> 0 | F123: =F121-F120 -> 0 | G123: =G121-G120 -> 0
A124: 8 | B124: 累计营业毛利 | C124: =C121-C120 -> 0 | D124: =C123+D123 -> 0 | E124: =C123+D123+E123 -> 0 | F124: =C123+D123+E123+F123 -> 0 | G124: =C123+D123+E123+F123+G123 -> 0
B126: 制表人： | G126: 项目部签字：
A128: 表九：数据校验
A129: 业主往来检验 | B129: 业主发票检验 | C129: 业主收入检验 | D129: 分包往来检验 | E129: 分包验工计价校验 | F129: 预缴税金检验 | G129: 两金指标
A130: =G13-T13-B109+C109-E109-F109-Q109-D109 -> 0 | B130: =H19-X19-K109+Q109 -> 0.010000004 | C130: =SUMIFS($G$53:$G$78,$D$53:$D$78,C12)/H118*H117-O13 -> -3678845.2 | D130: =G14+G15-T14-T15-G109+H109-I109-J109+R109 -> 4.4237822e-09 | E130: =C13*(1-K4)-C14-C15 -> -188195.35 | F130: =(SUMIFS($V$22:$V$48,$R$22:$R$48,C12)-SUMIFS($R$53:$R$78,$N$53:$N$78,C12))/1.09*0.02-D95 -> 0.011284404 | G130: =B109-C109+N109-O109 -> 4520345
A131: 应为零 | B131: 应为零 | C131: 应为零 | D131: 应为零 | E131: 应为零（正数为未验完，负数为超验） | F131: 应为零 | G131: 应尽量小，超过1000万预警
C132: =(G55)/W13*V13 -> 32243695
C133: =C132-SUM(O23,O26) -> -3664056.2
C134: =C130-C133 -> -14788.989
C138: -3678845.2

Sheet 攀枝花炳草岗
A1: 表一：基础信息表
A2: 单位名称 | B2: 合同名称 | C2: 合同编号 | D2: 合同类型 | E2: 合同金额 | K2: 管理费比例 | L2: 共享系统部门名称 | M2: 共享系统项目名称 | N2: 合同签订单位 | O2: 项目管理单位 | P2: 业主财务联系人及电话 | Q2: 分包方财务联系人及电话 | R2: 项目部经理及电话 | S2: 合同开工日期 | T2: 预计竣工时间 | U2: 合同工期 | V2: 工程类型 | W2: 项目所在地（*省*市） | X2: 项目状态 | Y2: 工程进度款支付比例 | Z2: 勘察设计费支付比例 | AA2: 主管税务机构名称 | AB2: 税务管理员及电话 | AC2: 银行行号 | AD2: 开户行 | AE2: 银行行号 | AF2: 银行账户名称 | AG2: 银行账号 | AH2: 银行地址 | AI2: 银行联系人 | AJ2: 备注
E3: 勘察设计 | F3: 工程施工 | G3: 设备采购 | H3: 业主承担管理费 | I3: 技术服务等 | J3: 合计
A4: 攀枝花市水务（集团）有限公司 | B4: 攀枝花市炳草岗污水处理厂提标升级改造工程项目勘察设计材料及设备采购施工总承包 | C4: 2019-生环院(总包)-003 | D4: 总包合同 | E4: 3010000 | F4: =60280000-G4 -> 34064400 | G4: 26215600 | J4: =SUM(E4:I4) -> 63290000 | K4: =(F4-F5)/F4 -> 0.022 | L4: 中铁二院攀枝花市炳草岗污水处理厂提标升级改造工程EPC项目部 | M4: 攀枝花市炳草岗污水处理厂提标升级改造工程勘察设计-材料及设备采购-施工总承包 | N4: 生态环境院 | O4: 生态环境院 | V4: 市政 | W4: 四川省攀枝花市 | X4: 收尾 | Y4: 0.9 | Z4: 0.8
A5: 四川锐信路桥工程有限公司 | B5: 攀枝花市炳草岗污水处理厂提标升级改造工程勘察设计-材料及设备采购-施工总承包联合体补充协议 | C5: 2019-生环院(分包)(总包)-001 | D5: 分包合同 | F5: =F4*0.978 -> 33314983 | J5: =SUM(E5:I5) -> 33314983
A6: 冶金工业部华东勘察基础工程总公司成都分公司 | B6: 攀枝花市炳草岗项目工程详勘 | C6: 2019-生环院(自揽外包)（承包）-008 | D6: 分包合同 | E6: 490000 | J6: =E6 -> 490000
A7: 璟城设计顾问有限公司 | B7: 技术服务合同 | D7: 分包合同 | E7: 450000 | J7: =E7 -> 450000
A8: 上海恒实环保能源（集团）有限公司 | B8: 攀枝花炳草岗污水处理厂提标升级改造工程项目设备采购及伴随服务合同 | C8: 2024-生环院(分包)(总包)-001 | D8: 分包合同 | G8: =25020600*0.978 -> 24470147 | J8: =SUM(E8:I8) -> 24470147
A10: 表二：汇总表 | O10: =O13+P13 -> 47214231 | P10: =O14+P17 -> 46492257 | Q10: =O10*0.978-P10 -> -316738.81
A11: 单位名称 | B11: 累计验工计价 | H11: 累计开票 | N11: 累计收入或成本 | T11: 累计收款/付款 | U11: 银行账户余额 | V11: 工程施工预计总收入 | W11: 工程施工预计总成本
B12: 勘察设计 | C12: 工程施工 | D12: 设备采购 | E12: 业主承担管理费 | F12: 服务费 | G12: 合计 | H12: 勘察设计 | I12: 工程施工 | J12: 设备采购 | K12: 业主承担管理费 | L12: 服务费 | M12: 合计 | N12: 勘察设计 | O12: 工程施工 | P12: 设备采购 | Q12: 业主承担管理费 | R12: 服务费 | S12: 合计
A13: 攀枝花市水务（集团）有限公司 | B13: =SUMIFS($E$22:$E$48,$D$22:$D$48,$B$12,$A$22:$A$48,$A$13) -> 3010000 | C13: =SUMIFS($E$22:$E$48,$D$22:$D$48,C12,$A$22:$A$48,A13) -> 31902290 | D13: =SUMIFS($E$22:$E$48,$D$22:$D$48,D12,$A$22:$A$48,A13) -> 18235665 | E13: =SUMIFS($E$22:$E$48,$D$22:$D$48,E12,$A$22:$A$48,A13) -> 0 | F13: =SUMIFS($E$22:$E$48,$D$22:$D$48,F12,$A$22:$A$48,A13) -> 0 | G13: =SUM(B13:F13) -> 53147955 | H13: =SUMIFS($V$22:$V$48,$R$22:$R$48,$H$12,$P$22:$P$48,$A$13) -> 2408000 | I13: =SUMIFS($V$22:$V$48,$R$22:$R$48,I12,$P$22:$P$48,$A$13) -> 33902290 | J13: =SUMIFS($V$22:$V$48,$R$22:$R$48,$J$12,$P$22:$P$48,$A$13) -> 18235665 | K13: =SUMIFS($V$22:$V$48,$R$22:$R$48,$K$12,$P$22:$P$48,$A$13) -> 0 | L13: =SUMIFS($V$22:$V$48,$R$22:$R$48,$L$12,$P$22:$P$48,$A$13) -> 0 | M13: =SUM(H13:L13) -> 54545955 | N13: =SUMIFS($O$22:$O$47,$N$22:$N$47,N12,$L$22:$L$47,A13) -> 2839622.6 | O13: =SUMIFS($O$22:$O$47,$N$22:$N$47,O12,$L$22:$L$47,A13) -> 31076474 | P13: =SUMIFS($O$22:$O$47,$N$22:$N$47,P12,$L$22:$L$47,A13) -> 16137757 | Q13: =SUMIFS($O$22:$O$47,$N$22:$N$47,Q12,$L$22:$L$47,A13) -> 0 | R13: =SUMIFS($O$22:$O$47,$N$22:$N$47,R12,$L$22:$L$47,A13) -> 0 | S13: =SUM(N13:R13) -> 50053853 | T13: =SUMIF($Z$22:$Z$48,A13,$AE$22:$AE$48) -> 54545955 | V13: =F4/1.09 -> 31251743 | W13: =(F5+F8)/1.09 -> 30564205 | X13: 31251743 | Y13: 30564205
A14: 四川锐信路桥工程有限公司 | B14: =SUMIFS($E$53:$E$78,$D$53:$D$78,B12,$A$53:$A$78,A14) -> 0 | C14: =SUMIFS($E$53:$E$78,$D$53:$D$78,C12,$A$53:$A$78,A14) -> 29945306 | D14: =SUMIFS($E$53:$E$78,$D$53:$D$78,D12,$A$53:$A$78,A14) -> 0 | E14: =SUMIFS($E$53:$E$78,$D$53:$D$78,E12,$A$53:$A$78,A14) -> 0 | F14: =SUMIFS($E$53:$E$78,$D$53:$D$78,F12,$A$53:$A$78,A14) -> 0 | G14: =SUM(B14:F14) -> 29945306 | H14: =SUMIFS($R$53:$R$78,$N$53:$N$78,H12,$L$53:$L$78,A14) -> 0 | I14: =SUMIFS($R$53:$R$78,$N$53:$N$78,I12,$L$53:$L$78,A14) -> 29945306 | J14: =SUMIFS($R$53:$R$78,$N$53:$N$78,J12,$L$53:$L$78,A14) -> 0 | K14: =SUMIFS($R$53:$R$78,$N$53:$N$78,K12,$L$53:$L$78,A14) -> 0 | L14: =SUMIFS($R$53:$R$78,$N$53:$N$78,L12,$L$53:$L$78,A14) -> 0 | M14: =SUM(H14:L14) -> 29945306 | N14: =SUMIFS($G$53:$G$78,$D$53:$D$78,N12,$A$53:$A$78,A14) -> 0 | O14: =SUMIFS($G$53:$G$78,$D$53:$D$78,$O$12,$A$53:$A$78,A14) -> 27472758 | P14: =SUMIFS($G$53:$G$78,$D$53:$D$78,$P$12,$A$53:$A$78,A14) -> 0 | Q14: =SUMIFS($G$53:$G$78,$D$53:$D$78,$Q$12,$A$53:$A$78,A14) -> 0 | R14: =SUMIFS($G$53:$G$78,$D$53:$D$78,$R$12,$A$53:$A$78,A14) -> 0 | S14: =SUM(N14:R14) -> 27472758 | T14: =SUMIF($V$53:$V$78,A14,$AA$53:$AA$78) -> 29901306
A15: 冶金工业部华东勘察基础工程总公司成都分公司 | B15: =SUMIFS($E$53:$E$78,$D$53:$D$78,B12,$A$53:$A$78,A15) -> 490000 | C15: =SUMIFS($E$53:$E$78,$D$53:$D$78,C12,$A$53:$A$78,A15) -> 0 | D15: =SUMIFS($E$53:$E$78,$D$53:$D$78,D12,$A$53:$A$78,A15) -> 0 | E15: =SUMIFS($E$53:$E$78,$D$53:$D$78,E12,$A$53:$A$78,A15) -> 0 | F15: =SUMIFS($E$53:$E$78,$D$53:$D$78,F12,$A$53:$A$78,A15) -> 0 | G15: =SUM(B15:F15) -> 490000 | H15: =SUMIFS($R$53:$R$78,$N$53:$N$78,H12,$L$53:$L$78,A15) -> 490000 | I15: =SUMIFS($R$53:$R$78,$N$53:$N$78,I12,$L$53:$L$78,A15) -> 0 | J15: =SUMIFS($R$53:$R$78,$N$53:$N$78,J12,$L$53:$L$78,A15) -> 0 | K15: =SUMIFS($R$53:$R$78,$N$53:$N$78,K12,$L$53:$L$78,A15) -> 0 | L15: =SUMIFS($R$53:$R$78,$N$53:$N$78,L12,$L$53:$L$78,A15) -> 0 | M15: =SUM(H15:L15) -> 490000 | N15: =SUMIFS($G$53:$G$78,$D$53:$D$78,$N$12,$A$53:$A$78,A15) -> 462264.15 | O15: =SUMIFS($G$53:$G$78,$D$53:$D$78,$O$12,$A$53:$A$78,A15) -> 0 | P15: =SUMIFS($G$53:$G$78,$D$53:$D$78,$P$12,$A$53:$A$78,A15) -> 0 | Q15: =SUMIFS($G$53:$G$78,$D$53:$D$78,$Q$12,$A$53:$A$78,A15) -> 0 | R15: =SUMIFS($G$53:$G$78,$D$53:$D$78,$R$12,$A$53:$A$78,A15) -> 0 | S15: =SUM(N15:R15) -> 462264.15 | T15: =SUMIF($V$53:$V$78,A15,$AA$53:$AA$78) -> 490000
A16: 璟城设计顾问有限公司 | B16: =SUMIFS($E$53:$E$78,$D$53:$D$78,B12,$A$53:$A$78,A16) -> 360000 | C16: =SUMIFS($E$53:$E$78,$D$53:$D$78,C13,$A$53:$A$78,A16) -> 0 | D16: =SUMIFS($E$53:$E$78,$D$53:$D$78,D13,$A$53:$A$78,A16) -> 0 | E16: =SUMIFS($E$53:$E$78,$D$53:$D$78,E13,$A$53:$A$78,A16) -> 0 | F16: =SUMIFS($E$53:$E$78,$D$53:$D$78,F13,$A$53:$A$78,A16) -> 0 | G16: =SUM(B16:F16) -> 360000 | H16: =SUMIFS($R$53:$R$78,$N$53:$N$78,H12,$L$53:$L$78,A16) -> 360000 | I16: =SUMIFS($R$53:$R$78,$N$53:$N$78,I13,$L$53:$L$78,A16) -> 0 | J16: =SUMIFS($R$53:$R$78,$N$53:$N$78,J13,$L$53:$L$78,A16) -> 0 | K16: =SUMIFS($R$53:$R$78,$N$53:$N$78,K13,$L$53:$L$78,A16) -> 0 | L16: =SUMIFS($R$53:$R$78,$N$53:$N$78,L13,$L$53:$L$78,A16) -> 0 | M16: =SUM(H16:L16) -> 360000 | N16: =SUMIFS($G$53:$G$78,$D$53:$D$78,$N$12,$A$53:$A$78,A16) -> 339622.64 | O16: =SUMIFS($G$53:$G$78,$D$53:$D$78,$O$12,$A$53:$A$78,A16) -> 0 | P16: =SUMIFS($G$53:$G$78,$D$53:$D$78,$P$12,$A$53:$A$78,A16) -> 0 | Q16: =SUMIFS($G$53:$G$78,$D$53:$D$78,$Q$12,$A$53:$A$78,A16) -> 0 | R16: =SUMIFS($G$53:$G$78,$D$53:$D$78,$R$12,$A$53:$A$78,A16) -> 0 | S16: =SUM(N16:R16) -> 339622.64 | T16: =SUMIF($V$53:$V$78,A16,$AA$53:$AA$78) -> 360000
A17: 上海恒实环保能源（集团）有限公司 | B17: =SUMIFS($E$53:$E$78,$D$53:$D$78,B14,$A$53:$A$78,A17) -> 0 | C17: =SUMIFS($E$53:$E$78,$D$53:$D$78,C14,$A$53:$A$78,A17) -> 0 | D17: =SUMIFS($E$53:$E$78,$D$53:$D$78,D12,$A$53:$A$78,A17) -> 21111614 | E17: =SUMIFS($E$53:$E$78,$D$53:$D$78,E14,$A$53:$A$78,A17) -> 0 | F17: =SUMIFS($E$53:$E$78,$D$53:$D$78,F14,$A$53:$A$78,A17) -> 0 | G17: =SUM(B17:F17) -> 21111614 | H17: =SUMIFS($R$53:$R$78,$N$53:$N$78,H14,$L$53:$L$78,A17) -> 0 | I17: =SUMIFS($R$53:$R$78,$N$53:$N$78,I14,$L$53:$L$78,A17) -> 0 | J17: =SUMIFS($R$53:$R$78,$N$53:$N$78,J12,$L$53:$L$78,A17) -> 21111614 | K17: =SUMIFS($R$53:$R$78,$N$53:$N$78,K14,$L$53:$L$78,A17) -> 0 | L17: =SUMIFS($R$53:$R$78,$N$53:$N$78,L14,$L$53:$L$78,A17) -> 0 | M17: =SUM(H17:L17) -> 21111614 | N17: =SUMIFS($G$53:$G$78,$D$53:$D$78,$N$12,$A$53:$A$78,A17) -> 0 | O17: =SUMIFS($G$53:$G$78,$D$53:$D$78,$O$12,$A$53:$A$78,A17) -> 0 | P17: =SUMIFS($G$53:$G$78,$D$53:$D$78,$P$12,$A$53:$A$78,A17) -> 19019499 | Q17: =SUMIFS($G$53:$G$78,$D$53:$D$78,$Q$12,$A$53:$A$78,A17) -> 0 | R17: =SUMIFS($G$53:$G$78,$D$53:$D$78,$R$12,$A$53:$A$78,A17) -> 0 | S17: =SUM(N17:R17) -> 19019499 | T17: =SUMIF($V$53:$V$78,A17,$AA$53:$AA$78) -> 21089614
A19: 表三：业主基础明细表 | C19: =SUM(C22:C47) -> 53147955 | E19: =SUM(E22:E47) -> 53147955 | G19: =SUM(G22:G47) -> 48245535 | H19: =SUM(H22:H47) -> 4902419.7 | O19: =SUM(O22:O47) -> 50053853 | V19: =SUM(V22:V47) -> 54545955 | W19: =SUM(W22:W47) -> 49165813 | X19: =SUM(X22:X47) -> 5033481.9 | AE19: =SUM(AE22:AE47) -> 54545955
A20: 业主结算明细 | L20: 收入确认表 | P20: 开票明细表（可按开票时间汇总登记） | Z20: 收款明细
A21: 业主名称 | B21: 验工时间 | C21: 验工计价 | D21: 结算内容 | E21: 列账金额 | F21: 税率 | G21: 不含税金额(注意与账上保持一致） | H21: 税额(注意与账上保持一致） | I21: 列账凭证时间 | J21: 预付款转回 | K21: 罚没等其他金额 | L21: 业主名称 | M21: 凭证时间 | N21: 收入类型 | O21: 确认金额 | P21: 业主名称 | Q21: 凭证时间 | R21: 开票内容 | S21: 开票时间 | T21: 发票号码 | U21: 发票代码 | V21: 发票金额 | W21: 不含税金额 | X21: 税额 | Y21: 税率 | Z21: 单位名称 | AA21: 凭证日期 | AB21: 收款账户类型 | AC21: 收款账户名称 | AD21: 收款账户银行账号 | AE21: 收款金额 | AF21: 收款性质 | AG21: 收款备注
A22: 攀枝花市水务（集团）有限公司 | C22: 3010000 | D22: 勘察设计 | E22: 3010000 | F22: 0.06 | G22: 2839622.6 | H22: 170377.35 | I22: 43762 | L22: 攀枝花市水务（集团）有限公司 | M22: 43762 | N22: 勘察设计 | O22: 2271698.1 | P22: 攀枝花市水务（集团）有限公司 | Q22: 43664 | R22: 勘察设计 | V22: 2408000 | W22: 2271698.1 | X22: 136301.88 | Z22: 攀枝花市水务（集团）有限公司 | AA22: 45348 | AB22: 专户 | AC22: 中铁二院攀枝花市炳草岗污水处理厂提标升级改造工程EPC项目部 | AE22: 440000 | AF22: 勘察设计
A23: 攀枝花市水务（集团）有限公司 | C23: 31902290 | D23: 工程施工 | E23: 31902290 | F23: 0.09 | G23: 29268156 | H23: 2634134 | I23: 44173 | L23: 攀枝花市水务（集团）有限公司 | M23: 44195 | N23: 工程施工 | O23: 29001888 | P23: 攀枝花市水务（集团）有限公司 | Q23: 43819 | R23: 工程施工 | V23: 31902290 | W23: 29001888 | X23: 2634134 | Z23: 攀枝花市水务（集团）有限公司 | AA23: 45348 | AB23: 专户 | AC23: 中铁二院攀枝花市炳草岗污水处理厂提标升级改造工程EPC项目部 | AE23: 1968000 | AF23: 勘察设计
A24: 攀枝花市水务（集团）有限公司 | C24: 17155273 | D24: 设备采购 | E24: 17155273 | F24: 0.13 | G24: 15172409 | H24: 1982864.1 | I24: 44173 | L24: 攀枝花市水务（集团）有限公司 | M24: 44561 | N24: 设备采购 | O24: 15172409 | P24: 攀枝花市水务（集团）有限公司 | Q24: 43832 | R24: 设备采购 | V24: 17235665 | W24: 15172409 | X24: 1982864.1 | Z24: 攀枝花市水务（集团）有限公司 | AA24: 45348 | AB24: 专户 | AC24: 中铁二院攀枝花市炳草岗污水处理厂提标升级改造工程EPC项目部 | AE24: 52137955 | AF24: 工程施工 | AH24: =AE24 -> 52137955
A25: 攀枝花市水务（集团）有限公司 | C25: 1000000 | D25: 设备采购 | E25: 1000000 | F25: 0.13 | G25: =ROUND(E25/(1+F25),2) -> 884955.75 | H25: =C25-G25 -> 115044.25 | I25: 45473 | L25: 攀枝花市水务（集团）有限公司 | M25: 43762 | N25: 勘察设计 | O25: 567924.53 | P25: 攀枝花市水务（集团）有限公司 | Q25: 44003 | R25: 工程施工 | V25: 2000000 | W25: 1834862.4 | X25: 165137.61
A26: 攀枝花市水务（集团）有限公司 | C26: 80391.74 | D26: 设备采购 | E26: 80391.74 | F26: 0.13 | G26: 80391.74 | I26: 45657 | L26: 攀枝花市水务（集团）有限公司 | M26: 44561 | N26: 工程施工 | O26: 198448.95 | P26: 攀枝花市水务（集团）有限公司 | Q26: 44065 | R26: 设备采购 | V26: 1000000 | W26: 884955.75 | X26: 115044.25
L27: 攀枝花市水务（集团）有限公司 | M27: 45473 | N27: 设备采购 | O27: 884955.75
L28: 攀枝花市水务（集团）有限公司 | M28: 45657 | N28: 设备采购 | O28: 80391.74
L29: 攀枝花市水务（集团）有限公司 | M29: 45473 | N29: 工程施工 | O29: 1876137.4
A50: 表四：分包方基础明细表 | C50: =SUM(C53:C77) -> 51906920 | E50: =SUM(E53:E77) -> 51906920 | G50: =SUM(G53:G77) -> 47294143 | H50: =SUM(H53:H77) -> 4612776.7 | J50: =SUM(J53:J77) -> 0 | K50: =SUM(K53:K77) -> 0 | R50: =SUM(R53:R77) -> 51906920 | S50: =SUM(S53:S77) -> 46957489 | T50: =SUM(T53:T77) -> 4949431.2 | AA50: =SUM(AA53:AA77) -> 51840920 | AD50: 51840920 | AE50: =AA50-AD50 -> 0
A51: 分包（采购）结算明细表 | L51: 分包（采购）发票明细表开票明细表（可按开票时间汇总登记） | V51: 分包（采购）付款明细表
A52: 单位名称 | B52: 验工时间 | C52: 验工计价 | D52: 结算内容 | E52: 金额 | F52: 税率 | G52: 不含税金额(注意与账上保持一致） | H52: 税额(注意与账上保持一致） | I52: 列账凭证时间 | J52: 预付款转回 | K52: 罚没等其他金额 | L52: 单位名称 | M52: 凭证时间 | N52: 开票内容 | O52: 开票时间 | P52: 发票号码 | Q52: 发票代码 | R52: 发票金额 | S52: 不含税金额 | T52: 税额 | U52: 税率 | V52: 单位名称 | W52: 凭证日期 | X52: 付款账户类型 | Y52: 付款账户名称 | Z52: 付款账户银行账号 | AA52: 付款金额 | AB52: 付款性质 | AC52: 付款备注
A53: 璟城设计顾问有限公司 | C53: 360000 | D53: 勘察设计 | E53: 360000 | F53: 0.06 | G53: =ROUND(E53/(1+F53),2) -> 339622.64 | H53: =C53-G53 -> 20377.36 | I53: 43668 | L53: 璟城设计顾问有限公司 | M53: 43851 | N53: 勘察设计 | R53: 360000 | S53: =ROUND(R53/(1+U53),2) -> 339622.64 | T53: =R53-S53 -> 20377.36 | U53: 0.06 | V53: 四川锐信路桥工程有限公司 | W53: 45390 | X53: 专户 | Y53: 中铁二院攀枝花市炳草岗污水处理厂提标升级改造工程EPC项目部 | AA53: =27945306+1956000 -> 29901306
A54: 冶金工业部华东勘察基础工程总公司成都分公司 | C54: 490000 | D54: 勘察设计 | E54: 490000 | F54: 0.06 | G54: =ROUND(E54/(1+F54),2) -> 462264.15 | H54: =C54-G54 -> 27735.85 | I54: 43668 | L54: 冶金工业部华东勘察基础工程总公司成都分公司 | M54: 43851 | N54: 勘察设计 | R54: 490000 | S54: =ROUND(R54/(1+U54),2) -> 462264.15 | T54: =R54-S54 -> 27735.85 | U54: 0.06 | V54: 上海恒实环保能源（集团）有限公司 | W54: 45390 | X54: 专户 | Y54: 中铁二院攀枝花市炳草岗污水处理厂提标升级改造工程EPC项目部 | AA54: =20111613.99+978000 -> 21089614
A55: 四川锐信路桥工程有限公司 | C55: 27945306 | D55: 工程施工 | E55: 27945306 | F55: 0.09 | G55: =ROUND(E55/(1+F55),2) -> 25637895 | H55: =C55-G55 -> 2307410.6 | I55: 44173 | L55: 四川锐信路桥工程有限公司 | M55: 44236 | N55: 工程施工 | R55: 27945306 | S55: =ROUND(R55/(1+U55),2) -> 25637895 | T55: =R55-S55 -> 2307410.6 | U55: 0.09 | V55: 冶金工业部华东勘察基础工程总公司成都分公司 | W55: 45390 | X55: 专户 | Y55: 中铁二院攀枝花市炳草岗污水处理厂提标升级改造工程EPC项目部 | AA55: 490000
A56: 上海恒实环保能源（集团）有限公司 | C56: 17185309 | D56: 设备采购 | E56: 17185309 | F56: 0.13 | G56: =ROUND(E56/(1+F56),2) -> 15208238 | H56: =C56-G56 -> 1977071 | I56: 44173 | L56: 上海恒实环保能源（集团）有限公司 | M56: 43808 | N56: 设备采购 | R56: 20111614 | S56: =ROUND(R56/(1+U56),2) -> 17797888 | T56: =R56-S56 -> 2313725.5 | U56: 0.13 | V56: 璟城设计顾问有限公司 | W56: 45390 | X56: 专户 | Y56: 中铁二院攀枝花市炳草岗污水处理厂提标升级改造工程EPC项目部 | AA56: 360000
A57: 上海恒实环保能源（集团）有限公司 | C57: 2926304.5 | D57: 设备采购 | E57: 2926304.5 | F57: 0.13 | G57: 2926304.5 | I57: 45616 | L57: 上海恒实环保能源（集团）有限公司 | M57: 43808 | N57: 设备采购 | R57: 1000000 | S57: =ROUND(R57/(1+U57),2) -> 884955.75 | T57: =R57-S57 -> 115044.25 | U57: 0.13
A58: 四川锐信路桥工程有限公司 | C58: 2000000 | D58: 工程施工 | E58: 2000000 | F58: 0.09 | G58: =ROUND(E58/(1+F58),2) -> 1834862.4 | H58: =C58-G58 -> 165137.61 | I58: 45390 | L58: 四川锐信路桥工程有限公司 | M58: 45390 | N58: 工程施工 | R58: 2000000 | S58: =ROUND(R58/(1+U58),2) -> 1834862.4 | T58: =R58-S58 -> 165137.61 | U58: 0.09
A59: 四川锐信路桥工程有限公司 | C59: 6108071.4 | D59: 工程施工 | E59: 6108071.4 | F59: 0.09 | G59: =ROUND(E59/(1+F59),2) -> 5603735.2 | H59: =C59-G59 -> 504336.17 | I59: 45616
A60: 四川锐信路桥工程有限公司 | C60: -6108071.4 | D60: 工程施工 | E60: -6108071.4 | F60: 0.09 | G60: =ROUND(E60/(1+F60),2) -> -5603735.2 | H60: =C60-G60 -> -504336.17 | I60: 45635
A61: 上海恒实环保能源（集团）有限公司 | C61: 1000000 | D61: 设备采购 | E61: 1000000 | F61: 0.13 | G61: =ROUND(E61/(1+F61),2) -> 884955.75 | H61: =C61-G61 -> 115044.25 | I61: 45390
A80: 表五：预缴税款情况统计表
A81: 凭证号/时间 | B81: 销售额 | C81: 扣除金额 | D81: 增值税 | E81: 城市维护建设税 | F81: 教育费附加 | G81: 地方教育费附加 | H81: 印花税 | I81: 企业所得税 | J81: 个人所得税 | K81: 其他税金 | L81: 合计 | M81: 备注
D82: 73732.04 | E82: 5161.24 | F82: 2211.96 | G82: 1474.64 | H82: 28651.7 | L82: =SUM(D82:K82) -> 111231.58
A83: 45923 | B83: 10142759 | C83: 8829860.1 | D83: 24089.88 | E83: 1686.29 | F83: 722.7 | G83: 481.8 | L83: =SUM(D83:K83) -> 26980.67
L84: =SUM(D84:K84) -> 0
L85: =SUM(D85:K85) -> 0
L86: =SUM(D86:K86) -> 0
L87: =SUM(D87:K87) -> 0
L88: =SUM(D88:K88) -> 0
L89: =SUM(D89:K89) -> 0
L90: =SUM(D90:K90) -> 0
L91: =SUM(D91:K91) -> 0
L92: =SUM(D92:K92) -> 0
L93: =SUM(D93:K93) -> 0
L94: =SUM(D94:K94) -> 0
A95: 合计 | B95: =SUM(B82:B94) -> 10142759 | C95: =SUM(C82:C94) -> 8829860.1 | D95: =SUM(D82:D94) -> 97821.92 | E95: =SUM(E82:E94) -> 6847.53 | F95: =SUM(F82:F94) -> 2934.66 | G95: =SUM(G82:G94) -> 1956.44 | H95: =SUM(H82:H94) -> 28651.7 | I95: =SUM(I82:I94) -> 0 | ... M95: =SUM(M82:M94) -> 0
A97: 表六：间接费用、财务费用、附加费明细表
A98: 费用类型 | B98: 以前年度累计 | C98: 2023年 | D98: 2024年 | E98: 2025年 | F98: 2026年 | G98: 2027年 | H98: 2028年 | I98: 合计
A99: 间接费用 | B99: 226992.11 | I99: =SUM(B99:H99) -> 226992.11
A100: 财务费用 | B100: =B102-B101 -> -15515.55 | C100: =C102-C101 -> -1125.59 | D100: =D102-D101 -> -1455.74 | I100: =SUM(B100:H100) -> -18096.88
A101: 其中：利息收入 | B101: 20642.96 | C101: 1485.59 | D101: 2234.75 | I101: =SUM(B101:H101) -> 24363.3
A102: 手续费支出 | B102: 5127.41 | C102: 360 | D102: 779.01 | I102: =SUM(B102:H102) -> 6266.42
A103: 营业外收入 | I103: =SUM(B103:H103) -> 0
A104: 营业外支出 | I104: =SUM(B104:H104) -> 0
A107: 表七：往来类科目明细表
A108: 项目名称 | B108: 应收账款 | C108: 合同负债 | D108: 合同资产 | E108: 长期应收款 | F108: 其他应收款 | G108: 应付账款 | H108: 预付账款 | I108: 长期应付款 | J108: 其他应付款 | K108: 待转销项税额 | L108: 专业分包成本 | M108: 直接材料费 | N108: 合同结算-收入结转 | O108: 合同结算-价款结算 | P108: 工程施工结转 | Q108: 合同负债增值税 | R108: 应付账款-预付账款增值税
A109: =M4 -> 攀枝花市炳草岗污水处理厂提标升级改造工程勘察设计-材料及设备采购-施工总承包 | B109: -1295271.4 | G109: 66000 | K109: -28333.55 | L109: 43146229 | M109: 3811260.3 | N109: 31076474 | O109: 29268156 | P109: 47184481 | Q109: 102728.59
A112: 表八：施工收入、成本计算表
A113: 2024年合同工程施工收入、成本计算表
A115: =L4 -> 中铁二院攀枝花市炳草岗污水处理厂提标升级改造工程EPC项目部 | H115: 金额：元
A116: 序号 | B116: 名称 | C116: 期初数 | D116: 1季度 | E116: 2季度 | F116: 3季度 | G116: 4季度 | H116: 开累数
A117: 1 | B117: 工程施工预计总收入 | H117: =V13 -> 31251743
A118: 2 | B118: 工程施工预计总成本 | H118: =W13 -> 30564205
A119: 3 | B119: 工程施工预计合同毛利 | H119: =H117-H118 -> 687538.35
A120: 4 | B120: 工程施工确认营业成本 | D120: 0 | H120: =C120+D120+E120+F120+G120 -> 0
A121: 5 | B121: 工程施工确认营业收入 | D121: 0 | H121: =C121+D121+E121+F121+G121 -> 0
A122: 6 | B122: 完工百分比 | C122: =ROUND(C120/H118,10) -> 0 | D122: =ROUND((C120+D120)/H118,10) -> 0 | E122: =ROUND((C120+D120+E120)/H118,10) -> 0 | F122: =ROUND((C120+D120+E120+F120)/H118,10) -> 0 | G122: =ROUND((C120+D120+E120+F120+G120)/H118,10) -> 0
A123: 7 | B123: 确认营业毛利 | C123: =C121-C120 -> 0 | D123: =D121-D120 -> 0 | E123: =E121-E120 -> 0 | F123: =F121-F120 -> 0 | G123: =G121-G120 -> 0
A124: 8 | B124: 累计营业毛利 | C124: =C121-C120 -> 0 | D124: =C123+D123 -> 0 | E124: =C123+D123+E123 -> 0 | F124: =C123+D123+E123+F123 -> 0 | G124: =C123+D123+E123+F123+G123 -> 0
B126: 制表人： | G126: 项目部签字：
A128: 表九：数据校验
A129: 业主往来检验 | B129: 业主发票检验 | C129: 业主收入检验 | D129: 分包往来检验 | E129: 分包验工计价校验 | F129: 预缴税金检验 | G129: 两金指标
A130: =G13-T13-B109+C109-E109-F109-D109+Q109 -> -0.0020354018 | B130: =H19-X19-K109+Q109 -> 3.3469405e-10 | C130: =SUMIFS($G$53:$G$78,$D$53:$D$78,C12)/H118*H117-O13 -> -2985719.8 | D130: =G14+G15-T14-T15-G109+H109-I109-J109+R109+G16-T16+G17-T17 -> 0.00097350031 | E130: =C13*(1-K4)-C14-C15 -> 1255133.6 | F130: =(SUMIFS($V$22:$V$48,$R$22:$R$48,C12)-SUMIFS($R$53:$R$78,$N$53:$N$78,C12))/1.09*0.02-D95 -> -25216.709 | G130: =B109-C109+N109-O109 -> 513046.79
A131: 应为零 | B131: 应为零 | C131: 应为零 | D131: 应为零 | E131: 应为零（正数为未验完，负数为超验） | F131: 应为零 | G131: 应尽量小，超过1000万预警
C132: =SUM(G55)/W13*V13 -> 26214617
C133: =SUM(O23) -> 29001888
C134: =C132-C133 -> -2787270.8
C135: =C130-C134 -> -198448.95
C136: -2985719.8

Sheet XX项目 (6)
A1: 表一：基础信息表
A2: 单位名称 | B2: 合同名称 | C2: 合同编号 | D2: 合同类型 | E2: 合同金额 | K2: 管理费比例 | L2: 共享系统部门名称 | M2: 共享系统项目名称 | N2: 合同签订单位 | O2: 项目管理单位 | P2: 业主财务联系人及电话 | Q2: 分包方财务联系人及电话 | R2: 项目部经理及电话 | S2: 合同开工日期 | T2: 预计竣工时间 | U2: 合同工期 | V2: 工程类型 | W2: 项目所在地（*省*市） | X2: 项目状态 | Y2: 工程进度款支付比例 | Z2: 勘察设计费支付比例 | AA2: 主管税务机构名称 | AB2: 税务管理员及电话 | AC2: 银行行号 | AD2: 开户行 | AE2: 银行行号 | AF2: 银行账户名称 | AG2: 银行账号 | AH2: 银行地址 | AI2: 银行联系人 | AJ2: 备注
E3: 勘察设计 | F3: 工程施工 | G3: 设备采购 | H3: 业主承担管理费 | I3: 技术服务等 | J3: 合计
A4: 来源于“共享系统”列账单位名称 | B4: 来源于“合同收款系统”或共享系统项目档案 | C4: 来源于“合同收款系统” | D4: 总包合同 | J4: =SUM(E4:I4) -> 0 | K4: =(F4-F5-F6)/F4 -> #DIV/0! | L4: 来源于“共享系统”系统管理-权限管理-人员管理 | M4: 来源于“共享系统”系统管理-权限管理-人员管理 | N4: 主合同编号中的单位 | O4: 实际管理单位
A5: 来源于“共享系统”列账单位名称 | B5: 来源于“合同收款系统”或共享系统项目档案 | C5: 来源于“合同收款系统” | D5: 分包合同 | J5: =SUM(E5:I5) -> 0
D6: 分包合同 | J6: =SUM(E6:I6) -> 0
A8: 表二：汇总表
A9: 单位名称 | B9: 累计验工计价 | H9: 累计开票 | N9: 累计收入或成本 | T9: 累计收款/付款 | U9: 银行账户余额 | V9: 工程施工预计总收入 | W9: 工程施工预计总成本
B10: 勘察设计 | C10: 工程施工 | D10: 设备采购 | E10: 业主承担管理费 | F10: 服务费 | G10: 合计 | H10: 勘察设计 | I10: 工程施工 | J10: 设备采购 | K10: 业主承担管理费 | L10: 服务费 | M10: 合计 | N10: 勘察设计 | O10: 工程施工 | P10: 设备采购 | Q10: 业主承担管理费 | R10: 服务费 | S10: 合计
B11: =SUMIFS($E$20:$E$46,$D$20:$D$46,$B$10,$A$20:$A$46,$A$11) -> 0 | C11: =SUMIFS($E$20:$E$46,$D$20:$D$46,C10,$A$20:$A$46,A11) -> 0 | D11: =SUMIFS($E$20:$E$46,$D$20:$D$46,D10,$A$20:$A$46,A11) -> 0 | E11: =SUMIFS($E$20:$E$46,$D$20:$D$46,E10,$A$20:$A$46,A11) -> 0 | F11: =SUMIFS($E$20:$E$46,$D$20:$D$46,F10,$A$20:$A$46,A11) -> 0 | G11: =SUM(B11:F11) -> 0 | H11: =SUMIFS($V$20:$V$46,$R$20:$R$46,$H$10,$P$20:$P$46,$A$11) -> 0 | I11: =SUMIFS($V$20:$V$46,$R$20:$R$46,I10,$P$20:$P$46,$A$11) -> 0 | J11: =SUMIFS($V$20:$V$46,$R$20:$R$46,$J$10,$P$20:$P$46,$A$11) -> 0 | K11: =SUMIFS($V$20:$V$46,$R$20:$R$46,$K$10,$P$20:$P$46,$A$11) -> 0 | L11: =SUMIFS($V$20:$V$46,$R$20:$R$46,$L$10,$P$20:$P$46,$A$11) -> 0 | M11: =SUM(H11:L11) -> 0 | N11: =SUMIFS($O$20:$O$45,$N$20:$N$45,N10,$L$20:$L$45,A11) -> 0 | O11: =SUMIFS($O$20:$O$45,$N$20:$N$45,O10,$L$20:$L$45,A11) -> 0 | P11: =SUMIFS($O$20:$O$45,$N$20:$N$45,P10,$L$20:$L$45,A11) -> 0 | Q11: =SUMIFS($O$20:$O$45,$N$20:$N$45,Q10,$L$20:$L$45,A11) -> 0 | R11: =SUMIFS($O$20:$O$45,$N$20:$N$45,R10,$L$20:$L$45,A11) -> 0 | S11: =SUM(N11:R11) -> 0 | T11: =SUMIF($Z$20:$Z$46,A11,$AE$20:$AE$46) -> 0 | V11: =F4/1.09 -> 0 | W11: =(F5+F6)/1.09 -> 0
B12: =SUMIFS($E$51:$E$76,$D$51:$D$76,B10,$A$51:$A$76,A12) -> 0 | C12: =SUMIFS($E$51:$E$76,$D$51:$D$76,C10,$A$51:$A$76,A12) -> 0 | D12: =SUMIFS($E$51:$E$76,$D$51:$D$76,D10,$A$51:$A$76,A12) -> 0 | E12: =SUMIFS($E$51:$E$76,$D$51:$D$76,E10,$A$51:$A$76,A12) -> 0 | F12: =SUMIFS($E$51:$E$76,$D$51:$D$76,F10,$A$51:$A$76,A12) -> 0 | G12: =SUM(B12:F12) -> 0 | H12: =SUMIFS($R$51:$R$76,$N$51:$N$76,H10,$L$51:$L$76,A12) -> 0 | I12: =SUMIFS($R$51:$R$76,$N$51:$N$76,I10,$L$51:$L$76,A12) -> 0 | J12: =SUMIFS($R$51:$R$76,$N$51:$N$76,J10,$L$51:$L$76,A12) -> 0 | K12: =SUMIFS($R$51:$R$76,$N$51:$N$76,K10,$L$51:$L$76,A12) -> 0 | L12: =SUMIFS($R$51:$R$76,$N$51:$N$76,L10,$L$51:$L$76,A12) -> 0 | M12: =SUM(H12:L12) -> 0 | N12: =SUMIFS($G$51:$G$76,$D$51:$D$76,N10,$A$51:$A$76,A12) -> 0 | O12: =SUMIFS($G$51:$G$76,$D$51:$D$76,$O$10,$A$51:$A$76,A12) -> 0 | P12: =SUMIFS($G$51:$G$76,$D$51:$D$76,$P$10,$A$51:$A$76,A12) -> 0 | Q12: =SUMIFS($G$51:$G$76,$D$51:$D$76,$Q$10,$A$51:$A$76,A12) -> 0 | R12: =SUMIFS($G$51:$G$76,$D$51:$D$76,$R$10,$A$51:$A$76,A12) -> 0 | S12: =SUM(N12:R12) -> 0 | T12: =SUMIF($V$51:$V$76,A12,$AA$51:$AA$76) -> 0
B13: =SUMIFS($E$51:$E$76,$D$51:$D$76,B10,$A$51:$A$76,A13) -> 0 | C13: =SUMIFS($E$51:$E$76,$D$51:$D$76,C10,$A$51:$A$76,A13) -> 0 | D13: =SUMIFS($E$51:$E$76,$D$51:$D$76,D10,$A$51:$A$76,A13) -> 0 | E13: =SUMIFS($E$51:$E$76,$D$51:$D$76,E10,$A$51:$A$76,A13) -> 0 | F13: =SUMIFS($E$51:$E$76,$D$51:$D$76,F10,$A$51:$A$76,A13) -> 0 | G13: =SUM(B13:F13) -> 0 | H13: =SUMIFS($R$51:$R$76,$N$51:$N$76,H10,$L$51:$L$76,A13) -> 0 | I13: =SUMIFS($R$51:$R$76,$N$51:$N$76,I10,$L$51:$L$76,A13) -> 0 | J13: =SUMIFS($R$51:$R$76,$N$51:$N$76,J10,$L$51:$L$76,A13) -> 0 | K13: =SUMIFS($R$51:$R$76,$N$51:$N$76,K10,$L$51:$L$76,A13) -> 0 | L13: =SUMIFS($R$51:$R$76,$N$51:$N$76,L10,$L$51:$L$76,A13) -> 0 | M13: =SUM(H13:L13) -> 0 | N13: =SUMIFS($G$51:$G$76,$D$51:$D$76,$N$10,$A$51:$A$76,A13) -> 0 | O13: =SUMIFS($G$51:$G$76,$D$51:$D$76,$O$10,$A$51:$A$76,A13) -> 0 | P13: =SUMIFS($G$51:$G$76,$D$51:$D$76,$P$10,$A$51:$A$76,A13) -> 0 | Q13: =SUMIFS($G$51:$G$76,$D$51:$D$76,$Q$10,$A$51:$A$76,A13) -> 0 | R13: =SUMIFS($G$51:$G$76,$D$51:$D$76,$R$10,$A$51:$A$76,A13) -> 0 | S13: =SUM(N13:R13) -> 0 | T13: =SUMIF($V$51:$V$76,A13,$AA$51:$AA$76) -> 0
G14: =G11-C17 -> 0 | M14: =M11-V17 -> 0 | S14: =S11-O17 -> 0 | T14: =T11-AE17 -> 0
G15: =G12+G13-C48 -> 0 | M15: =M12+M13-R48 -> 0 | S15: =S12+S13-G48 -> 0 | T15: =T12+T13-AA48 -> 0
A17: 表三：业主基础明细表 | C17: =SUM(C20:C45) -> 0 | E17: =SUM(E20:E45) -> 0 | G17: =SUM(G20:G45) -> 0 | H17: =SUM(H20:H45) -> 0 | O17: =SUM(O20:O45) -> 0 | V17: =SUM(V20:V45) -> 0 | W17: =SUM(W20:W45) -> 0 | X17: =SUM(X20:X45) -> 0 | AE17: =SUM(AE20:AE45) -> 0
A18: 业主结算明细 | L18: 收入确认表 | P18: 开票明细表（可按开票时间汇总登记） | Z18: 收款明细
A19: 业主名称 | B19: 验工时间 | C19: 验工计价 | D19: 结算内容 | E19: 列账金额 | F19: 税率 | G19: 不含税金额(注意与账上保持一致） | H19: 税额(注意与账上保持一致） | I19: 列账凭证时间 | J19: 预付款转回 | K19: 罚没等其他金额 | L19: 业主名称 | M19: 凭证时间 | N19: 收入类型 | O19: 确认金额 | P19: 业主名称 | Q19: 凭证时间 | R19: 开票内容 | S19: 开票时间 | T19: 发票号码 | U19: 发票代码 | V19: 发票金额 | W19: 不含税金额 | X19: 税额 | Y19: 税率 | Z19: 单位名称 | AA19: 凭证日期 | AB19: 收款账户类型 | AC19: 收款账户名称 | AD19: 收款账户银行账号 | AE19: 收款金额 | AF19: 收款性质 | AG19: 收款备注
A48: 表四：分包方基础明细表 | C48: =SUM(C51:C75) -> 0 | E48: =SUM(E51:E75) -> 0 | G48: =SUM(G51:G75) -> 0 | H48: =SUM(H51:H75) -> 0 | J48: =SUM(J51:J75) -> 0 | K48: =SUM(K51:K75) -> 0 | R48: =SUM(R51:R75) -> 0 | S48: =SUM(S51:S75) -> 0 | T48: =SUM(T51:T75) -> 0 | AA48: =SUM(AA51:AA75) -> 0
A49: 分包（采购）结算明细表 | L49: 分包（采购）发票明细表开票明细表（可按开票时间汇总登记） | V49: 分包（采购）付款明细表
A50: 单位名称 | B50: 验工时间 | C50: 验工计价 | D50: 结算内容 | E50: 金额 | F50: 税率 | G50: 不含税金额(注意与账上保持一致） | H50: 税额(注意与账上保持一致） | I50: 列账凭证时间 | J50: 预付款转回 | K50: 罚没等其他金额 | L50: 单位名称 | M50: 凭证时间 | N50: 开票内容 | O50: 开票时间 | P50: 发票号码 | Q50: 发票代码 | R50: 发票金额 | S50: 不含税金额 | T50: 税额 | U50: 税率 | V50: 单位名称 | W50: 凭证日期 | X50: 付款账户类型 | Y50: 付款账户名称 | Z50: 付款账户银行账号 | AA50: 付款金额 | AB50: 付款性质 | AC50: 付款备注
A78: 表五：预缴税款情况统计表
A79: 凭证号/时间 | B79: 销售额 | C79: 扣除金额 | D79: 增值税 | E79: 城市维护建设税 | F79: 教育费附加 | G79: 地方教育费附加 | H79: 印花税 | I79: 企业所得税 | J79: 个人所得税 | K79: 其他税金 | L79: 合计 | M79: 备注
L80: =SUM(D80:K80) -> 0
L81: =SUM(D81:K81) -> 0
L82: =SUM(D82:K82) -> 0
L83: =SUM(D83:K83) -> 0
L84: =SUM(D84:K84) -> 0
L85: =SUM(D85:K85) -> 0
L86: =SUM(D86:K86) -> 0
L87: =SUM(D87:K87) -> 0
L88: =SUM(D88:K88) -> 0
L89: =SUM(D89:K89) -> 0
L90: =SUM(D90:K90) -> 0
L91: =SUM(D91:K91) -> 0
L92: =SUM(D92:K92) -> 0
A93: 合计 | B93: =SUM(B80:B92) -> 0 | C93: =SUM(C80:C92) -> 0 | D93: =SUM(D80:D92) -> 0 | E93: =SUM(E80:E92) -> 0 | F93: =SUM(F80:F92) -> 0 | G93: =SUM(G80:G92) -> 0 | H93: =SUM(H80:H92) -> 0 | I93: =SUM(I80:I92) -> 0 | ... M93: =SUM(M80:M92) -> 0
A95: 表六：间接费用、财务费用、附加费明细表
A96: 费用类型 | B96: 以前年度累计 | C96: 2023年 | D96: 2024年 | E96: 2025年 | F96: 2026年 | G96: 2027年 | H96: 2028年 | I96: 合计
A97: 间接费用 | I97: =SUM(B97:H97) -> 0
A98: 财务费用 | I98: =SUM(B98:H98) -> 0
A99: 其中：利息收入 | I99: =SUM(B99:H99) -> 0
A100: 手续费支出 | I100: =SUM(B100:H100) -> 0
A101: 营业外收入 | I101: =SUM(B101:H101) -> 0
A102: 营业外支出 | I102: =SUM(B102:H102) -> 0
A105: 表七：往来类科目明细表
A106: 项目名称 | B106: 应收账款 | C106: 合同负债 | D106: 长期应收款 | E106: 其他应收款 | F106: 应付账款 | G106: 预付账款 | H106: 长期应付款 | I106: 其他应付款 | J106: 待转销项税额 | K106: 专业分包成本 | L106: 直接材料费 | M106: 合同结算-收入结转 | N106: 合同结算-价款结算 | O106: 工程施工结转 | P106: 合同负债增值税 | Q106: 应付账款-预付账款增值税
A107: =M4 -> 来源于“共享系统”系统管理-权限管理-人员管理
A110: 表八：施工收入、成本计算表
A111: 2024年合同工程施工收入、成本计算表
A113: =L4 -> 来源于“共享系统”系统管理-权限管理-人员管理 | H113: 金额：元
A114: 序号 | B114: 名称 | C114: 期初数 | D114: 1季度 | E114: 2季度 | F114: 3季度 | G114: 4季度 | H114: 开累数
A115: 1 | B115: 工程施工预计总收入 | H115: =V11 -> 0
A116: 2 | B116: 工程施工预计总成本 | H116: =W11 -> 0
A117: 3 | B117: 工程施工预计合同毛利 | H117: =H115-H116 -> 0
A118: 4 | B118: 工程施工确认营业成本 | D118: 0 | H118: =C118+D118+E118+F118+G118 -> 0
A119: 5 | B119: 工程施工确认营业收入 | D119: 0 | H119: =C119+D119+E119+F119+G119 -> 0
A120: 6 | B120: 完工百分比 | C120: =ROUND(C118/H116,10) -> #DIV/0! | D120: =ROUND((C118+D118)/H116,10) -> #DIV/0! | E120: =ROUND((C118+D118+E118)/H116,10) -> #DIV/0! | F120: =ROUND((C118+D118+E118+F118)/H116,10) -> #DIV/0! | G120: =ROUND((C118+D118+E118+F118+G118)/H116,10) -> #DIV/0!
A121: 7 | B121: 确认营业毛利 | C121: =C119-C118 -> 0 | D121: =D119-D118 -> 0 | E121: =E119-E118 -> 0 | F121: =F119-F118 -> 0 | G121: =G119-G118 -> 0
A122: 8 | B122: 累计营业毛利 | C122: =C119-C118 -> 0 | D122: =C121+D121 -> 0 | E122: =C121+D121+E121 -> 0 | F122: =C121+D121+E121+F121 -> 0 | G122: =C121+D121+E121+F121+G121 -> 0
B124: 制表人： | G124: 项目部签字：
A126: 表九：数据校验
A127: 业主往来检验 | B127: 业主发票检验 | C127: 业主收入检验 | D127: 分包往来检验 | E127: 分包验工计价校验 | F127: 预缴税金检验 | G127: 两金指标
A128: =G11-T11-B107+C107-D107-E107-P107 -> 0 | B128: =H17-X17-J107+P107 -> 0 | C128: =SUMIFS($G$51:$G$76,$D$51:$D$76,C10)/H116*H115-O11 -> #DIV/0! | D128: =G12+G13-T12-T13-F107+G107-H107-I107+Q107 -> 0 | E128: =C11*(1-K4)-C12-C13 -> #DIV/0! | F128: =(SUMIFS($V$20:$V$46,$R$20:$R$46,C10)-SUMIFS($R$51:$R$76,$N$51:$N$76,C10))/1.09*0.02-D93 -> 0 | G128: =B107-C107+M107-N107 -> 0
A129: 应为零 | B129: 应为零 | C129: 应为零 | D129: 应为零 | E129: 应为零（正数为未验完，负数为超验） | F129: 应为零 | G129: 应尽量小，超过1000万预警

Sheet XX项目 (7)
A1: 表一：基础信息表
A2: 单位名称 | B2: 合同名称 | C2: 合同编号 | D2: 合同类型 | E2: 合同金额 | K2: 管理费比例 | L2: 共享系统部门名称 | M2: 共享系统项目名称 | N2: 合同签订单位 | O2: 项目管理单位 | P2: 业主财务联系人及电话 | Q2: 分包方财务联系人及电话 | R2: 项目部经理及电话 | S2: 合同开工日期 | T2: 预计竣工时间 | U2: 合同工期 | V2: 工程类型 | W2: 项目所在地（*省*市） | X2: 项目状态 | Y2: 工程进度款支付比例 | Z2: 勘察设计费支付比例 | AA2: 主管税务机构名称 | AB2: 税务管理员及电话 | AC2: 银行行号 | AD2: 开户行 | AE2: 银行行号 | AF2: 银行账户名称 | AG2: 银行账号 | AH2: 银行地址 | AI2: 银行联系人 | AJ2: 备注
E3: 勘察设计 | F3: 工程施工 | G3: 设备采购 | H3: 业主承担管理费 | I3: 技术服务等 | J3: 合计
A4: 来源于“共享系统”列账单位名称 | B4: 来源于“合同收款系统”或共享系统项目档案 | C4: 来源于“合同收款系统” | D4: 总包合同 | J4: =SUM(E4:I4) -> 0 | K4: =(F4-F5-F6)/F4 -> #DIV/0! | L4: 来源于“共享系统”系统管理-权限管理-人员管理 | M4: 来源于“共享系统”系统管理-权限管理-人员管理 | N4: 主合同编号中的单位 | O4: 实际管理单位
A5: 来源于“共享系统”列账单位名称 | B5: 来源于“合同收款系统”或共享系统项目档案 | C5: 来源于“合同收款系统” | D5: 分包合同 | J5: =SUM(E5:I5) -> 0
D6: 分包合同 | J6: =SUM(E6:I6) -> 0
A8: 表二：汇总表
A9: 单位名称 | B9: 累计验工计价 | H9: 累计开票 | N9: 累计收入或成本 | T9: 累计收款/付款 | U9: 银行账户余额 | V9: 工程施工预计总收入 | W9: 工程施工预计总成本
B10: 勘察设计 | C10: 工程施工 | D10: 设备采购 | E10: 业主承担管理费 | F10: 服务费 | G10: 合计 | H10: 勘察设计 | I10: 工程施工 | J10: 设备采购 | K10: 业主承担管理费 | L10: 服务费 | M10: 合计 | N10: 勘察设计 | O10: 工程施工 | P10: 设备采购 | Q10: 业主承担管理费 | R10: 服务费 | S10: 合计
B11: =SUMIFS($E$20:$E$46,$D$20:$D$46,$B$10,$A$20:$A$46,$A$11) -> 0 | C11: =SUMIFS($E$20:$E$46,$D$20:$D$46,C10,$A$20:$A$46,A11) -> 0 | D11: =SUMIFS($E$20:$E$46,$D$20:$D$46,D10,$A$20:$A$46,A11) -> 0 | E11: =SUMIFS($E$20:$E$46,$D$20:$D$46,E10,$A$20:$A$46,A11) -> 0 | F11: =SUMIFS($E$20:$E$46,$D$20:$D$46,F10,$A$20:$A$46,A11) -> 0 | G11: =SUM(B11:F11) -> 0 | H11: =SUMIFS($V$20:$V$46,$R$20:$R$46,$H$10,$P$20:$P$46,$A$11) -> 0 | I11: =SUMIFS($V$20:$V$46,$R$20:$R$46,I10,$P$20:$P$46,$A$11) -> 0 | J11: =SUMIFS($V$20:$V$46,$R$20:$R$46,$J$10,$P$20:$P$46,$A$11) -> 0 | K11: =SUMIFS($V$20:$V$46,$R$20:$R$46,$K$10,$P$20:$P$46,$A$11) -> 0 | L11: =SUMIFS($V$20:$V$46,$R$20:$R$46,$L$10,$P$20:$P$46,$A$11) -> 0 | M11: =SUM(H11:L11) -> 0 | N11: =SUMIFS($O$20:$O$45,$N$20:$N$45,N10,$L$20:$L$45,A11) -> 0 | O11: =SUMIFS($O$20:$O$45,$N$20:$N$45,O10,$L$20:$L$45,A11) -> 0 | P11: =SUMIFS($O$20:$O$45,$N$20:$N$45,P10,$L$20:$L$45,A11) -> 0 | Q11: =SUMIFS($O$20:$O$45,$N$20:$N$45,Q10,$L$20:$L$45,A11) -> 0 | R11: =SUMIFS($O$20:$O$45,$N$20:$N$45,R10,$L$20:$L$45,A11) -> 0 | S11: =SUM(N11:R11) -> 0 | T11: =SUMIF($Z$20:$Z$46,A11,$AE$20:$AE$46) -> 0 | V11: =F4/1.09 -> 0 | W11: =(F5+F6)/1.09 -> 0
B12: =SUMIFS($E$51:$E$76,$D$51:$D$76,B10,$A$51:$A$76,A12) -> 0 | C12: =SUMIFS($E$51:$E$76,$D$51:$D$76,C10,$A$51:$A$76,A12) -> 0 | D12: =SUMIFS($E$51:$E$76,$D$51:$D$76,D10,$A$51:$A$76,A12) -> 0 | E12: =SUMIFS($E$51:$E$76,$D$51:$D$76,E10,$A$51:$A$76,A12) -> 0 | F12: =SUMIFS($E$51:$E$76,$D$51:$D$76,F10,$A$51:$A$76,A12) -> 0 | G12: =SUM(B12:F12) -> 0 | H12: =SUMIFS($R$51:$R$76,$N$51:$N$76,H10,$L$51:$L$76,A12) -> 0 | I12: =SUMIFS($R$51:$R$76,$N$51:$N$76,I10,$L$51:$L$76,A12) -> 0 | J12: =SUMIFS($R$51:$R$76,$N$51:$N$76,J10,$L$51:$L$76,A12) -> 0 | K12: =SUMIFS($R$51:$R$76,$N$51:$N$76,K10,$L$51:$L$76,A12) -> 0 | L12: =SUMIFS($R$51:$R$76,$N$51:$N$76,L10,$L$51:$L$76,A12) -> 0 | M12: =SUM(H12:L12) -> 0 | N12: =SUMIFS($G$51:$G$76,$D$51:$D$76,N10,$A$51:$A$76,A12) -> 0 | O12: =SUMIFS($G$51:$G$76,$D$51:$D$76,$O$10,$A$51:$A$76,A12) -> 0 | P12: =SUMIFS($G$51:$G$76,$D$51:$D$76,$P$10,$A$51:$A$76,A12) -> 0 | Q12: =SUMIFS($G$51:$G$76,$D$51:$D$76,$Q$10,$A$51:$A$76,A12) -> 0 | R12: =SUMIFS($G$51:$G$76,$D$51:$D$76,$R$10,$A$51:$A$76,A12) -> 0 | S12: =SUM(N12:R12) -> 0 | T12: =SUMIF($V$51:$V$76,A12,$AA$51:$AA$76) -> 0
B13: =SUMIFS($E$51:$E$76,$D$51:$D$76,B10,$A$51:$A$76,A13) -> 0 | C13: =SUMIFS($E$51:$E$76,$D$51:$D$76,C10,$A$51:$A$76,A13) -> 0 | D13: =SUMIFS($E$51:$E$76,$D$51:$D$76,D10,$A$51:$A$76,A13) -> 0 | E13: =SUMIFS($E$51:$E$76,$D$51:$D$76,E10,$A$51:$A$76,A13) -> 0 | F13: =SUMIFS($E$51:$E$76,$D$51:$D$76,F10,$A$51:$A$76,A13) -> 0 | G13: =SUM(B13:F13) -> 0 | H13: =SUMIFS($R$51:$R$76,$N$51:$N$76,H10,$L$51:$L$76,A13) -> 0 | I13: =SUMIFS($R$51:$R$76,$N$51:$N$76,I10,$L$51:$L$76,A13) -> 0 | J13: =SUMIFS($R$51:$R$76,$N$51:$N$76,J10,$L$51:$L$76,A13) -> 0 | K13: =SUMIFS($R$51:$R$76,$N$51:$N$76,K10,$L$51:$L$76,A13) -> 0 | L13: =SUMIFS($R$51:$R$76,$N$51:$N$76,L10,$L$51:$L$76,A13) -> 0 | M13: =SUM(H13:L13) -> 0 | N13: =SUMIFS($G$51:$G$76,$D$51:$D$76,$N$10,$A$51:$A$76,A13) -> 0 | O13: =SUMIFS($G$51:$G$76,$D$51:$D$76,$O$10,$A$51:$A$76,A13) -> 0 | P13: =SUMIFS($G$51:$G$76,$D$51:$D$76,$P$10,$A$51:$A$76,A13) -> 0 | Q13: =SUMIFS($G$51:$G$76,$D$51:$D$76,$Q$10,$A$51:$A$76,A13) -> 0 | R13: =SUMIFS($G$51:$G$76,$D$51:$D$76,$R$10,$A$51:$A$76,A13) -> 0 | S13: =SUM(N13:R13) -> 0 | T13: =SUMIF($V$51:$V$76,A13,$AA$51:$AA$76) -> 0
G14: =G11-C17 -> 0 | M14: =M11-V17 -> 0 | S14: =S11-O17 -> 0 | T14: =T11-AE17 -> 0
G15: =G12+G13-C48 -> 0 | M15: =M12+M13-R48 -> 0 | S15: =S12+S13-G48 -> 0 | T15: =T12+T13-AA48 -> 0
A17: 表三：业主基础明细表 | C17: =SUM(C20:C45) -> 0 | E17: =SUM(E20:E45) -> 0 | G17: =SUM(G20:G45) -> 0 | H17: =SUM(H20:H45) -> 0 | O17: =SUM(O20:O45) -> 0 | V17: =SUM(V20:V45) -> 0 | W17: =SUM(W20:W45) -> 0 | X17: =SUM(X20:X45) -> 0 | AE17: =SUM(AE20:AE45) -> 0
A18: 业主结算明细 | L18: 收入确认表 | P18: 开票明细表（可按开票时间汇总登记） | Z18: 收款明细
A19: 业主名称 | B19: 验工时间 | C19: 验工计价 | D19: 结算内容 | E19: 列账金额 | F19: 税率 | G19: 不含税金额(注意与账上保持一致） | H19: 税额(注意与账上保持一致） | I19: 列账凭证时间 | J19: 预付款转回 | K19: 罚没等其他金额 | L19: 业主名称 | M19: 凭证时间 | N19: 收入类型 | O19: 确认金额 | P19: 业主名称 | Q19: 凭证时间 | R19: 开票内容 | S19: 开票时间 | T19: 发票号码 | U19: 发票代码 | V19: 发票金额 | W19: 不含税金额 | X19: 税额 | Y19: 税率 | Z19: 单位名称 | AA19: 凭证日期 | AB19: 收款账户类型 | AC19: 收款账户名称 | AD19: 收款账户银行账号 | AE19: 收款金额 | AF19: 收款性质 | AG19: 收款备注
A48: 表四：分包方基础明细表 | C48: =SUM(C51:C75) -> 0 | E48: =SUM(E51:E75) -> 0 | G48: =SUM(G51:G75) -> 0 | H48: =SUM(H51:H75) -> 0 | J48: =SUM(J51:J75) -> 0 | K48: =SUM(K51:K75) -> 0 | R48: =SUM(R51:R75) -> 0 | S48: =SUM(S51:S75) -> 0 | T48: =SUM(T51:T75) -> 0 | AA48: =SUM(AA51:AA75) -> 0
A49: 分包（采购）结算明细表 | L49: 分包（采购）发票明细表开票明细表（可按开票时间汇总登记） | V49: 分包（采购）付款明细表
A50: 单位名称 | B50: 验工时间 | C50: 验工计价 | D50: 结算内容 | E50: 金额 | F50: 税率 | G50: 不含税金额(注意与账上保持一致） | H50: 税额(注意与账上保持一致） | I50: 列账凭证时间 | J50: 预付款转回 | K50: 罚没等其他金额 | L50: 单位名称 | M50: 凭证时间 | N50: 开票内容 | O50: 开票时间 | P50: 发票号码 | Q50: 发票代码 | R50: 发票金额 | S50: 不含税金额 | T50: 税额 | U50: 税率 | V50: 单位名称 | W50: 凭证日期 | X50: 付款账户类型 | Y50: 付款账户名称 | Z50: 付款账户银行账号 | AA50: 付款金额 | AB50: 付款性质 | AC50: 付款备注
A78: 表五：预缴税款情况统计表
A79: 凭证号/时间 | B79: 销售额 | C79: 扣除金额 | D79: 增值税 | E79: 城市维护建设税 | F79: 教育费附加 | G79: 地方教育费附加 | H79: 印花税 | I79: 企业所得税 | J79: 个人所得税 | K79: 其他税金 | L79: 合计 | M79: 备注
L80: =SUM(D80:K80) -> 0
L81: =SUM(D81:K81) -> 0
L82: =SUM(D82:K82) -> 0
L83: =SUM(D83:K83) -> 0
L84: =SUM(D84:K84) -> 0
L85: =SUM(D85:K85) -> 0
L86: =SUM(D86:K86) -> 0
L87: =SUM(D87:K87) -> 0
L88: =SUM(D88:K88) -> 0
L89: =SUM(D89:K89) -> 0
L90: =SUM(D90:K90) -> 0
L91: =SUM(D91:K91) -> 0
L92: =SUM(D92:K92) -> 0
A93: 合计 | B93: =SUM(B80:B92) -> 0 | C93: =SUM(C80:C92) -> 0 | D93: =SUM(D80:D92) -> 0 | E93: =SUM(E80:E92) -> 0 | F93: =SUM(F80:F92) -> 0 | G93: =SUM(G80:G92) -> 0 | H93: =SUM(H80:H92) -> 0 | I93: =SUM(I80:I92) -> 0 | ... M93: =SUM(M80:M92) -> 0
A95: 表六：间接费用、财务费用、附加费明细表
A96: 费用类型 | B96: 以前年度累计 | C96: 2023年 | D96: 2024年 | E96: 2025年 | F96: 2026年 | G96: 2027年 | H96: 2028年 | I96: 合计
A97: 间接费用 | I97: =SUM(B97:H97) -> 0
A98: 财务费用 | I98: =SUM(B98:H98) -> 0
A99: 其中：利息收入 | I99: =SUM(B99:H99) -> 0
A100: 手续费支出 | I100: =SUM(B100:H100) -> 0
A101: 营业外收入 | I101: =SUM(B101:H101) -> 0
A102: 营业外支出 | I102: =SUM(B102:H102) -> 0
A105: 表七：往来类科目明细表
A106: 项目名称 | B106: 应收账款 | C106: 合同负债 | D106: 长期应收款 | E106: 其他应收款 | F106: 应付账款 | G106: 预付账款 | H106: 长期应付款 | I106: 其他应付款 | J106: 待转销项税额 | K106: 专业分包成本 | L106: 直接材料费 | M106: 合同结算-收入结转 | N106: 合同结算-价款结算 | O106: 工程施工结转 | P106: 合同负债增值税 | Q106: 应付账款-预付账款增值税
A107: =M4 -> 来源于“共享系统”系统管理-权限管理-人员管理
A110: 表八：施工收入、成本计算表
A111: 2024年合同工程施工收入、成本计算表
A113: =L4 -> 来源于“共享系统”系统管理-权限管理-人员管理 | H113: 金额：元
A114: 序号 | B114: 名称 | C114: 期初数 | D114: 1季度 | E114: 2季度 | F114: 3季度 | G114: 4季度 | H114: 开累数
A115: 1 | B115: 工程施工预计总收入 | H115: =V11 -> 0
A116: 2 | B116: 工程施工预计总成本 | H116: =W11 -> 0
A117: 3 | B117: 工程施工预计合同毛利 | H117: =H115-H116 -> 0
A118: 4 | B118: 工程施工确认营业成本 | D118: 0 | H118: =C118+D118+E118+F118+G118 -> 0
A119: 5 | B119: 工程施工确认营业收入 | D119: 0 | H119: =C119+D119+E119+F119+G119 -> 0
A120: 6 | B120: 完工百分比 | C120: =ROUND(C118/H116,10) -> #DIV/0! | D120: =ROUND((C118+D118)/H116,10) -> #DIV/0! | E120: =ROUND((C118+D118+E118)/H116,10) -> #DIV/0! | F120: =ROUND((C118+D118+E118+F118)/H116,10) -> #DIV/0! | G120: =ROUND((C118+D118+E118+F118+G118)/H116,10) -> #DIV/0!
A121: 7 | B121: 确认营业毛利 | C121: =C119-C118 -> 0 | D121: =D119-D118 -> 0 | E121: =E119-E118 -> 0 | F121: =F119-F118 -> 0 | G121: =G119-G118 -> 0
A122: 8 | B122: 累计营业毛利 | C122: =C119-C118 -> 0 | D122: =C121+D121 -> 0 | E122: =C121+D121+E121 -> 0 | F122: =C121+D121+E121+F121 -> 0 | G122: =C121+D121+E121+F121+G121 -> 0
B124: 制表人： | G124: 项目部签字：
A126: 表九：数据校验
A127: 业主往来检验 | B127: 业主发票检验 | C127: 业主收入检验 | D127: 分包往来检验 | E127: 分包验工计价校验 | F127: 预缴税金检验 | G127: 两金指标
A128: =G11-T11-B107+C107-D107-E107-P107 -> 0 | B128: =H17-X17-J107+P107 -> 0 | C128: =SUMIFS($G$51:$G$76,$D$51:$D$76,C10)/H116*H115-O11 -> #DIV/0! | D128: =G12+G13-T12-T13-F107+G107-H107-I107+Q107 -> 0 | E128: =C11*(1-K4)-C12-C13 -> #DIV/0! | F128: =(SUMIFS($V$20:$V$46,$R$20:$R$46,C10)-SUMIFS($R$51:$R$76,$N$51:$N$76,C10))/1.09*0.02-D93 -> 0 | G128: =B107-C107+M107-N107 -> 0
A129: 应为零 | B129: 应为零 | C129: 应为零 | D129: 应为零 | E129: 应为零（正数为未验完，负数为超验） | F129: 应为零 | G129: 应尽量小，超过1000万预警

Sheet XX项目 (8)
A1: 表一：基础信息表
A2: 单位名称 | B2: 合同名称 | C2: 合同编号 | D2: 合同类型 | E2: 合同金额 | K2: 管理费比例 | L2: 共享系统部门名称 | M2: 共享系统项目名称 | N2: 合同签订单位 | O2: 项目管理单位 | P2: 业主财务联系人及电话 | Q2: 分包方财务联系人及电话 | R2: 项目部经理及电话 | S2: 合同开工日期 | T2: 预计竣工时间 | U2: 合同工期 | V2: 工程类型 | W2: 项目所在地（*省*市） | X2: 项目状态 | Y2: 工程进度款支付比例 | Z2: 勘察设计费支付比例 | AA2: 主管税务机构名称 | AB2: 税务管理员及电话 | AC2: 银行行号 | AD2: 开户行 | AE2: 银行行号 | AF2: 银行账户名称 | AG2: 银行账号 | AH2: 银行地址 | AI2: 银行联系人 | AJ2: 备注
E3: 勘察设计 | F3: 工程施工 | G3: 设备采购 | H3: 业主承担管理费 | I3: 技术服务等 | J3: 合计
A4: 来源于“共享系统”列账单位名称 | B4: 来源于“合同收款系统”或共享系统项目档案 | C4: 来源于“合同收款系统” | D4: 总包合同 | J4: =SUM(E4:I4) -> 0 | K4: =(F4-F5-F6)/F4 -> #DIV/0! | L4: 来源于“共享系统”系统管理-权限管理-人员管理 | M4: 来源于“共享系统”系统管理-权限管理-人员管理 | N4: 主合同编号中的单位 | O4: 实际管理单位
A5: 来源于“共享系统”列账单位名称 | B5: 来源于“合同收款系统”或共享系统项目档案 | C5: 来源于“合同收款系统” | D5: 分包合同 | J5: =SUM(E5:I5) -> 0
D6: 分包合同 | J6: =SUM(E6:I6) -> 0
A8: 表二：汇总表
A9: 单位名称 | B9: 累计验工计价 | H9: 累计开票 | N9: 累计收入或成本 | T9: 累计收款/付款 | U9: 银行账户余额 | V9: 工程施工预计总收入 | W9: 工程施工预计总成本
B10: 勘察设计 | C10: 工程施工 | D10: 设备采购 | E10: 业主承担管理费 | F10: 服务费 | G10: 合计 | H10: 勘察设计 | I10: 工程施工 | J10: 设备采购 | K10: 业主承担管理费 | L10: 服务费 | M10: 合计 | N10: 勘察设计 | O10: 工程施工 | P10: 设备采购 | Q10: 业主承担管理费 | R10: 服务费 | S10: 合计
B11: =SUMIFS($E$20:$E$46,$D$20:$D$46,$B$10,$A$20:$A$46,$A$11) -> 0 | C11: =SUMIFS($E$20:$E$46,$D$20:$D$46,C10,$A$20:$A$46,A11) -> 0 | D11: =SUMIFS($E$20:$E$46,$D$20:$D$46,D10,$A$20:$A$46,A11) -> 0 | E11: =SUMIFS($E$20:$E$46,$D$20:$D$46,E10,$A$20:$A$46,A11) -> 0 | F11: =SUMIFS($E$20:$E$46,$D$20:$D$46,F10,$A$20:$A$46,A11) -> 0 | G11: =SUM(B11:F11) -> 0 | H11: =SUMIFS($V$20:$V$46,$R$20:$R$46,$H$10,$P$20:$P$46,$A$11) -> 0 | I11: =SUMIFS($V$20:$V$46,$R$20:$R$46,I10,$P$20:$P$46,$A$11) -> 0 | J11: =SUMIFS($V$20:$V$46,$R$20:$R$46,$J$10,$P$20:$P$46,$A$11) -> 0 | K11: =SUMIFS($V$20:$V$46,$R$20:$R$46,$K$10,$P$20:$P$46,$A$11) -> 0 | L11: =SUMIFS($V$20:$V$46,$R$20:$R$46,$L$10,$P$20:$P$46,$A$11) -> 0 | M11: =SUM(H11:L11) -> 0 | N11: =SUMIFS($O$20:$O$45,$N$20:$N$45,N10,$L$20:$L$45,A11) -> 0 | O11: =SUMIFS($O$20:$O$45,$N$20:$N$45,O10,$L$20:$L$45,A11) -> 0 | P11: =SUMIFS($O$20:$O$45,$N$20:$N$45,P10,$L$20:$L$45,A11) -> 0 | Q11: =SUMIFS($O$20:$O$45,$N$20:$N$45,Q10,$L$20:$L$45,A11) -> 0 | R11: =SUMIFS($O$20:$O$45,$N$20:$N$45,R10,$L$20:$L$45,A11) -> 0 | S11: =SUM(N11:R11) -> 0 | T11: =SUMIF($Z$20:$Z$46,A11,$AE$20:$AE$46) -> 0 | V11: =F4/1.09 -> 0 | W11: =(F5+F6)/1.09 -> 0
B12: =SUMIFS($E$51:$E$76,$D$51:$D$76,B10,$A$51:$A$76,A12) -> 0 | C12: =SUMIFS($E$51:$E$76,$D$51:$D$76,C10,$A$51:$A$76,A12) -> 0 | D12: =SUMIFS($E$51:$E$76,$D$51:$D$76,D10,$A$51:$A$76,A12) -> 0 | E12: =SUMIFS($E$51:$E$76,$D$51:$D$76,E10,$A$51:$A$76,A12) -> 0 | F12: =SUMIFS($E$51:$E$76,$D$51:$D$76,F10,$A$51:$A$76,A12) -> 0 | G12: =SUM(B12:F12) -> 0 | H12: =SUMIFS($R$51:$R$76,$N$51:$N$76,H10,$L$51:$L$76,A12) -> 0 | I12: =SUMIFS($R$51:$R$76,$N$51:$N$76,I10,$L$51:$L$76,A12) -> 0 | J12: =SUMIFS($R$51:$R$76,$N$51:$N$76,J10,$L$51:$L$76,A12) -> 0 | K12: =SUMIFS($R$51:$R$76,$N$51:$N$76,K10,$L$51:$L$76,A12) -> 0 | L12: =SUMIFS($R$51:$R$76,$N$51:$N$76,L10,$L$51:$L$76,A12) -> 0 | M12: =SUM(H12:L12) -> 0 | N12: =SUMIFS($G$51:$G$76,$D$51:$D$76,N10,$A$51:$A$76,A12) -> 0 | O12: =SUMIFS($G$51:$G$76,$D$51:$D$76,$O$10,$A$51:$A$76,A12) -> 0 | P12: =SUMIFS($G$51:$G$76,$D$51:$D$76,$P$10,$A$51:$A$76,A12) -> 0 | Q12: =SUMIFS($G$51:$G$76,$D$51:$D$76,$Q$10,$A$51:$A$76,A12) -> 0 | R12: =SUMIFS($G$51:$G$76,$D$51:$D$76,$R$10,$A$51:$A$76,A12) -> 0 | S12: =SUM(N12:R12) -> 0 | T12: =SUMIF($V$51:$V$76,A12,$AA$51:$AA$76) -> 0
B13: =SUMIFS($E$51:$E$76,$D$51:$D$76,B10,$A$51:$A$76,A13) -> 0 | C13: =SUMIFS($E$51:$E$76,$D$51:$D$76,C10,$A$51:$A$76,A13) -> 0 | D13: =SUMIFS($E$51:$E$76,$D$51:$D$76,D10,$A$51:$A$76,A13) -> 0 | E13: =SUMIFS($E$51:$E$76,$D$51:$D$76,E10,$A$51:$A$76,A13) -> 0 | F13: =SUMIFS($E$51:$E$76,$D$51:$D$76,F10,$A$51:$A$76,A13) -> 0 | G13: =SUM(B13:F13) -> 0 | H13: =SUMIFS($R$51:$R$76,$N$51:$N$76,H10,$L$51:$L$76,A13) -> 0 | I13: =SUMIFS($R$51:$R$76,$N$51:$N$76,I10,$L$51:$L$76,A13) -> 0 | J13: =SUMIFS($R$51:$R$76,$N$51:$N$76,J10,$L$51:$L$76,A13) -> 0 | K13: =SUMIFS($R$51:$R$76,$N$51:$N$76,K10,$L$51:$L$76,A13) -> 0 | L13: =SUMIFS($R$51:$R$76,$N$51:$N$76,L10,$L$51:$L$76,A13) -> 0 | M13: =SUM(H13:L13) -> 0 | N13: =SUMIFS($G$51:$G$76,$D$51:$D$76,$N$10,$A$51:$A$76,A13) -> 0 | O13: =SUMIFS($G$51:$G$76,$D$51:$D$76,$O$10,$A$51:$A$76,A13) -> 0 | P13: =SUMIFS($G$51:$G$76,$D$51:$D$76,$P$10,$A$51:$A$76,A13) -> 0 | Q13: =SUMIFS($G$51:$G$76,$D$51:$D$76,$Q$10,$A$51:$A$76,A13) -> 0 | R13: =SUMIFS($G$51:$G$76,$D$51:$D$76,$R$10,$A$51:$A$76,A13) -> 0 | S13: =SUM(N13:R13) -> 0 | T13: =SUMIF($V$51:$V$76,A13,$AA$51:$AA$76) -> 0
G14: =G11-C17 -> 0 | M14: =M11-V17 -> 0 | S14: =S11-O17 -> 0 | T14: =T11-AE17 -> 0
G15: =G12+G13-C48 -> 0 | M15: =M12+M13-R48 -> 0 | S15: =S12+S13-G48 -> 0 | T15: =T12+T13-AA48 -> 0
A17: 表三：业主基础明细表 | C17: =SUM(C20:C45) -> 0 | E17: =SUM(E20:E45) -> 0 | G17: =SUM(G20:G45) -> 0 | H17: =SUM(H20:H45) -> 0 | O17: =SUM(O20:O45) -> 0 | V17: =SUM(V20:V45) -> 0 | W17: =SUM(W20:W45) -> 0 | X17: =SUM(X20:X45) -> 0 | AE17: =SUM(AE20:AE45) -> 0
A18: 业主结算明细 | L18: 收入确认表 | P18: 开票明细表（可按开票时间汇总登记） | Z18: 收款明细
A19: 业主名称 | B19: 验工时间 | C19: 验工计价 | D19: 结算内容 | E19: 列账金额 | F19: 税率 | G19: 不含税金额(注意与账上保持一致） | H19: 税额(注意与账上保持一致） | I19: 列账凭证时间 | J19: 预付款转回 | K19: 罚没等其他金额 | L19: 业主名称 | M19: 凭证时间 | N19: 收入类型 | O19: 确认金额 | P19: 业主名称 | Q19: 凭证时间 | R19: 开票内容 | S19: 开票时间 | T19: 发票号码 | U19: 发票代码 | V19: 发票金额 | W19: 不含税金额 | X19: 税额 | Y19: 税率 | Z19: 单位名称 | AA19: 凭证日期 | AB19: 收款账户类型 | AC19: 收款账户名称 | AD19: 收款账户银行账号 | AE19: 收款金额 | AF19: 收款性质 | AG19: 收款备注
A48: 表四：分包方基础明细表 | C48: =SUM(C51:C75) -> 0 | E48: =SUM(E51:E75) -> 0 | G48: =SUM(G51:G75) -> 0 | H48: =SUM(H51:H75) -> 0 | J48: =SUM(J51:J75) -> 0 | K48: =SUM(K51:K75) -> 0 | R48: =SUM(R51:R75) -> 0 | S48: =SUM(S51:S75) -> 0 | T48: =SUM(T51:T75) -> 0 | AA48: =SUM(AA51:AA75) -> 0
A49: 分包（采购）结算明细表 | L49: 分包（采购）发票明细表开票明细表（可按开票时间汇总登记） | V49: 分包（采购）付款明细表
A50: 单位名称 | B50: 验工时间 | C50: 验工计价 | D50: 结算内容 | E50: 金额 | F50: 税率 | G50: 不含税金额(注意与账上保持一致） | H50: 税额(注意与账上保持一致） | I50: 列账凭证时间 | J50: 预付款转回 | K50: 罚没等其他金额 | L50: 单位名称 | M50: 凭证时间 | N50: 开票内容 | O50: 开票时间 | P50: 发票号码 | Q50: 发票代码 | R50: 发票金额 | S50: 不含税金额 | T50: 税额 | U50: 税率 | V50: 单位名称 | W50: 凭证日期 | X50: 付款账户类型 | Y50: 付款账户名称 | Z50: 付款账户银行账号 | AA50: 付款金额 | AB50: 付款性质 | AC50: 付款备注
A78: 表五：预缴税款情况统计表
A79: 凭证号/时间 | B79: 销售额 | C79: 扣除金额 | D79: 增值税 | E79: 城市维护建设税 | F79: 教育费附加 | G79: 地方教育费附加 | H79: 印花税 | I79: 企业所得税 | J79: 个人所得税 | K79: 其他税金 | L79: 合计 | M79: 备注
L80: =SUM(D80:K80) -> 0
L81: =SUM(D81:K81) -> 0
L82: =SUM(D82:K82) -> 0
L83: =SUM(D83:K83) -> 0
L84: =SUM(D84:K84) -> 0
L85: =SUM(D85:K85) -> 0
L86: =SUM(D86:K86) -> 0
L87: =SUM(D87:K87) -> 0
L88: =SUM(D88:K88) -> 0
L89: =SUM(D89:K89) -> 0
L90: =SUM(D90:K90) -> 0
L91: =SUM(D91:K91) -> 0
L92: =SUM(D92:K92) -> 0
A93: 合计 | B93: =SUM(B80:B92) -> 0 | C93: =SUM(C80:C92) -> 0 | D93: =SUM(D80:D92) -> 0 | E93: =SUM(E80:E92) -> 0 | F93: =SUM(F80:F92) -> 0 | G93: =SUM(G80:G92) -> 0 | H93: =SUM(H80:H92) -> 0 | I93: =SUM(I80:I92) -> 0 | ... M93: =SUM(M80:M92) -> 0
A95: 表六：间接费用、财务费用、附加费明细表
A96: 费用类型 | B96: 以前年度累计 | C96: 2023年 | D96: 2024年 | E96: 2025年 | F96: 2026年 | G96: 2027年 | H96: 2028年 | I96: 合计
A97: 间接费用 | I97: =SUM(B97:H97) -> 0
A98: 财务费用 | I98: =SUM(B98:H98) -> 0
A99: 其中：利息收入 | I99: =SUM(B99:H99) -> 0
A100: 手续费支出 | I100: =SUM(B100:H100) -> 0
A101: 营业外收入 | I101: =SUM(B101:H101) -> 0
A102: 营业外支出 | I102: =SUM(B102:H102) -> 0
A105: 表七：往来类科目明细表
A106: 项目名称 | B106: 应收账款 | C106: 合同负债 | D106: 长期应收款 | E106: 其他应收款 | F106: 应付账款 | G106: 预付账款 | H106: 长期应付款 | I106: 其他应付款 | J106: 待转销项税额 | K106: 专业分包成本 | L106: 直接材料费 | M106: 合同结算-收入结转 | N106: 合同结算-价款结算 | O106: 工程施工结转 | P106: 合同负债增值税 | Q106: 应付账款-预付账款增值税
A107: =M4 -> 来源于“共享系统”系统管理-权限管理-人员管理
A110: 表八：施工收入、成本计算表
A111: 2024年合同工程施工收入、成本计算表
A113: =L4 -> 来源于“共享系统”系统管理-权限管理-人员管理 | H113: 金额：元
A114: 序号 | B114: 名称 | C114: 期初数 | D114: 1季度 | E114: 2季度 | F114: 3季度 | G114: 4季度 | H114: 开累数
A115: 1 | B115: 工程施工预计总收入 | H115: =V11 -> 0
A116: 2 | B116: 工程施工预计总成本 | H116: =W11 -> 0
A117: 3 | B117: 工程施工预计合同毛利 | H117: =H115-H116 -> 0
A118: 4 | B118: 工程施工确认营业成本 | D118: 0 | H118: =C118+D118+E118+F118+G118 -> 0
A119: 5 | B119: 工程施工确认营业收入 | D119: 0 | H119: =C119+D119+E119+F119+G119 -> 0
A120: 6 | B120: 完工百分比 | C120: =ROUND(C118/H116,10) -> #DIV/0! | D120: =ROUND((C118+D118)/H116,10) -> #DIV/0! | E120: =ROUND((C118+D118+E118)/H116,10) -> #DIV/0! | F120: =ROUND((C118+D118+E118+F118)/H116,10) -> #DIV/0! | G120: =ROUND((C118+D118+E118+F118+G118)/H116,10) -> #DIV/0!
A121: 7 | B121: 确认营业毛利 | C121: =C119-C118 -> 0 | D121: =D119-D118 -> 0 | E121: =E119-E118 -> 0 | F121: =F119-F118 -> 0 | G121: =G119-G118 -> 0
A122: 8 | B122: 累计营业毛利 | C122: =C119-C118 -> 0 | D122: =C121+D121 -> 0 | E122: =C121+D121+E121 -> 0 | F122: =C121+D121+E121+F121 -> 0 | G122: =C121+D121+E121+F121+G121 -> 0
B124: 制表人： | G124: 项目部签字：
A126: 表九：数据校验
A127: 业主往来检验 | B127: 业主发票检验 | C127: 业主收入检验 | D127: 分包往来检验 | E127: 分包验工计价校验 | F127: 预缴税金检验 | G127: 两金指标
A128: =G11-T11-B107+C107-D107-E107-P107 -> 0 | B128: =H17-X17-J107+P107 -> 0 | C128: =SUMIFS($G$51:$G$76,$D$51:$D$76,C10)/H116*H115-O11 -> #DIV/0! | D128: =G12+G13-T12-T13-F107+G107-H107-I107+Q107 -> 0 | E128: =C11*(1-K4)-C12-C13 -> #DIV/0! | F128: =(SUMIFS($V$20:$V$46,$R$20:$R$46,C10)-SUMIFS($R$51:$R$76,$N$51:$N$76,C10))/1.09*0.02-D93 -> 0 | G128: =B107-C107+M107-N107 -> 0
A129: 应为零 | B129: 应为零 | C129: 应为零 | D129: 应为零 | E129: 应为零（正数为未验完，负数为超验） | F129: 应为零 | G129: 应尽量小，超过1000万预警

Sheet XX项目 (9)
A1: 表一：基础信息表
A2: 单位名称 | B2: 合同名称 | C2: 合同编号 | D2: 合同类型 | E2: 合同金额 | K2: 管理费比例 | L2: 共享系统部门名称 | M2: 共享系统项目名称 | N2: 合同签订单位 | O2: 项目管理单位 | P2: 业主财务联系人及电话 | Q2: 分包方财务联系人及电话 | R2: 项目部经理及电话 | S2: 合同开工日期 | T2: 预计竣工时间 | U2: 合同工期 | V2: 工程类型 | W2: 项目所在地（*省*市） | X2: 项目状态 | Y2: 工程进度款支付比例 | Z2: 勘察设计费支付比例 | AA2: 主管税务机构名称 | AB2: 税务管理员及电话 | AC2: 银行行号 | AD2: 开户行 | AE2: 银行行号 | AF2: 银行账户名称 | AG2: 银行账号 | AH2: 银行地址 | AI2: 银行联系人 | AJ2: 备注
E3: 勘察设计 | F3: 工程施工 | G3: 设备采购 | H3: 业主承担管理费 | I3: 技术服务等 | J3: 合计
A4: 来源于“共享系统”列账单位名称 | B4: 来源于“合同收款系统”或共享系统项目档案 | C4: 来源于“合同收款系统” | D4: 总包合同 | J4: =SUM(E4:I4) -> 0 | K4: =(F4-F5-F6)/F4 -> #DIV/0! | L4: 来源于“共享系统”系统管理-权限管理-人员管理 | M4: 来源于“共享系统”系统管理-权限管理-人员管理 | N4: 主合同编号中的单位 | O4: 实际管理单位
A5: 来源于“共享系统”列账单位名称 | B5: 来源于“合同收款系统”或共享系统项目档案 | C5: 来源于“合同收款系统” | D5: 分包合同 | J5: =SUM(E5:I5) -> 0
D6: 分包合同 | J6: =SUM(E6:I6) -> 0
A8: 表二：汇总表
A9: 单位名称 | B9: 累计验工计价 | H9: 累计开票 | N9: 累计收入或成本 | T9: 累计收款/付款 | U9: 银行账户余额 | V9: 工程施工预计总收入 | W9: 工程施工预计总成本
B10: 勘察设计 | C10: 工程施工 | D10: 设备采购 | E10: 业主承担管理费 | F10: 服务费 | G10: 合计 | H10: 勘察设计 | I10: 工程施工 | J10: 设备采购 | K10: 业主承担管理费 | L10: 服务费 | M10: 合计 | N10: 勘察设计 | O10: 工程施工 | P10: 设备采购 | Q10: 业主承担管理费 | R10: 服务费 | S10: 合计
B11: =SUMIFS($E$20:$E$46,$D$20:$D$46,$B$10,$A$20:$A$46,$A$11) -> 0 | C11: =SUMIFS($E$20:$E$46,$D$20:$D$46,C10,$A$20:$A$46,A11) -> 0 | D11: =SUMIFS($E$20:$E$46,$D$20:$D$46,D10,$A$20:$A$46,A11) -> 0 | E11: =SUMIFS($E$20:$E$46,$D$20:$D$46,E10,$A$20:$A$46,A11) -> 0 | F11: =SUMIFS($E$20:$E$46,$D$20:$D$46,F10,$A$20:$A$46,A11) -> 0 | G11: =SUM(B11:F11) -> 0 | H11: =SUMIFS($V$20:$V$46,$R$20:$R$46,$H$10,$P$20:$P$46,$A$11) -> 0 | I11: =SUMIFS($V$20:$V$46,$R$20:$R$46,I10,$P$20:$P$46,$A$11) -> 0 | J11: =SUMIFS($V$20:$V$46,$R$20:$R$46,$J$10,$P$20:$P$46,$A$11) -> 0 | K11: =SUMIFS($V$20:$V$46,$R$20:$R$46,$K$10,$P$20:$P$46,$A$11) -> 0 | L11: =SUMIFS($V$20:$V$46,$R$20:$R$46,$L$10,$P$20:$P$46,$A$11) -> 0 | M11: =SUM(H11:L11) -> 0 | N11: =SUMIFS($O$20:$O$45,$N$20:$N$45,N10,$L$20:$L$45,A11) -> 0 | O11: =SUMIFS($O$20:$O$45,$N$20:$N$45,O10,$L$20:$L$45,A11) -> 0 | P11: =SUMIFS($O$20:$O$45,$N$20:$N$45,P10,$L$20:$L$45,A11) -> 0 | Q11: =SUMIFS($O$20:$O$45,$N$20:$N$45,Q10,$L$20:$L$45,A11) -> 0 | R11: =SUMIFS($O$20:$O$45,$N$20:$N$45,R10,$L$20:$L$45,A11) -> 0 | S11: =SUM(N11:R11) -> 0 | T11: =SUMIF($Z$20:$Z$46,A11,$AE$20:$AE$46) -> 0 | V11: =F4/1.09 -> 0 | W11: =(F5+F6)/1.09 -> 0
B12: =SUMIFS($E$51:$E$76,$D$51:$D$76,B10,$A$51:$A$76,A12) -> 0 | C12: =SUMIFS($E$51:$E$76,$D$51:$D$76,C10,$A$51:$A$76,A12) -> 0 | D12: =SUMIFS($E$51:$E$76,$D$51:$D$76,D10,$A$51:$A$76,A12) -> 0 | E12: =SUMIFS($E$51:$E$76,$D$51:$D$76,E10,$A$51:$A$76,A12) -> 0 | F12: =SUMIFS($E$51:$E$76,$D$51:$D$76,F10,$A$51:$A$76,A12) -> 0 | G12: =SUM(B12:F12) -> 0 | H12: =SUMIFS($R$51:$R$76,$N$51:$N$76,H10,$L$51:$L$76,A12) -> 0 | I12: =SUMIFS($R$51:$R$76,$N$51:$N$76,I10,$L$51:$L$76,A12) -> 0 | J12: =SUMIFS($R$51:$R$76,$N$51:$N$76,J10,$L$51:$L$76,A12) -> 0 | K12: =SUMIFS($R$51:$R$76,$N$51:$N$76,K10,$L$51:$L$76,A12) -> 0 | L12: =SUMIFS($R$51:$R$76,$N$51:$N$76,L10,$L$51:$L$76,A12) -> 0 | M12: =SUM(H12:L12) -> 0 | N12: =SUMIFS($G$51:$G$76,$D$51:$D$76,N10,$A$51:$A$76,A12) -> 0 | O12: =SUMIFS($G$51:$G$76,$D$51:$D$76,$O$10,$A$51:$A$76,A12) -> 0 | P12: =SUMIFS($G$51:$G$76,$D$51:$D$76,$P$10,$A$51:$A$76,A12) -> 0 | Q12: =SUMIFS($G$51:$G$76,$D$51:$D$76,$Q$10,$A$51:$A$76,A12) -> 0 | R12: =SUMIFS($G$51:$G$76,$D$51:$D$76,$R$10,$A$51:$A$76,A12) -> 0 | S12: =SUM(N12:R12) -> 0 | T12: =SUMIF($V$51:$V$76,A12,$AA$51:$AA$76) -> 0
B13: =SUMIFS($E$51:$E$76,$D$51:$D$76,B10,$A$51:$A$76,A13) -> 0 | C13: =SUMIFS($E$51:$E$76,$D$51:$D$76,C10,$A$51:$A$76,A13) -> 0 | D13: =SUMIFS($E$51:$E$76,$D$51:$D$76,D10,$A$51:$A$76,A13) -> 0 | E13: =SUMIFS($E$51:$E$76,$D$51:$D$76,E10,$A$51:$A$76,A13) -> 0 | F13: =SUMIFS($E$51:$E$76,$D$51:$D$76,F10,$A$51:$A$76,A13) -> 0 | G13: =SUM(B13:F13) -> 0 | H13: =SUMIFS($R$51:$R$76,$N$51:$N$76,H10,$L$51:$L$76,A13) -> 0 | I13: =SUMIFS($R$51:$R$76,$N$51:$N$76,I10,$L$51:$L$76,A13) -> 0 | J13: =SUMIFS($R$51:$R$76,$N$51:$N$76,J10,$L$51:$L$76,A13) -> 0 | K13: =SUMIFS($R$51:$R$76,$N$51:$N$76,K10,$L$51:$L$76,A13) -> 0 | L13: =SUMIFS($R$51:$R$76,$N$51:$N$76,L10,$L$51:$L$76,A13) -> 0 | M13: =SUM(H13:L13) -> 0 | N13: =SUMIFS($G$51:$G$76,$D$51:$D$76,$N$10,$A$51:$A$76,A13) -> 0 | O13: =SUMIFS($G$51:$G$76,$D$51:$D$76,$O$10,$A$51:$A$76,A13) -> 0 | P13: =SUMIFS($G$51:$G$76,$D$51:$D$76,$P$10,$A$51:$A$76,A13) -> 0 | Q13: =SUMIFS($G$51:$G$76,$D$51:$D$76,$Q$10,$A$51:$A$76,A13) -> 0 | R13: =SUMIFS($G$51:$G$76,$D$51:$D$76,$R$10,$A$51:$A$76,A13) -> 0 | S13: =SUM(N13:R13) -> 0 | T13: =SUMIF($V$51:$V$76,A13,$AA$51:$AA$76) -> 0
G14: =G11-C17 -> 0 | M14: =M11-V17 -> 0 | S14: =S11-O17 -> 0 | T14: =T11-AE17 -> 0
G15: =G12+G13-C48 -> 0 | M15: =M12+M13-R48 -> 0 | S15: =S12+S13-G48 -> 0 | T15: =T12+T13-AA48 -> 0
A17: 表三：业主基础明细表 | C17: =SUM(C20:C45) -> 0 | E17: =SUM(E20:E45) -> 0 | G17: =SUM(G20:G45) -> 0 | H17: =SUM(H20:H45) -> 0 | O17: =SUM(O20:O45) -> 0 | V17: =SUM(V20:V45) -> 0 | W17: =SUM(W20:W45) -> 0 | X17: =SUM(X20:X45) -> 0 | AE17: =SUM(AE20:AE45) -> 0
A18: 业主结算明细 | L18: 收入确认表 | P18: 开票明细表（可按开票时间汇总登记） | Z18: 收款明细
A19: 业主名称 | B19: 验工时间 | C19: 验工计价 | D19: 结算内容 | E19: 列账金额 | F19: 税率 | G19: 不含税金额(注意与账上保持一致） | H19: 税额(注意与账上保持一致） | I19: 列账凭证时间 | J19: 预付款转回 | K19: 罚没等其他金额 | L19: 业主名称 | M19: 凭证时间 | N19: 收入类型 | O19: 确认金额 | P19: 业主名称 | Q19: 凭证时间 | R19: 开票内容 | S19: 开票时间 | T19: 发票号码 | U19: 发票代码 | V19: 发票金额 | W19: 不含税金额 | X19: 税额 | Y19: 税率 | Z19: 单位名称 | AA19: 凭证日期 | AB19: 收款账户类型 | AC19: 收款账户名称 | AD19: 收款账户银行账号 | AE19: 收款金额 | AF19: 收款性质 | AG19: 收款备注
A48: 表四：分包方基础明细表 | C48: =SUM(C51:C75) -> 0 | E48: =SUM(E51:E75) -> 0 | G48: =SUM(G51:G75) -> 0 | H48: =SUM(H51:H75) -> 0 | J48: =SUM(J51:J75) -> 0 | K48: =SUM(K51:K75) -> 0 | R48: =SUM(R51:R75) -> 0 | S48: =SUM(S51:S75) -> 0 | T48: =SUM(T51:T75) -> 0 | AA48: =SUM(AA51:AA75) -> 0
A49: 分包（采购）结算明细表 | L49: 分包（采购）发票明细表开票明细表（可按开票时间汇总登记） | V49: 分包（采购）付款明细表
A50: 单位名称 | B50: 验工时间 | C50: 验工计价 | D50: 结算内容 | E50: 金额 | F50: 税率 | G50: 不含税金额(注意与账上保持一致） | H50: 税额(注意与账上保持一致） | I50: 列账凭证时间 | J50: 预付款转回 | K50: 罚没等其他金额 | L50: 单位名称 | M50: 凭证时间 | N50: 开票内容 | O50: 开票时间 | P50: 发票号码 | Q50: 发票代码 | R50: 发票金额 | S50: 不含税金额 | T50: 税额 | U50: 税率 | V50: 单位名称 | W50: 凭证日期 | X50: 付款账户类型 | Y50: 付款账户名称 | Z50: 付款账户银行账号 | AA50: 付款金额 | AB50: 付款性质 | AC50: 付款备注
A78: 表五：预缴税款情况统计表
A79: 凭证号/时间 | B79: 销售额 | C79: 扣除金额 | D79: 增值税 | E79: 城市维护建设税 | F79: 教育费附加 | G79: 地方教育费附加 | H79: 印花税 | I79: 企业所得税 | J79: 个人所得税 | K79: 其他税金 | L79: 合计 | M79: 备注
L80: =SUM(D80:K80) -> 0
L81: =SUM(D81:K81) -> 0
L82: =SUM(D82:K82) -> 0
L83: =SUM(D83:K83) -> 0
L84: =SUM(D84:K84) -> 0
L85: =SUM(D85:K85) -> 0
L86: =SUM(D86:K86) -> 0
L87: =SUM(D87:K87) -> 0
L88: =SUM(D88:K88) -> 0
L89: =SUM(D89:K89) -> 0
L90: =SUM(D90:K90) -> 0
L91: =SUM(D91:K91) -> 0
L92: =SUM(D92:K92) -> 0
A93: 合计 | B93: =SUM(B80:B92) -> 0 | C93: =SUM(C80:C92) -> 0 | D93: =SUM(D80:D92) -> 0 | E93: =SUM(E80:E92) -> 0 | F93: =SUM(F80:F92) -> 0 | G93: =SUM(G80:G92) -> 0 | H93: =SUM(H80:H92) -> 0 | I93: =SUM(I80:I92) -> 0 | ... M93: =SUM(M80:M92) -> 0
A95: 表六：间接费用、财务费用、附加费明细表
A96: 费用类型 | B96: 以前年度累计 | C96: 2023年 | D96: 2024年 | E96: 2025年 | F96: 2026年 | G96: 2027年 | H96: 2028年 | I96: 合计
A97: 间接费用 | I97: =SUM(B97:H97) -> 0
A98: 财务费用 | I98: =SUM(B98:H98) -> 0
A99: 其中：利息收入 | I99: =SUM(B99:H99) -> 0
A100: 手续费支出 | I100: =SUM(B100:H100) -> 0
A101: 营业外收入 | I101: =SUM(B101:H101) -> 0
A102: 营业外支出 | I102: =SUM(B102:H102) -> 0
A105: 表七：往来类科目明细表
A106: 项目名称 | B106: 应收账款 | C106: 合同负债 | D106: 长期应收款 | E106: 其他应收款 | F106: 应付账款 | G106: 预付账款 | H106: 长期应付款 | I106: 其他应付款 | J106: 待转销项税额 | K106: 专业分包成本 | L106: 直接材料费 | M106: 合同结算-收入结转 | N106: 合同结算-价款结算 | O106: 工程施工结转 | P106: 合同负债增值税 | Q106: 应付账款-预付账款增值税
A107: =M4 -> 来源于“共享系统”系统管理-权限管理-人员管理
A110: 表八：施工收入、成本计算表
A111: 2024年合同工程施工收入、成本计算表
A113: =L4 -> 来源于“共享系统”系统管理-权限管理-人员管理 | H113: 金额：元
A114: 序号 | B114: 名称 | C114: 期初数 | D114: 1季度 | E114: 2季度 | F114: 3季度 | G114: 4季度 | H114: 开累数
A115: 1 | B115: 工程施工预计总收入 | H115: =V11 -> 0
A116: 2 | B116: 工程施工预计总成本 | H116: =W11 -> 0
A117: 3 | B117: 工程施工预计合同毛利 | H117: =H115-H116 -> 0
A118: 4 | B118: 工程施工确认营业成本 | D118: 0 | H118: =C118+D118+E118+F118+G118 -> 0
A119: 5 | B119: 工程施工确认营业收入 | D119: 0 | H119: =C119+D119+E119+F119+G119 -> 0
A120: 6 | B120: 完工百分比 | C120: =ROUND(C118/H116,10) -> #DIV/0! | D120: =ROUND((C118+D118)/H116,10) -> #DIV/0! | E120: =ROUND((C118+D118+E118)/H116,10) -> #DIV/0! | F120: =ROUND((C118+D118+E118+F118)/H116,10) -> #DIV/0! | G120: =ROUND((C118+D118+E118+F118+G118)/H116,10) -> #DIV/0!
A121: 7 | B121: 确认营业毛利 | C121: =C119-C118 -> 0 | D121: =D119-D118 -> 0 | E121: =E119-E118 -> 0 | F121: =F119-F118 -> 0 | G121: =G119-G118 -> 0
A122: 8 | B122: 累计营业毛利 | C122: =C119-C118 -> 0 | D122: =C121+D121 -> 0 | E122: =C121+D121+E121 -> 0 | F122: =C121+D121+E121+F121 -> 0 | G122: =C121+D121+E121+F121+G121 -> 0
B124: 制表人： | G124: 项目部签字：
A126: 表九：数据校验
A127: 业主往来检验 | B127: 业主发票检验 | C127: 业主收入检验 | D127: 分包往来检验 | E127: 分包验工计价校验 | F127: 预缴税金检验 | G127: 两金指标
A128: =G11-T11-B107+C107-D107-E107+P107 -> 0 | B128: =H17-X17-J107+P107 -> 0 | C128: =SUMIFS($G$51:$G$76,$D$51:$D$76,C10)/H116*H115-O11 -> #DIV/0! | D128: =G12+G13-T12-T13-F107+G107-H107-I107+Q107 -> 0 | E128: =C11*(1-K4)-C12-C13 -> #DIV/0! | F128: =(SUMIFS($V$20:$V$46,$R$20:$R$46,C10)-SUMIFS($R$51:$R$76,$N$51:$N$76,C10))/1.09*0.02-D93 -> 0 | G128: =B107-C107+M107-N107 -> 0
A129: 应为零 | B129: 应为零 | C129: 应为零 | D129: 应为零 | E129: 应为零（正数为未验完，负数为超验） | F129: 应为零 | G129: 应尽量小，超过1000万预警

Sheet XX项目 (10)
A1: 表一：基础信息表
A2: 单位名称 | B2: 合同名称 | C2: 合同编号 | D2: 合同类型 | E2: 合同金额 | K2: 管理费比例 | L2: 共享系统部门名称 | M2: 共享系统项目名称 | N2: 合同签订单位 | O2: 项目管理单位 | P2: 业主财务联系人及电话 | Q2: 分包方财务联系人及电话 | R2: 项目部经理及电话 | S2: 合同开工日期 | T2: 预计竣工时间 | U2: 合同工期 | V2: 工程类型 | W2: 项目所在地（*省*市） | X2: 项目状态 | Y2: 工程进度款支付比例 | Z2: 勘察设计费支付比例 | AA2: 主管税务机构名称 | AB2: 税务管理员及电话 | AC2: 银行行号 | AD2: 开户行 | AE2: 银行行号 | AF2: 银行账户名称 | AG2: 银行账号 | AH2: 银行地址 | AI2: 银行联系人 | AJ2: 备注
E3: 勘察设计 | F3: 工程施工 | G3: 设备采购 | H3: 业主承担管理费 | I3: 技术服务等 | J3: 合计
A4: 来源于“共享系统”列账单位名称 | B4: 来源于“合同收款系统”或共享系统项目档案 | C4: 来源于“合同收款系统” | D4: 总包合同 | J4: =SUM(E4:I4) -> 0 | K4: =(F4-F5-F6)/F4 -> #DIV/0! | L4: 来源于“共享系统”系统管理-权限管理-人员管理 | M4: 来源于“共享系统”系统管理-权限管理-人员管理 | N4: 主合同编号中的单位 | O4: 实际管理单位
A5: 来源于“共享系统”列账单位名称 | B5: 来源于“合同收款系统”或共享系统项目档案 | C5: 来源于“合同收款系统” | D5: 分包合同 | J5: =SUM(E5:I5) -> 0
D6: 分包合同 | J6: =SUM(E6:I6) -> 0
A8: 表二：汇总表
A9: 单位名称 | B9: 累计验工计价 | H9: 累计开票 | N9: 累计收入或成本 | T9: 累计收款/付款 | U9: 银行账户余额 | V9: 工程施工预计总收入 | W9: 工程施工预计总成本
B10: 勘察设计 | C10: 工程施工 | D10: 设备采购 | E10: 业主承担管理费 | F10: 服务费 | G10: 合计 | H10: 勘察设计 | I10: 工程施工 | J10: 设备采购 | K10: 业主承担管理费 | L10: 服务费 | M10: 合计 | N10: 勘察设计 | O10: 工程施工 | P10: 设备采购 | Q10: 业主承担管理费 | R10: 服务费 | S10: 合计
B11: =SUMIFS($E$20:$E$46,$D$20:$D$46,$B$10,$A$20:$A$46,$A$11) -> 0 | C11: =SUMIFS($E$20:$E$46,$D$20:$D$46,C10,$A$20:$A$46,A11) -> 0 | D11: =SUMIFS($E$20:$E$46,$D$20:$D$46,D10,$A$20:$A$46,A11) -> 0 | E11: =SUMIFS($E$20:$E$46,$D$20:$D$46,E10,$A$20:$A$46,A11) -> 0 | F11: =SUMIFS($E$20:$E$46,$D$20:$D$46,F10,$A$20:$A$46,A11) -> 0 | G11: =SUM(B11:F11) -> 0 | H11: =SUMIFS($V$20:$V$46,$R$20:$R$46,$H$10,$P$20:$P$46,$A$11) -> 0 | I11: =SUMIFS($V$20:$V$46,$R$20:$R$46,I10,$P$20:$P$46,$A$11) -> 0 | J11: =SUMIFS($V$20:$V$46,$R$20:$R$46,$J$10,$P$20:$P$46,$A$11) -> 0 | K11: =SUMIFS($V$20:$V$46,$R$20:$R$46,$K$10,$P$20:$P$46,$A$11) -> 0 | L11: =SUMIFS($V$20:$V$46,$R$20:$R$46,$L$10,$P$20:$P$46,$A$11) -> 0 | M11: =SUM(H11:L11) -> 0 | N11: =SUMIFS($O$20:$O$45,$N$20:$N$45,N10,$L$20:$L$45,A11) -> 0 | O11: =SUMIFS($O$20:$O$45,$N$20:$N$45,O10,$L$20:$L$45,A11) -> 0 | P11: =SUMIFS($O$20:$O$45,$N$20:$N$45,P10,$L$20:$L$45,A11) -> 0 | Q11: =SUMIFS($O$20:$O$45,$N$20:$N$45,Q10,$L$20:$L$45,A11) -> 0 | R11: =SUMIFS($O$20:$O$45,$N$20:$N$45,R10,$L$20:$L$45,A11) -> 0 | S11: =SUM(N11:R11) -> 0 | T11: =SUMIF($Z$20:$Z$46,A11,$AE$20:$AE$46) -> 0 | V11: =F4/1.09 -> 0 | W11: =(F5+F6)/1.09 -> 0
B12: =SUMIFS($E$51:$E$76,$D$51:$D$76,B10,$A$51:$A$76,A12) -> 0 | C12: =SUMIFS($E$51:$E$76,$D$51:$D$76,C10,$A$51:$A$76,A12) -> 0 | D12: =SUMIFS($E$51:$E$76,$D$51:$D$76,D10,$A$51:$A$76,A12) -> 0 | E12: =SUMIFS($E$51:$E$76,$D$51:$D$76,E10,$A$51:$A$76,A12) -> 0 | F12: =SUMIFS($E$51:$E$76,$D$51:$D$76,F10,$A$51:$A$76,A12) -> 0 | G12: =SUM(B12:F12) -> 0 | H12: =SUMIFS($R$51:$R$76,$N$51:$N$76,H10,$L$51:$L$76,A12) -> 0 | I12: =SUMIFS($R$51:$R$76,$N$51:$N$76,I10,$L$51:$L$76,A12) -> 0 | J12: =SUMIFS($R$51:$R$76,$N$51:$N$76,J10,$L$51:$L$76,A12) -> 0 | K12: =SUMIFS($R$51:$R$76,$N$51:$N$76,K10,$L$51:$L$76,A12) -> 0 | L12: =SUMIFS($R$51:$R$76,$N$51:$N$76,L10,$L$51:$L$76,A12) -> 0 | M12: =SUM(H12:L12) -> 0 | N12: =SUMIFS($G$51:$G$76,$D$51:$D$76,N10,$A$51:$A$76,A12) -> 0 | O12: =SUMIFS($G$51:$G$76,$D$51:$D$76,$O$10,$A$51:$A$76,A12) -> 0 | P12: =SUMIFS($G$51:$G$76,$D$51:$D$76,$P$10,$A$51:$A$76,A12) -> 0 | Q12: =SUMIFS($G$51:$G$76,$D$51:$D$76,$Q$10,$A$51:$A$76,A12) -> 0 | R12: =SUMIFS($G$51:$G$76,$D$51:$D$76,$R$10,$A$51:$A$76,A12) -> 0 | S12: =SUM(N12:R12) -> 0 | T12: =SUMIF($V$51:$V$76,A12,$AA$51:$AA$76) -> 0
B13: =SUMIFS($E$51:$E$76,$D$51:$D$76,B10,$A$51:$A$76,A13) -> 0 | C13: =SUMIFS($E$51:$E$76,$D$51:$D$76,C10,$A$51:$A$76,A13) -> 0 | D13: =SUMIFS($E$51:$E$76,$D$51:$D$76,D10,$A$51:$A$76,A13) -> 0 | E13: =SUMIFS($E$51:$E$76,$D$51:$D$76,E10,$A$51:$A$76,A13) -> 0 | F13: =SUMIFS($E$51:$E$76,$D$51:$D$76,F10,$A$51:$A$76,A13) -> 0 | G13: =SUM(B13:F13) -> 0 | H13: =SUMIFS($R$51:$R$76,$N$51:$N$76,H10,$L$51:$L$76,A13) -> 0 | I13: =SUMIFS($R$51:$R$76,$N$51:$N$76,I10,$L$51:$L$76,A13) -> 0 | J13: =SUMIFS($R$51:$R$76,$N$51:$N$76,J10,$L$51:$L$76,A13) -> 0 | K13: =SUMIFS($R$51:$R$76,$N$51:$N$76,K10,$L$51:$L$76,A13) -> 0 | L13: =SUMIFS($R$51:$R$76,$N$51:$N$76,L10,$L$51:$L$76,A13) -> 0 | M13: =SUM(H13:L13) -> 0 | N13: =SUMIFS($G$51:$G$76,$D$51:$D$76,$N$10,$A$51:$A$76,A13) -> 0 | O13: =SUMIFS($G$51:$G$76,$D$51:$D$76,$O$10,$A$51:$A$76,A13) -> 0 | P13: =SUMIFS($G$51:$G$76,$D$51:$D$76,$P$10,$A$51:$A$76,A13) -> 0 | Q13: =SUMIFS($G$51:$G$76,$D$51:$D$76,$Q$10,$A$51:$A$76,A13) -> 0 | R13: =SUMIFS($G$51:$G$76,$D$51:$D$76,$R$10,$A$51:$A$76,A13) -> 0 | S13: =SUM(N13:R13) -> 0 | T13: =SUMIF($V$51:$V$76,A13,$AA$51:$AA$76) -> 0
G14: =G11-C17 -> 0 | M14: =M11-V17 -> 0 | S14: =S11-O17 -> 0 | T14: =T11-AE17 -> 0
G15: =G12+G13-C48 -> 0 | M15: =M12+M13-R48 -> 0 | S15: =S12+S13-G48 -> 0 | T15: =T12+T13-AA48 -> 0
A17: 表三：业主基础明细表 | C17: =SUM(C20:C45) -> 0 | E17: =SUM(E20:E45) -> 0 | G17: =SUM(G20:G45) -> 0 | H17: =SUM(H20:H45) -> 0 | O17: =SUM(O20:O45) -> 0 | V17: =SUM(V20:V45) -> 0 | W17: =SUM(W20:W45) -> 0 | X17: =SUM(X20:X45) -> 0 | AE17: =SUM(AE20:AE45) -> 0
A18: 业主结算明细 | L18: 收入确认表 | P18: 开票明细表（可按开票时间汇总登记） | Z18: 收款明细
A19: 业主名称 | B19: 验工时间 | C19: 验工计价 | D19: 结算内容 | E19: 列账金额 | F19: 税率 | G19: 不含税金额(注意与账上保持一致） | H19: 税额(注意与账上保持一致） | I19: 列账凭证时间 | J19: 预付款转回 | K19: 罚没等其他金额 | L19: 业主名称 | M19: 凭证时间 | N19: 收入类型 | O19: 确认金额 | P19: 业主名称 | Q19: 凭证时间 | R19: 开票内容 | S19: 开票时间 | T19: 发票号码 | U19: 发票代码 | V19: 发票金额 | W19: 不含税金额 | X19: 税额 | Y19: 税率 | Z19: 单位名称 | AA19: 凭证日期 | AB19: 收款账户类型 | AC19: 收款账户名称 | AD19: 收款账户银行账号 | AE19: 收款金额 | AF19: 收款性质 | AG19: 收款备注
A48: 表四：分包方基础明细表 | C48: =SUM(C51:C75) -> 0 | E48: =SUM(E51:E75) -> 0 | G48: =SUM(G51:G75) -> 0 | H48: =SUM(H51:H75) -> 0 | J48: =SUM(J51:J75) -> 0 | K48: =SUM(K51:K75) -> 0 | R48: =SUM(R51:R75) -> 0 | S48: =SUM(S51:S75) -> 0 | T48: =SUM(T51:T75) -> 0 | AA48: =SUM(AA51:AA75) -> 0
A49: 分包（采购）结算明细表 | L49: 分包（采购）发票明细表开票明细表（可按开票时间汇总登记） | V49: 分包（采购）付款明细表
A50: 单位名称 | B50: 验工时间 | C50: 验工计价 | D50: 结算内容 | E50: 金额 | F50: 税率 | G50: 不含税金额(注意与账上保持一致） | H50: 税额(注意与账上保持一致） | I50: 列账凭证时间 | J50: 预付款转回 | K50: 罚没等其他金额 | L50: 单位名称 | M50: 凭证时间 | N50: 开票内容 | O50: 开票时间 | P50: 发票号码 | Q50: 发票代码 | R50: 发票金额 | S50: 不含税金额 | T50: 税额 | U50: 税率 | V50: 单位名称 | W50: 凭证日期 | X50: 付款账户类型 | Y50: 付款账户名称 | Z50: 付款账户银行账号 | AA50: 付款金额 | AB50: 付款性质 | AC50: 付款备注
A78: 表五：预缴税款情况统计表
A79: 凭证号/时间 | B79: 销售额 | C79: 扣除金额 | D79: 增值税 | E79: 城市维护建设税 | F79: 教育费附加 | G79: 地方教育费附加 | H79: 印花税 | I79: 企业所得税 | J79: 个人所得税 | K79: 其他税金 | L79: 合计 | M79: 备注
L80: =SUM(D80:K80) -> 0
L81: =SUM(D81:K81) -> 0
L82: =SUM(D82:K82) -> 0
L83: =SUM(D83:K83) -> 0
L84: =SUM(D84:K84) -> 0
L85: =SUM(D85:K85) -> 0
L86: =SUM(D86:K86) -> 0
L87: =SUM(D87:K87) -> 0
L88: =SUM(D88:K88) -> 0
L89: =SUM(D89:K89) -> 0
L90: =SUM(D90:K90) -> 0
L91: =SUM(D91:K91) -> 0
L92: =SUM(D92:K92) -> 0
A93: 合计 | B93: =SUM(B80:B92) -> 0 | C93: =SUM(C80:C92) -> 0 | D93: =SUM(D80:D92) -> 0 | E93: =SUM(E80:E92) -> 0 | F93: =SUM(F80:F92) -> 0 | G93: =SUM(G80:G92) -> 0 | H93: =SUM(H80:H92) -> 0 | I93: =SUM(I80:I92) -> 0 | ... M93: =SUM(M80:M92) -> 0
A95: 表六：间接费用、财务费用、附加费明细表
A96: 费用类型 | B96: 以前年度累计 | C96: 2023年 | D96: 2024年 | E96: 2025年 | F96: 2026年 | G96: 2027年 | H96: 2028年 | I96: 合计
A97: 间接费用 | I97: =SUM(B97:H97) -> 0
A98: 财务费用 | I98: =SUM(B98:H98) -> 0
A99: 其中：利息收入 | I99: =SUM(B99:H99) -> 0
A100: 手续费支出 | I100: =SUM(B100:H100) -> 0
A101: 营业外收入 | I101: =SUM(B101:H101) -> 0
A102: 营业外支出 | I102: =SUM(B102:H102) -> 0
A105: 表七：往来类科目明细表
A106: 项目名称 | B106: 应收账款 | C106: 合同负债 | D106: 长期应收款 | E106: 其他应收款 | F106: 应付账款 | G106: 预付账款 | H106: 长期应付款 | I106: 其他应付款 | J106: 待转销项税额 | K106: 专业分包成本 | L106: 直接材料费 | M106: 合同结算-收入结转 | N106: 合同结算-价款结算 | O106: 工程施工结转 | P106: 合同负债增值税 | Q106: 应付账款-预付账款增值税
A107: =M4 -> 来源于“共享系统”系统管理-权限管理-人员管理
A110: 表八：施工收入、成本计算表
A111: 2024年合同工程施工收入、成本计算表
A113: =L4 -> 来源于“共享系统”系统管理-权限管理-人员管理 | H113: 金额：元
A114: 序号 | B114: 名称 | C114: 期初数 | D114: 1季度 | E114: 2季度 | F114: 3季度 | G114: 4季度 | H114: 开累数
A115: 1 | B115: 工程施工预计总收入 | H115: =V11 -> 0
A116: 2 | B116: 工程施工预计总成本 | H116: =W11 -> 0
A117: 3 | B117: 工程施工预计合同毛利 | H117: =H115-H116 -> 0
A118: 4 | B118: 工程施工确认营业成本 | D118: 0 | H118: =C118+D118+E118+F118+G118 -> 0
A119: 5 | B119: 工程施工确认营业收入 | D119: 0 | H119: =C119+D119+E119+F119+G119 -> 0
A120: 6 | B120: 完工百分比 | C120: =ROUND(C118/H116,10) -> #DIV/0! | D120: =ROUND((C118+D118)/H116,10) -> #DIV/0! | E120: =ROUND((C118+D118+E118)/H116,10) -> #DIV/0! | F120: =ROUND((C118+D118+E118+F118)/H116,10) -> #DIV/0! | G120: =ROUND((C118+D118+E118+F118+G118)/H116,10) -> #DIV/0!
A121: 7 | B121: 确认营业毛利 | C121: =C119-C118 -> 0 | D121: =D119-D118 -> 0 | E121: =E119-E118 -> 0 | F121: =F119-F118 -> 0 | G121: =G119-G118 -> 0
A122: 8 | B122: 累计营业毛利 | C122: =C119-C118 -> 0 | D122: =C121+D121 -> 0 | E122: =C121+D121+E121 -> 0 | F122: =C121+D121+E121+F121 -> 0 | G122: =C121+D121+E121+F121+G121 -> 0
B124: 制表人： | G124: 项目部签字：
A126: 表九：数据校验
A127: 业主往来检验 | B127: 业主发票检验 | C127: 业主收入检验 | D127: 分包往来检验 | E127: 分包验工计价校验 | F127: 预缴税金检验 | G127: 两金指标
A128: =G11-T11-B107+C107-D107-E107-P107 -> 0 | B128: =H17-X17-J107+P107 -> 0 | C128: =SUMIFS($G$51:$G$76,$D$51:$D$76,C10)/H116*H115-O11 -> #DIV/0! | D128: =G12+G13-T12-T13-F107+G107-H107-I107+Q107 -> 0 | E128: =C11*(1-K4)-C12-C13 -> #DIV/0! | F128: =(SUMIFS($V$20:$V$46,$R$20:$R$46,C10)-SUMIFS($R$51:$R$76,$N$51:$N$76,C10))/1.09*0.02-D93 -> 0 | G128: =B107-C107+M107-N107 -> 0
A129: 应为零 | B129: 应为零 | C129: 应为零 | D129: 应为零 | E129: 应为零（正数为未验完，负数为超验） | F129: 应为零 | G129: 应尽量小，超过1000万预警
